Workbook

Sheet Cover
D14: Typ dokumentu | F14: Plik z danymi roku bazowego
D18: Cel powstania | F18: Wprowadzenie topologii i danych dla sektora rolnictwa
D22: Data powstania | F22: 45173
D25: Ostatnia aktualizacja | F25: 45915
D28: Autor(zy) | F28: Artur Wyrwa
F29: Patrycja Rzeszut
F30: Maciej Raczyński
F31: Janusz Zyśk
D33: Osoba kontaktowa | F33: Artur Wyrwa
F34: awyrwa@agh.edu.pl

Sheet Metadane
D4: Metadane
D6: Wersja modelu wykorzystująca plik: TIMES-PL
D8: Arkusz | E8: Moduł | F8: Uwagi
D9: AGR_Comm | E9: Bazowy | F9: Zaktualizowano listę dóbr
D10: AGR_Proc | E10: Bazowy | F10: Zaktualizowano listę procesów
D11: SECTF | E11: Bazowy | F11: Zaktualizowano listę procesów i dóbr
D12: AGR_LIV | E12: TIMES-PL Rozszerzenie
D13: AGR_LAND | E13: TIMES-PL Rozszerzenie
D14: AGR_BIOG | E14: TIMES-PL Rozszerzenie
D15: AGR_CHP | E15: Bazowy
D16: DIV | E16: TIMES-PL Rozszerzenie
D17: AGR_FEC | E17: Bazowy
D18: EMI | E18: Bazowy | F18: Zaktualizowano listę procesów i dóbr

Sheet AGR_Comm
B2: Definicja dóbr | Commodity Definition
B4: ~FI_Comm
B5: Csets | C5: Region | D5: CommName | E5: CommDesc | F5: Unit | G5: LimType | H5: CTSLvl | I5: PeakTS | J5: Ctype
B6: * Przynależność do zbioru dóbr | C6: Region | D6: Nazwa dobra | E6: Opis dobra | F6: Jednostka | G6: Znak w równaniu bilansu | H6: Poziom podokresów | I6: Monitorowanie szczytu | J6: Wskaźnik energii elektrycznej
B7: NRG | C7: PL | D7: AGR_HC | E7: Hard Coal | F7: PJ | H7: ANNUAL
B8: NRG | C8: PL | D8: AGR_BC | E8: Brown Coal | F8: PJ | H8: ANNUAL
B9: NRG | C9: PL | D9: AGR_OIL_GSL | E9: Gasoline | F9: PJ | H9: ANNUAL
B10: NRG | C10: PL | D10: AGR_OIL_DSL | E10: Diesel | F10: PJ | H10: ANNUAL
B11: NRG | C11: PL | D11: AGR_OIL_LPG | E11: LPG | F11: PJ | H11: ANNUAL
B12: NRG | C12: PL | D12: AGR_OIL_FUE | E12: Fuel Oil | F12: PJ | H12: ANNUAL
B13: NRG | C13: PL | D13: AGR_NAT_GAS | E13: Natural Gas | F13: PJ | H13: ANNUAL
B14: NRG | C14: PL | D14: PRI_BIOG_AGR | E14: Biogas AGR | F14: PJ | H14: ANNUAL
B15: NRG | C15: PL | D15: PRI_BIO_CH4_AGR | E15: Biometan AGR | F15: PJ | H15: ANNUAL
B16: NRG | C16: PL | D16: AGR_BIOG | E16: Biogas AGR | F16: PJ | H16: ANNUAL
B17: NRG | C17: PL | D17: AGR_BIOM | E17: Biomass | F17: PJ | H17: ANNUAL
B18: NRG | C18: PL | D18: AGR_RDF | E18: RDF | F18: PJ | H18: ANNUAL
... B22: DEM | C22: PL | D22: AGR_DEM | E22: Agriculture Demand | F22: IPI | H22: ANNUAL
B23: ENV | C23: PL | D23: AGR_CO2 | E23: Carbon Dioxide - Combustion (AGR) | F23: kt
B24: ENV | C24: PL | D24: AGR_SO2 | E24: Sulphur Dioxide - Combustion (AGR) | F24: kt
B25: ENV | C25: PL | D25: AGR_NOX | E25: Nitrogen Oxides - Combustion (AGR) | F25: kt
B26: ENV | C26: PL | D26: AGR_TSP | E26: Total Suspended Particulate - Combustion (AGR)
B27: ENV | C27: PL | D27: AGR_PM10 | E27: Particulate Matter <= 10 um - Combustion (AGR) | F27: kt
B28: ENV | C28: PL | D28: AGR_PM2.5 | E28: Particulate Matter <= 2.5 um - Combustion (AGR) | F28: kt
B29: ENV | C29: PL | D29: AGR_HG | E29: Mercury - Combustion (AGR) | F29: kt
B30: \I: NRG | C30: PL | D30: HT_AGR_CHPI | F30: PJ | H30: DAYNITE
B31: NRG | C31: PL | D31: AGR_HT_OWN_USE | F31: PJ | H31: ANNUAL
B32: \I: nowododane dobra dla biogazowni
B33: \I: NRG | C33: PL | D33: AGR_BIO_CH4 | E33: Agricultural Biomethane | F33: PJ
B34: ENV | C34: PL | D34: AGR_N2O | E34: Nitrous Oxide - Field (AGR) | F34: kt
B35: ENV | C35: PL | D35: AGR_CH4_ENT | E35: Methane - Livestock Enteric Digestion (AGR) | F35: kt
B36: ENV | C36: PL | D36: AGR_CH4_MAN | E36: Methane - Livestock Manure (AGR) | F36: kt
B37: \I: ENV | C37: PL | D37: AGR_CH4_LAND | E37: Methane - LAND (AGR) | F37: kt
B38: NRG | C38: PL | D38: AGR_LIV_MANURE_CAT_DAIRY | E38: Animal Manure - Dairy Cattle | F38: kt
B39: NRG | C39: PL | D39: AGR_LIV_MANURE_CAT_NON-DAIRY | E39: Animal Manure - Non Dairy Cattle | F39: kt
B40: NRG | C40: PL | D40: AGR_LIV_MANURE_SHEEP | E40: Animal Manure - Sheep | F40: kt
B41: NRG | C41: PL | D41: AGR_LIV_MANURE_SWINE | E41: Animal Manure - Swine | F41: kt
B42: NRG | C42: PL | D42: AGR_LIV_MANURE_GOAT | E42: Animal Manure - Goat | F42: kt
B43: \I: | C43: PL | D43: AGR_LIV_MANURE_HORSE | E43: Animal Manure - Horse | F43: kt
B44: NRG | C44: PL | D44: AGR_LIV_MANURE_POULTRY | E44: Animal Manure - Poultry | F44: kt
... B61: NRG | C61: PL | D61: AGR_RESID_CROP_VEG | E61: Crop Residues | F61: kt
B62: MAT | C62: PL | D62: AGR_LIVESTOCK_FOOD | E62: Dummy Energy for Agriculture | F62: DUM | H62: ANNUAL
B63: MAT | C63: PL | D63: AGR_LAND | E63: Dummy Energy for Agriculture | F63: kha | H63: ANNUAL
B64: \I: | C64: PL | D64: AGR_DUMMY_NRG_CATTLE | E64: Dummy Energy for Agriculture | F64: DUM | H64: ANNUAL
B65: \I: | C65: PL | D65: AGR_DUMMY_NRG_LAND | E65: Dummy Energy for Agriculture | F65: DUM | H65: ANNUAL
B66: \I: NRG | C66: PL | D66: AGR_DUMMY_DMD_LAND | E66: Dummy Land Demand for Agriculture | F66: DUM | H66: ANNUAL
B67: \I: NRG | C67: PL | D67: AGR_DUMMY_LAND_RESIDUES | E67: Dummy Crop Residues for Biogas Production | F67: DUM | H67: ANNUAL
B68: DEM | C68: PL | D68: AGR_DEM_LIV_CAT_DAIRY | E68: AGR_DEM_LIV_CAT_DAIRY | F68: kt | H68: ANNUAL
B69: DEM | C69: PL | D69: AGR_DEM_LIV_CAT_NON-DAIRY | E69: AGR_DEM_LIV_CAT_NON-DAIRY | F69: kt | H69: ANNUAL
B70: DEM | C70: PL | D70: AGR_DEM_LIV_SHEEP | E70: AGR_DEM_LIV_SHEEP | F70: kt | H70: ANNUAL
B71: DEM | C71: PL | D71: AGR_DEM_LIV_SWINE | E71: AGR_DEM_LIV_SWINE | F71: kt | H71: ANNUAL
B72: DEM | C72: PL | D72: AGR_DEM_LIV_GOAT | E72: AGR_DEM_LIV_GOAT | F72: kt | H72: ANNUAL
B73: \I: | C73: PL | D73: AGR_DEM_LIV_HORSE | E73: AGR_DEM_LIV_HORSE | F73: kt | H73: ANNUAL
... B77: \I: | C77: PL | D77: AGR_DEM_LIV_INDIRECT | E77: AGR_DEM_LIV_INDIRECT | F77: kt | H77: ANNUAL
B78: DEM | C78: PL | D78: AGR_DEM_CROP_WHEAT | E78: Crop Residues | F78: kt
B79: DEM | C79: PL | D79: AGR_DEM_CROP_BARLEY | E79: Crop Residues | F79: kt
B80: DEM | C80: PL | D80: AGR_DEM_CROP_MAIZE | E80: Crop Residues | F80: kt
B81: DEM | C81: PL | D81: AGR_DEM_CROP_CER-MIX | E81: Crop Residues | F81: kt
B82: DEM | C82: PL | D82: AGR_DEM_CROP_TRITICALE | E82: Crop Residues | F82: kt
B83: DEM | C83: PL | D83: AGR_DEM_CROP_OATS | E83: Crop Residues | F83: kt
B84: DEM | C84: PL | D84: AGR_DEM_CROP_RYE | E84: Crop Residues | F84: kt
B85: DEM | C85: PL | D85: AGR_DEM_CROP_MILL-BUCK | E85: Crop Residues | F85: kt
B86: DEM | C86: PL | D86: AGR_DEM_CROP_PULS-FEED | E86: Crop Residues | F86: kt
B87: DEM | C87: PL | D87: AGR_DEM_CROP_PULS-EDIB | E87: Crop Residues | F87: kt
B88: DEM | C88: PL | D88: AGR_DEM_CROP_POTATO | E88: Crop Residues | F88: kt
B89: DEM | C89: PL | D89: AGR_DEM_CROP_OIL | E89: Crop Residues | F89: kt
... B97: NRG | C97: PL | D97: AGR_OTH_SVC | E97: Agriculture Service - Other | F97: PJ
B99: \I: Previously Defined - For Copying
B100: NRG | D100: ELC_GNC | E100: Generic Electricity - all voltages | F100: PJ | H100: DAYNITE | J100: ELC

Sheet AGR_Proc
B2: Definicja procesów | Process Definition
B4: ~FI_Process
B5: Sets | C5: Region | D5: TechName | E5: TechDesc | F5: Tact | G5: Tcap | H5: Tslvl | I5: PrimaryCG | J5: Vintage
B6: * Przynależność do zbioru procesów | C6: Nazwa regionu | D6: Nazwa technologii | E6: Opis technologii | F6: Jednostka aktywności | G6: Jednostka mocy | H6: Podokres aktywności procesu | I6: Przynależność do grupy głównej dóbr | J6: Śledzenie rocznika
B7: PRE | C7: PL | D7: SECTF_AGR_HC | E7: Sector fuel - Hard Coal | F7: PJ | G7: Pja
B8: PRE | C8: PL | D8: SECTF_AGR_BC | E8: Sector fuel - Brown Coal | F8: PJ | G8: Pja
B9: PRE | C9: PL | D9: SECTF_AGR_OIL_GSL | E9: Sector fuel - Gasoline | F9: PJ | G9: Pja
B10: PRE | C10: PL | D10: SECTF_AGR_OIL_DSL | E10: Sector fuel - Diesel | F10: PJ | G10: Pja
B11: PRE | C11: PL | D11: SECTF_AGR_OIL_LPG | E11: Sector fuel - LPG | F11: PJ | G11: Pja
B12: PRE | C12: PL | D12: SECTF_AGR_OIL_FUE | E12: Sector fuel - Fuel Oil | F12: PJ | G12: Pja
B13: PRE | C13: PL | D13: SECTF_AGR_NAT_GAS | E13: Sector fuel - Natural Gas | F13: PJ | G13: Pja
B14: PRE | C14: PL | D14: SECTF_AGR_BIOG | E14: Sector fuel - Biogas | F14: PJ | G14: Pja
B15: PRE | C15: PL | D15: SECTF_AGR_BIOM | E15: Sector fuel - Biomass | F15: PJ | G15: Pja
B16: PRE | C16: PL | D16: SECTF_AGR_RDF | E16: Sector fuel - RDF | F16: PJ | G16: Pja
B17: PRE | C17: PL | D17: SECTF_AGR_ELC | E17: Sector fuel - Electricity | F17: PJ | G17: Pja | H17: DAYNITE
B18: PRE | C18: PL | D18: SECTF_AGR_DH | E18: Sector fuel - District Heat | F18: PJ | G18: Pja | H18: ANNUAL
B19: PRE | C19: PL | D19: SECTF_AGR_OTH | E19: Sector fuel - Other Fuels | F19: PJ | G19: Pja
B20: DMD | C20: PL | D20: AGR_DEM_OWN_HEAT | E20: Heat demand related to CHPs in agr., e.g. drying | F20: PJ | G20: Pja
B21: DMD | C21: PL | D21: AGR_DEM_AGR | E21: Agriculture Demand Process | F21: IPI | G21: IPIa
B22: CHP | C22: PL | D22: CHPI_EX_BIOG_AGR | E22: Industrial Chp Plants for biogas from agriculture residues | F22: PJ | G22: GW | H22: DAYNITE | J22: NO
B23: \I: | C23: PL | D23: ELC_VOLT_DIV_AGR_CHPI | E23: Voltage Divider - AGR CHPI | F23: PJ | G23: PJa | H23: DAYNITE
B24: \I: PRE | C24: PL | D24: HT_DIV_AGR_CHPI | E24: Heat Divider - AGR CHPI | F24: PJ | G24: PJa | H24: DAYNITE
B25: \I: nowododane procesy dla biogazu
B26: PRE | C26: PL | D26: AGR_EX_BIOG | E26: Agriculture Existing Biogass | F26: PJ | G26: mln m3 | H26: ANNUAL
B27: PRE | C27: PL | D27: AGR_EX_BIOG_CLEAN | E27: Agriculture Biogaz Cleaning | F27: PJ | G27: Pja | H27: ANNUAL
B28: \I: | C28: PL | D28: AGR_IMP_DUMMY_NRG_LIV | E28: Dummy Energy Import | F28: DUM | G28: DUM | H28: ANNUAL
B29: \I: | C29: PL | D29: AGR_IMP_LAND_RESIDUE | E29: Dummy Import of Crop Residues for Biogas Production | F29: kt | G29: kt | H29: ANNUAL
B30: \I: | C30: PL | D30: AGR_IMP_DUMMY_NRG_LAND | E30: Dummy Land Import | F30: DUM | G30: DUM | H30: ANNUAL
B31: IMP | C31: PL | D31: AGR_IMP_DUMMY_FOOD_LIV | E31: Dummy Energy Import | F31: IPI | G31: 1000s of animals | H31: ANNUAL
B32: IMP | C32: PL | D32: AGR_IMP_DUMMY_LAND | E32: Dummy Land Import | F32: kha/a | G32: kha | H32: ANNUAL
B33: PRE | C33: PL | D33: AGR_EX_LIV_CAT_DAIRY | E33: AGR_LIV_CAT_DAIRY | F33: IPI | G33: 1000s of animals | H33: ANNUAL
B34: PRE | C34: PL | D34: AGR_EX_LIV_CAT_NON-DAIRY | E34: AGR_LIV_CAT_NON-DAIRY | F34: IPI | G34: 1000s of animals | H34: ANNUAL
B35: PRE | C35: PL | D35: AGR_EX_LIV_SHEEP | E35: AGR_LIV_SHEEP | F35: IPI | G35: 1000s of animals | H35: ANNUAL
B36: PRE | C36: PL | D36: AGR_EX_LIV_SWINE | E36: AGR_LIV_SWINE | F36: IPI | G36: 1000s of animals | H36: ANNUAL
B37: PRE | C37: PL | D37: AGR_EX_LIV_GOAT | E37: AGR_LIV_GOAT | F37: IPI | G37: 1000s of animals | H37: ANNUAL
... B71: \I:IMP | C71: PL | D71: AGR_IMP_LAND_RESIDUE | E71: Dummy Import of Crop Residues for Biogas Production | F71: kt | G71: kt | H71: ANNUAL
B72: PRE | C72: PL | D72: AGR_PRC_MECH_WORK | F72: PJ | G72: PJa | H72: ANNUAL
B73: PRE | C73: PL | D73: AGR_PRC_DRY_SVC | F73: PJ | G73: PJa | H73: ANNUAL
B74: PRE | C74: PL | D74: AGR_PRC_LIV_HT | F74: PJ | G74: PJa | H74: ANNUAL
B75: PRE | C75: PL | D75: AGR_PRC_LIV_ELC_SVC | F75: PJ | G75: PJa | H75: ANNUAL
B76: PRE | C76: PL | D76: AGR_PRC_OTH_SVC | F76: PJ | G76: PJa | H76: ANNUAL

Sheet SECTF
B2: Paliwa sektorowe | Sector fuels
E4: ~FI_T: PL
B5: TechName | C5: * TechDesc | D5: Comm-IN | E5: Comm-OUT | F5: EFF | G5: Share-I~UP | H5: Share-I~UP~0 | I5: FLO_COST~2020~2021 | J5: FLO_COST~2025 | K5: FLO_COST~2030 | L5: FLO_COST~2035 | M5: FLO_COST~2040 | N5: FLO_COST~2045 | O5: FLO_COST~2050 | P5: FLO_DELIV~2020~2021 | Q5: FLO_DELIV~2025 | R5: FLO_DELIV~2030 | S5: FLO_DELIV~2035 | T5: FLO_DELIV~2040 | U5: FLO_DELIV~2045 | V5: FLO_DELIV~2050 | W5: FLO_TAX
B6: \I: UNITS | I6: Mzl/PJ | J6: Mzl/PJ | K6: Mzl/PJ | L6: Mzl/PJ | M6: Mzl/PJ | N6: Mzl/PJ | O6: Mzl/PJ | P6: Mzl/PJ | Q6: Mzl/PJ | R6: Mzl/PJ | S6: Mzl/PJ | T6: Mzl/PJ | U6: Mzl/PJ | V6: Mzl/PJ | W6: Mzl/PJ
B7: =AGR_Proc!D7 -> SECTF_AGR_HC | C7: =AGR_Proc!E7 -> Sector fuel - Hard Coal | D7: PRI_HC | F7: 1
E8: =AGR_Comm!D7 -> AGR_HC | P8: 7.81 | Q8: 12 | R8: 12 | S8: 12 | T8: 12 | U8: 12 | V8: 12
B9: =AGR_Proc!D8 -> SECTF_AGR_BC | C9: =AGR_Proc!E8 -> Sector fuel - Brown Coal | D9: PRI_BC | F9: 1
E10: =AGR_Comm!D8 -> AGR_BC
B11: =AGR_Proc!D9 -> SECTF_AGR_OIL_GSL | C11: =AGR_Proc!E9 -> Sector fuel - Gasoline | D11: SEC_OIL_GSL | F11: 1
E12: =AGR_Comm!D9 -> AGR_OIL_GSL
B13: =AGR_Proc!D10 -> SECTF_AGR_OIL_DSL | C13: =AGR_Proc!E10 -> Sector fuel - Diesel | D13: SEC_OIL_DSL | F13: 1
E14: =AGR_Comm!D10 -> AGR_OIL_DSL
B15: =AGR_Proc!D11 -> SECTF_AGR_OIL_LPG | C15: =AGR_Proc!E11 -> Sector fuel - LPG | D15: SEC_OIL_LPG | F15: 1
E16: =AGR_Comm!D11 -> AGR_OIL_LPG
B17: =AGR_Proc!D12 -> SECTF_AGR_OIL_FUE | C17: =AGR_Proc!E12 -> Sector fuel - Fuel Oil | D17: SEC_OIL_FUE | F17: 1
E18: =AGR_Comm!D12 -> AGR_OIL_FUE
B19: =AGR_Proc!D13 -> SECTF_AGR_NAT_GAS | C19: =AGR_Proc!E13 -> Sector fuel - Natural Gas | D19: PRI_GAS_NAT_LP | F19: 1 | I19: 2.25 | J19: 5.04 | K19: =J19 -> 5.04 | L19: =K19 -> 5.04 | M19: =L19 -> 5.04 | N19: =M19 -> 5.04 | O19: =N19 -> 5.04
E20: =AGR_Comm!D13 -> AGR_NAT_GAS | P20: 6.19 | Q20: 7.44 | R20: =Q20 -> 7.44 | S20: =R20 -> 7.44 | T20: =S20 -> 7.44 | U20: =T20 -> 7.44 | V20: =U20 -> 7.44
B21: =AGR_Proc!D14 -> SECTF_AGR_BIOG | C21: =AGR_Proc!E14 -> Sector fuel - Biogas | D21: PRI_BIOG_AGR | F21: 1 | Y21: =AGR_Proc!D14 -> SECTF_AGR_BIOG | AA21: Biogaz rolniczy wytwarza się sam
E22: =OLD_AGR_Comm!D14 -> AGR_BIOG
B23: =AGR_Proc!D15 -> SECTF_AGR_BIOM | C23: =AGR_Proc!E15 -> Sector fuel - Biomass | D23: PRI_BIO_WOOD | F23: 1
E24: =AGR_Comm!D17 -> AGR_BIOM
B25: =AGR_Proc!D16 -> SECTF_AGR_RDF | C25: =AGR_Proc!E16 -> Sector fuel - RDF | D25: PRI_NREN_RDF | F25: 1
D26: PRI_REN_RDF
E27: =AGR_Comm!D18 -> AGR_RDF
B28: =AGR_Proc!D17 -> SECTF_AGR_ELC | C28: =AGR_Proc!E17 -> Sector fuel - Electricity | F28: 1
D29: ELC_LV-LV | G29: 0.91 | I29: 9.5112 | J29: 25 | K29: =J29 -> 25 | L29: =K29 -> 25 | M29: =L29 -> 25 | N29: =M29 -> 25 | O29: =N29 -> 25 | P29: 53.8966 | Q29: 141.68 | R29: =Q29 -> 141.68 | S29: =R29 -> 141.68 | T29: =S29 -> 141.68 | U29: =T29 -> 141.68 | V29: =U29 -> 141.68
E30: =AGR_Comm!D19 -> AGR_ELC
B31: =AGR_Proc!D18 -> SECTF_AGR_DH | C31: =AGR_Proc!E18 -> Sector fuel - District Heat | D31: HT_DH | F31: 1
E32: =AGR_Comm!D20 -> AGR_DH | P32: 19 | Q32: 25 | R32: =Q32 -> 25 | S32: =R32 -> 25 | T32: =S32 -> 25 | U32: =T32 -> 25 | V32: =U32 -> 25
B33: =AGR_Proc!D19 -> SECTF_AGR_OTH | C33: =AGR_Proc!E19 -> Sector fuel - Other Fuels | D33: PRI_IND_OTH_FUE | E33: =AGR_Comm!D21 -> AGR_OTH_FUE | F33: 1
G37: MV Jako możliwość

Sheet AGR_LAND
B4: TechName | C4: *TechDesc | D4: Comm-IN | E4: Comm-OUT | F4: Comm-OUT-A | G4: Stock~2020~2050 | H4: Output~2020~AGR_N2O | I4: Output~2050~AGR_N2O | J4: Cap2Act | K4: AFA~FX | L4: Input
B5: * Technology name | C5: Technology description | E5: Commodity output | G5: k ha | H5: kt/k ha
B6: AGR_FERT_N_INORG | C6: AGR_FERT_N_INORG | D6: AGR_LAND | E6: AGR_DUMMY_DMD_LAND | F6: AGR_N2O | G6: 100 | H6: 0.0033536446 | I6: 0.0033536446 | J6: 1 | K6: 1 | L6: 1
B7: AGR_FERT_N_MANURE | C7: AGR_FERT_N_MANURE | D7: AGR_LAND | E7: AGR_DUMMY_DMD_LAND | F7: AGR_N2O | G7: 100 | H7: 0.0013636722 | I7: 0.0013636722 | J7: 1 | K7: 1 | L7: 1
B8: AGR_FERT_N_SLUDGE | C8: AGR_FERT_N_SLUDGE | D8: AGR_LAND | E8: AGR_DUMMY_DMD_LAND | F8: AGR_N2O | G8: 100 | H8: 1.6167877e-05 | I8: 1.6167877e-05 | J8: 1 | K8: 1 | L8: 1
B9: AGR_FERT_N_URINE | C9: AGR_FERT_N_URINE | D9: AGR_LAND | E9: AGR_DUMMY_DMD_LAND | F9: AGR_N2O | G9: 100 | H9: 0.00035521266 | I9: 0.00035521266 | J9: 1 | K9: 1 | L9: 1
B10: AGR_FERT_N_CROP-RES | C10: AGR_FERT_N_CROP-RES | D10: AGR_LAND | E10: AGR_DUMMY_DMD_LAND | F10: AGR_N2O | G10: 100 | H10: 0.0013317293 | I10: 0.0013317293 | J10: 1 | K10: 1 | L10: 1
B11: AGR_FERT_N_MIN | C11: AGR_FERT_N_MIN | D11: AGR_LAND | E11: AGR_DUMMY_DMD_LAND | F11: AGR_N2O | G11: 100 | H11: 3.3444093e-05 | I11: 3.3444093e-05 | J11: 1 | K11: 1 | L11: 1
B12: AGR_FERT_N_CULT | C12: AGR_FERT_N_CULT | D12: AGR_LAND | E12: AGR_DUMMY_DMD_LAND | F12: AGR_N2O | G12: 100 | H12: 0.0023921301 | I12: 0.0023921301 | J12: 1 | K12: 1 | L12: 1
B13: AGR_FERT_N_ATM-DEP | C13: AGR_FERT_N_ATM-DEP | D13: AGR_LAND | E13: AGR_DUMMY_DMD_LAND | F13: AGR_N2O | G13: 100 | H13: 0.00064745988 | I13: 0.00064745988 | J13: 1 | K13: 1 | L13: 1
B14: AGR_FERT_N_NITR-LEACH | C14: AGR_FERT_N_NITR-LEACH | D14: AGR_LAND | E14: AGR_DUMMY_DMD_LAND | F14: AGR_N2O | G14: 100 | H14: 0.0014128414 | I14: 0.0014128414 | J14: 1 | K14: 1 | L14: 1
B17: TechName | C17: *TechDesc | D17: Comm-IN | E17: Comm-OUT | F17: Comm-OUT-A | G17: Stock~2020~2050 | H17: Output~2020~AGR_CO2 | I17: Output~2050~AGR_CO2 | J17: Cap2Act | K17: AFA~FX | L17: Input
B18: * Technology name | C18: Technology description | E18: Commodity output | G18: k ha | H18: kt/k ha
B19: AGR_LAND_FERT_CO2_LIM | C19: AGR_LAND_FERT_CO2_LIM | D19: AGR_LAND | E19: AGR_DUMMY_DMD_LAND | F19: AGR_CO2 | G19: 100 | H19: 0.13152132 | I19: 0.13152132 | J19: 1 | K19: 1 | L19: 1
B20: AGR_LAND_FERT_CO2_DOL | C20: AGR_LAND_FERT_CO2_DOL | D20: AGR_LAND | E20: AGR_DUMMY_DMD_LAND | F20: AGR_CO2 | G20: 100 | H20: 0.048130325 | I20: 0.048130325 | J20: 1 | K20: 1 | L20: 1
B21: AGR_LAND_FERT_CO2_UREA | C21: AGR_LAND_FERT_CO2_UREA | D21: AGR_LAND | E21: AGR_DUMMY_DMD_LAND | F21: AGR_CO2 | G21: 100 | H21: 0.089067159 | I21: 0.089067159 | J21: 1 | K21: 1 | L21: 1
B22: AGR_LAND_FERT_CO2_OTH | C22: AGR_LAND_FERT_CO2_OTH | D22: AGR_LAND | E22: AGR_DUMMY_DMD_LAND | F22: AGR_CO2 | G22: 100 | H22: 0.053429613 | I22: 0.053429613 | J22: 1 | K22: 1 | L22: 1
F25: ~FI_T:PL
B26: TechName | C26: *TechDesc | D26: Comm-IN | E26: Comm-OUT | F26: Comm-OUT-A | G26: Stock~2024 | H26: Stock~2025 | I26: Stock~2030 | J26: Stock~2035 | K26: Stock~2040 | L26: Stock~2045 | M26: Stock~2050 | N26: Input~2024 | O26: Input~2025 | P26: Input~2030 | Q26: Input~2035 | R26: Input~2040 | S26: Input~2045 | T26: Input~2050 | U26: Output~2024 | V26: Output~2025 | W26: Output~2030 | X26: Output~2035 | Y26: Output~2040 | Z26: Output~2045 | AA26: Output~2050 | AB26: Cap2Act | AC26: ACTFLO~2024 | AD26: ACTFLO~2025 | AE26: ACTFLO~2030 | AF26: ACTFLO~2035 | AG26: ACTFLO~2040 | AH26: ACTFLO~2045 | AI26: ACTFLO~2050 | AJ26: AFA | AK26: Output~2020~AGR_N2O | AL26: Output~2050~AGR_N2O | AN26: Uzysk odpadów 2024 | AO26: Uzysk odpadów 2025 | AP26: Uzysk odpadów 2030 | AQ26: Uzysk odpadów 2035 | AR26: Uzysk odpadów 2040 | AS26: Uzysk odpadów 2045 | AT26: Uzysk odpadów 2050 | AU26: Współczynnik zebrania | AW26: Produkcja odpadów max
B27: * Technology name | C27: Technology description | E27: Commodity output | G27: k ha | H27: k ha | I27: k ha | J27: k ha | K27: k ha | L27: k ha | M27: k ha | N27: kha/kha | U27: kt/kha | AC27: kt/kha | AD27: kt/kha | AE27: kt/kha | AF27: kt/kha | AG27: kt/kha | AH27: kt/kha | AI27: kt/kha | AK27: kt/k ha | AN27: t/ha | AO27: t/ha | AP27: t/ha | AQ27: t/ha | AR27: t/ha | AS27: t/ha | AT27: t/ha | AW27: kt
B28: AGR_LAND_CROP_WHEAT | C28: AGR_LAND_CROP_WHEAT | G28: =Y140 -> 2385.693 | H28: 2414.111 | I28: 2428.6907 | J28: 2190.4248 | K28: 1956.1429 | L28: 1725.7935 | M28: 1499.3258 | AB28: 1 | AJ28: 1
D29: =AGR_Comm!D63 -> AGR_LAND | N29: 1 | O29: 1 | P29: 1 | Q29: 1 | R29: 1 | S29: 1 | T29: 1
D30: =AGR_Comm!D93 -> AGR_MACH_WORK | N30: =AGR_SVC!N121 -> 0.0030442496 | O30: =AGR_SVC!AP121 -> 0.0030370705 | P30: =AGR_SVC!BD121 -> 0.0027741051 | Q30: =AGR_SVC!BR121 -> 0.0027980839 | R30: =AGR_SVC!CF121 -> 0.0028185575 | S30: =AGR_SVC!CT121 -> 0.0028338342 | T30: =AGR_SVC!AB121 -> 0.0028411038
D31: =AGR_Comm!D94 -> AGR_DRY_SVC | N31: =AGR_SVC!O121 -> 0.00051400711 | O31: =AGR_SVC!AQ121 -> 0.00050334749 | P31: =AGR_SVC!BE121 -> 0.00049311342 | Q31: =AGR_SVC!BS121 -> 0.00058586881 | R31: =AGR_SVC!CG121 -> 0.00071862313 | S31: =AGR_SVC!CU121 -> 0.00092434721 | T31: =AGR_SVC!AC121 -> 0.0012859811
D32: =AGR_Comm!D97 -> AGR_OTH_SVC | N32: =AGR_SVC!R121 -> 0.0013836154 | O32: =AGR_SVC!AT121 -> 0.001407374 | P32: =AGR_SVC!BH121 -> 0.001431353 | Q32: =AGR_SVC!BV121 -> 0.0016281797 | R32: =AGR_SVC!CJ121 -> 0.001875697 | S32: =AGR_SVC!CX121 -> 0.0021960249 | T32: =AGR_SVC!AF121 -> 0.0026263346
E33: AGR_DEM_CROP_WHEAT | AC33: =Z140/10 -> 5.2 | AD33: 5.59 | AE33: 5.6393486 | AF33: 5.6891328 | AG33: 5.7393565 | AH33: 5.7900235 | AI33: 5.8411379
E34: AGR_RESID_CROP_WHEAT | U34: =AN34*$AU$34 -> 0.76362 | V34: =AO34*$AU$34 -> 0.8208915 | W34: =AP34*$AU$34 -> 0.82813834 | X34: =AQ34*$AU$34 -> 0.83544915 | Y34: =AR34*$AU$34 -> 0.8428245 | Z34: =AS34*$AU$34 -> 0.85026496 | AA34: =AT34*$AU$34 -> 0.8577711 | AN34: =((AF140)/$AF$139)*Y128*0.33 -> 1.52724 | AO34: =((AG140)/AG139)*$Y$128*0.33 -> 1.641783 | AP34: =((AH140)/AH139)*$Y$128*0.33 -> 1.6562767 | AQ34: =((AI140)/AI139)*$Y$128*0.33 -> 1.6708983 | AR34: =((AJ140)/AJ139)*$Y$128*0.33 -> 1.685649 | AS34: =((AK140)/AK139)*$Y$128*0.33 -> 1.7005299 | AT34: =((AL140)/AL139)*$Y$128*0.33 -> 1.7155422 | AU34: 0.5 | AW34: =U34*G28 -> 1821.7629
F35: AGR_N2O | AK35: 0.0014 | AL35: 0.0014
B36: AGR_LAND_CROP_BARLEY | C36: AGR_LAND_CROP_BARLEY | G36: =Y144 -> 695.314 | H36: 620.626 | I36: 671.35791 | J36: 601.65783 | K36: 533.6735 | L36: 467.37186 | M36: 402.72041 | AB36: 1 | AJ36: 1
D37: =AGR_Comm!D63 -> AGR_LAND | N37: 1 | O37: 1 | P37: 1 | Q37: 1 | R37: 1 | S37: 1 | T37: 1
D38: =AGR_Comm!D93 -> AGR_MACH_WORK | N38: =AGR_SVC!N122 -> 0.0030442496 | O38: =AGR_SVC!AP122 -> 0.0030370705 | P38: =AGR_SVC!BD122 -> 0.0027741051 | Q38: =AGR_SVC!BR122 -> 0.0027980839 | R38: =AGR_SVC!CF122 -> 0.0028185575 | S38: =AGR_SVC!CT122 -> 0.0028338342 | T38: =AGR_SVC!AB122 -> 0.0028411038
D39: =AGR_Comm!D94 -> AGR_DRY_SVC | N39: =AGR_SVC!O122 -> 0.00043690604 | O39: =AGR_SVC!AQ122 -> 0.00042784537 | P39: =AGR_SVC!BE122 -> 0.00041914641 | Q39: =AGR_SVC!BS122 -> 0.00049798849 | R39: =AGR_SVC!CG122 -> 0.00061082966 | S39: =AGR_SVC!CU122 -> 0.00078569513 | T39: =AGR_SVC!AC122 -> 0.0010930839
D40: =AGR_Comm!D97 -> AGR_OTH_SVC | N40: =AGR_SVC!R122 -> 0.0013144346 | O40: =AGR_SVC!AT122 -> 0.0013370053 | P40: =AGR_SVC!BH122 -> 0.0013597853 | Q40: =AGR_SVC!BV122 -> 0.0015467707 | R40: =AGR_SVC!CJ122 -> 0.0017819121 | S40: =AGR_SVC!CX122 -> 0.0020862237 | T40: =AGR_SVC!AF122 -> 0.0024950179
E41: AGR_DEM_CROP_BARLEY | AC41: =Z144/10 -> 4.34 | AD41: 4.82 | AE41: 4.8841756 | AF41: 4.9492057 | AG41: 5.0151017 | AH41: 5.081875 | AI41: 5.1495373
E42: AGR_RESID_CROP_BARLEY | U42: =AN42*$AU$42 -> 0.57288 | V42: =AO42*$AU$42 -> 0.63624 | W42: =AP42*$AU$42 -> 0.64471118 | X42: =AQ42*$AU$42 -> 0.65329516 | Y42: =AR42*$AU$42 -> 0.66199342 | Z42: =AS42*$AU$42 -> 0.6708075 | AA42: =AT42*$AU$42 -> 0.67973893 | AN42: =((AF142)/AF141)*$Z$128*0.33 -> 1.14576 | AO42: =((AG142)/AG141)*$Z$128*0.33 -> 1.27248 | AP42: =((AH142)/AH141)*$Z$128*0.33 -> 1.2894224 | AQ42: =((AI142)/AI141)*$Z$128*0.33 -> 1.3065903 | AR42: =((AJ142)/AJ141)*$Z$128*0.33 -> 1.3239868 | AS42: =((AK142)/AK141)*$Z$128*0.33 -> 1.341615 | AT42: =((AL142)/AL141)*$Z$128*0.33 -> 1.3594779 | AU42: 0.5 | AW42: =U42*G36 -> 398.33148
F43: AGR_N2O | AK43: 0.0014 | AL43: 0.0014
B44: AGR_LAND_CROP_MAIZE | C44: AGR_LAND_CROP_MAIZE | G44: =Y152 -> 1276.727 | H44: 1341.812 | I44: 1379.8495 | J44: 1084.356 | K44: 798.94853 | L44: 523.36153 | M44: 257.33578 | AB44: 1 | AJ44: 1
D45: =AGR_Comm!D63 -> AGR_LAND | N45: 1 | O45: 1 | P45: 1 | Q45: 1 | R45: 1 | S45: 1 | T45: 1
D46: =AGR_Comm!D93 -> AGR_MACH_WORK | N46: =AGR_SVC!N123 -> 0.0038053119 | O46: =AGR_SVC!AP123 -> 0.0037963381 | P46: =AGR_SVC!BD123 -> 0.0034676314 | Q46: =AGR_SVC!BR123 -> 0.0034976049 | R46: =AGR_SVC!CF123 -> 0.0035231968 | S46: =AGR_SVC!CT123 -> 0.0035422927 | T46: =AGR_SVC!AB123 -> 0.0035513797
D47: =AGR_Comm!D94 -> AGR_DRY_SVC | N47: =AGR_SVC!O123 -> 0.0025700355 | O47: =AGR_SVC!AQ123 -> 0.0025167374 | P47: =AGR_SVC!BE123 -> 0.0024655671 | Q47: =AGR_SVC!BS123 -> 0.002929344 | R47: =AGR_SVC!CG123 -> 0.0035931156 | S47: =AGR_SVC!CU123 -> 0.004621736 | T47: =AGR_SVC!AC123 -> 0.0064299056
D48: =AGR_Comm!D97 -> AGR_OTH_SVC | N48: =AGR_SVC!R123 -> 0.0017987 | O48: =AGR_SVC!AT123 -> 0.0018295862 | P48: =AGR_SVC!BH123 -> 0.0018607589 | Q48: =AGR_SVC!BV123 -> 0.0021166336 | R48: =AGR_SVC!CJ123 -> 0.0024384061 | S48: =AGR_SVC!CX123 -> 0.0028548324 | T48: =AGR_SVC!AF123 -> 0.003414235
E49: AGR_DEM_CROP_MAIZE | AC49: =Z152/10 -> 7.36 | AD49: 7.85 | AE49: 7.9923165 | AF49: 8.1372132 | AG49: 8.2847368 | AH49: 8.4349349 | AI49: 8.587856
E50: AGR_RESID_CROP_MAIZE | U50: =AN50*$AU$50 -> 1.57872 | V50: =AO50*$AU$50 -> 1.683825 | W50: =AP50*$AU$50 -> 1.7143519 | X50: =AQ50*$AU$50 -> 1.7454322 | Y50: =AR50*$AU$50 -> 1.777076 | Z50: =AS50*$AU$50 -> 1.8092935 | AA50: =AT50*$AU$50 -> 1.8420951 | AN50: =((AF144)/AF143)*$AA$128*0.33 -> 3.15744 | AO50: =((AG144)/AG143)*$AA$128*0.33 -> 3.36765 | AP50: =((AH144)/AH143)*$AA$128*0.33 -> 3.4287038 | AQ50: =((AI144)/AI143)*$AA$128*0.33 -> 3.4908645 | AR50: =((AJ144)/AJ143)*$AA$128*0.33 -> 3.5541521 | AS50: =((AK144)/AK143)*$AA$128*0.33 -> 3.6185871 | AT50: =((AL144)/AL143)*$AA$128*0.33 -> 3.6841902 | AU50: 0.5 | AW50: =U50*G44 -> 2015.5944
F51: AGR_N2O | AK51: 0.00237 | AL51: 0.00237
B52: AGR_LAND_CROP_CER-MIX | C52: AGR_LAND_CROP_CER-MIX | G52: =Y150 -> 252.4 | H52: 197.244 | I52: 165.41704 | J52: 263.45818 | K52: 360.11515 | L52: 455.40256 | M52: 549.33487 | AB52: 1 | AJ52: 1
D53: =AGR_Comm!D63 -> AGR_LAND | N53: 1 | O53: 1 | P53: 1 | Q53: 1 | R53: 1 | S53: 1 | T53: 1
D54: =AGR_Comm!D93 -> AGR_MACH_WORK | N54: =AGR_SVC!N124 -> 0.0025876121 | O54: =AGR_SVC!AP124 -> 0.0025815099 | P54: =AGR_SVC!BD124 -> 0.0023579893 | Q54: =AGR_SVC!BR124 -> 0.0023783713 | R54: =AGR_SVC!CF124 -> 0.0023957738 | S54: =AGR_SVC!CT124 -> 0.0024087591 | T54: =AGR_SVC!AB124 -> 0.0024149382
D55: =AGR_Comm!D94 -> AGR_DRY_SVC | N55: =AGR_SVC!O124 -> 0.0002313032 | O55: =AGR_SVC!AQ124 -> 0.00022650637 | P55: =AGR_SVC!BE124 -> 0.00022190104 | Q55: =AGR_SVC!BS124 -> 0.00026364096 | R55: =AGR_SVC!CG124 -> 0.00032338041 | S55: =AGR_SVC!CU124 -> 0.00041595624 | T55: =AGR_SVC!AC124 -> 0.0005786915
D56: =AGR_Comm!D97 -> AGR_OTH_SVC | N56: =AGR_SVC!R124 -> 0.0011068923 | O56: =AGR_SVC!AT124 -> 0.0011258992 | P56: =AGR_SVC!BH124 -> 0.0011450824 | Q56: =AGR_SVC!BV124 -> 0.0013025437 | R56: =AGR_SVC!CJ124 -> 0.0015005576 | S56: =AGR_SVC!CX124 -> 0.0017568199 | T56: =AGR_SVC!AF124 -> 0.0021010677
E57: AGR_DEM_CROP_CER-MIX | AC57: =Z150/10 -> 3.3 | AD57: 3.6 | AE57: 3.6254417 | AF57: 3.6510632 | AG57: 3.6768658 | AH57: 3.7028507 | AI57: 3.7290192
E58: AGR_RESID_CROP_CER-MIX | U58: =AN58*$AU$58 -> 0.49005 | V58: =AO58*$AU$58 -> 0.5346 | W58: =AP58*$AU$58 -> 0.53837809 | X58: =AQ58*$AU$58 -> 0.54218288 | Y58: =AR58*$AU$58 -> 0.54601457 | Z58: =AS58*$AU$58 -> 0.54987333 | AA58: =AT58*$AU$58 -> 0.55375936 | AN58: =((AF146)/AF145)*$AB$128*0.33 -> 0.9801 | AO58: =((AG146)/AG145)*$AB$128*0.33 -> 1.0692 | AP58: =((AH146)/AH145)*$AB$128*0.33 -> 1.0767562 | AQ58: =((AI146)/AI145)*$AB$128*0.33 -> 1.0843658 | AR58: =((AJ146)/AJ145)*$AB$128*0.33 -> 1.0920291 | AS58: =((AK146)/AK145)*$AB$128*0.33 -> 1.0997467 | AT58: =((AL146)/AL145)*$AB$128*0.33 -> 1.1075187 | AU58: 0.5 | AW58: =U58*G52 -> 123.68862
F59: AGR_N2O | AK59: 0.0024316667 | AL59: 0.0024316667
B60: AGR_LAND_CROP_TRITICALE | C60: AGR_LAND_CROP_TRITICALE | G60: =Y148 -> 1147.034 | H60: 1115.504 | I60: 1036.0262 | J60: 966.49993 | K60: 897.91681 | L60: 830.26683 | M60: 763.54016 | AB60: 1 | AJ60: 1
D61: =AGR_Comm!D63 -> AGR_LAND | N61: 1 | O61: 1 | P61: 1 | Q61: 1 | R61: 1 | S61: 1 | T61: 1
D62: =AGR_Comm!D93 -> AGR_MACH_WORK | N62: =AGR_SVC!N125 -> 0.0027398246 | O62: =AGR_SVC!AP125 -> 0.0027333634 | P62: =AGR_SVC!BD125 -> 0.0024966946 | Q62: =AGR_SVC!BR125 -> 0.0025182755 | R62: =AGR_SVC!CF125 -> 0.0025367017 | S62: =AGR_SVC!CT125 -> 0.0025504508 | T62: =AGR_SVC!AB125 -> 0.0025569934
D63: =AGR_Comm!D94 -> AGR_DRY_SVC | N63: =AGR_SVC!O125 -> 0.00035980497 | O63: =AGR_SVC!AQ125 -> 0.00035234324 | P63: =AGR_SVC!BE125 -> 0.0003451794 | Q63: =AGR_SVC!BS125 -> 0.00041010817 | R63: =AGR_SVC!CG125 -> 0.00050303619 | S63: =AGR_SVC!CU125 -> 0.00064704305 | T63: =AGR_SVC!AC125 -> 0.00090018678
D64: =AGR_Comm!D97 -> AGR_OTH_SVC | N64: =AGR_SVC!R125 -> 0.0012452539 | O64: =AGR_SVC!AT125 -> 0.0012666366 | P64: =AGR_SVC!BH125 -> 0.0012882177 | Q64: =AGR_SVC!BV125 -> 0.0014653617 | R64: =AGR_SVC!CJ125 -> 0.0016881273 | S64: =AGR_SVC!CX125 -> 0.0019764224 | T64: =AGR_SVC!AF125 -> 0.0023637011
E65: AGR_DEM_CROP_TRITICALE | AC65: =Z148/10 -> 4.4 | AD65: 4.72 | AE65: 4.7540619 | AF65: 4.7883695 | AG65: 4.8229248 | AH65: 4.8577294 | AI65: 4.8927852
E66: AGR_RESID_CROP_TRITICALE | U66: =AN66*$AU$66 -> 0.7986 | V66: =AO66*$AU$66 -> 0.85668 | W66: =AP66*$AU$66 -> 0.86286223 | X66: =AQ66*$AU$66 -> 0.86908907 | Y66: =AR66*$AU$66 -> 0.87536084 | Z66: =AS66*$AU$66 -> 0.88167788 | AA66: =AT66*$AU$66 -> 0.88804051 | AN66: =((AF148)/AF147)*$AC$128*0.33 -> 1.5972 | AO66: =((AG148)/AG147)*$AC$128*0.33 -> 1.71336 | AP66: =((AH148)/AH147)*$AC$128*0.33 -> 1.7257245 | AQ66: =((AI148)/AI147)*$AC$128*0.33 -> 1.7381781 | AR66: =((AJ148)/AJ147)*$AC$128*0.33 -> 1.7507217 | AS66: =((AK148)/AK147)*$AC$128*0.33 -> 1.7633558 | AT66: =((AL148)/AL147)*$AC$128*0.33 -> 1.776081 | AU66: 0.5 | AW66: =U66*G60 -> 916.02135
F67: AGR_N2O | AK67: 0.0045 | AL67: 0.0045
B68: AGR_LAND_CROP_OATS | C68: AGR_LAND_CROP_OATS | G68: =Y146 -> 519.003 | H68: 528.653 | I68: 490.98734 | J68: 425.94506 | K68: 361.8096 | L68: 298.57132 | M68: 236.22064 | AB68: 1 | AJ68: 1
D69: =AGR_Comm!D63 -> AGR_LAND | N69: 1 | O69: 1 | P69: 1 | Q69: 1 | R69: 1 | S69: 1 | T69: 1
D70: =AGR_Comm!D93 -> AGR_MACH_WORK | N70: =AGR_SVC!N126 -> 0.0024353996 | O70: =AGR_SVC!AP126 -> 0.0024296564 | P70: =AGR_SVC!BD126 -> 0.0022192841 | Q70: =AGR_SVC!BR126 -> 0.0022384671 | R70: =AGR_SVC!CF126 -> 0.002254846 | S70: =AGR_SVC!CT126 -> 0.0022670674 | T70: =AGR_SVC!AB126 -> 0.002272883
D71: =AGR_Comm!D94 -> AGR_DRY_SVC | N71: =AGR_SVC!O126 -> 0.00017990249 | O71: =AGR_SVC!AQ126 -> 0.00017617162 | P71: =AGR_SVC!BE126 -> 0.0001725897 | Q71: =AGR_SVC!BS126 -> 0.00020505408 | R71: =AGR_SVC!CG126 -> 0.00025151809 | S71: =AGR_SVC!CU126 -> 0.00032352152 | T71: =AGR_SVC!AC126 -> 0.00045009339
D72: =AGR_Comm!D97 -> AGR_OTH_SVC | N72: =AGR_SVC!R126 -> 0.0011068923 | O72: =AGR_SVC!AT126 -> 0.0011258992 | P72: =AGR_SVC!BH126 -> 0.0011450824 | Q72: =AGR_SVC!BV126 -> 0.0013025437 | R72: =AGR_SVC!CJ126 -> 0.0015005576 | S72: =AGR_SVC!CX126 -> 0.0017568199 | T72: =AGR_SVC!AF126 -> 0.0021010677
E73: AGR_DEM_CROP_OATS | AC73: =Z146/10 -> 3.17 | AD73: 3.49 | AE73: 3.5151856 | AF73: 3.5405529 | AG73: 3.5661033 | AH73: 3.591838 | AI73: 3.6177585
E74: AGR_RESID_CROP_OATS | U74: =AN74*$AU$74 -> 0.575355 | V74: =AO74*$AU$74 -> 0.633435 | W74: =AP74*$AU$74 -> 0.63800618 | X74: =AQ74*$AU$74 -> 0.64261035 | Y74: =AR74*$AU$74 -> 0.64724774 | Z74: =AS74*$AU$74 -> 0.6519186 | AA74: =AT74*$AU$74 -> 0.65662317 | AN74: =((AF150)/AF149)*$AD$128*0.33 -> 1.15071 | AO74: =((AG150)/AG149)*$AD$128*0.33 -> 1.26687 | AP74: =((AH150)/AH149)*$AD$128*0.33 -> 1.2760124 | AQ74: =((AI150)/AI149)*$AD$128*0.33 -> 1.2852207 | AR74: =((AJ150)/AJ149)*$AD$128*0.33 -> 1.2944955 | AS74: =((AK150)/AK149)*$AD$128*0.33 -> 1.3038372 | AT74: =((AL150)/AL149)*$AD$128*0.33 -> 1.3132463 | AU74: 0.5 | AW74: =U74*G68 -> 298.61097
F75: AGR_N2O | AK75: 0.00196 | AL75: 0.00196
B76: AGR_LAND_CROP_RYE | C76: AGR_LAND_CROP_RYE | G76: =Y142 -> 682.181 | H76: 603.916 | I76: 560.88797 | J76: 508.69902 | K76: 457.22912 | L76: 406.47065 | M76: 356.41605 | AB76: 1 | AJ76: 1
D77: =AGR_Comm!D63 -> AGR_LAND | N77: 1 | O77: 1 | P77: 1 | Q77: 1 | R77: 1 | S77: 1 | T77: 1
D78: =AGR_Comm!D93 -> AGR_MACH_WORK | N78: =AGR_SVC!N127 -> 0.0021309747 | O78: =AGR_SVC!AP127 -> 0.0021259493 | P78: =AGR_SVC!BD127 -> 0.0019418736 | Q78: =AGR_SVC!BR127 -> 0.0019586587 | R78: =AGR_SVC!CF127 -> 0.0019729902 | S78: =AGR_SVC!CT127 -> 0.0019836839 | T78: =AGR_SVC!AB127 -> 0.0019887726
D79: =AGR_Comm!D94 -> AGR_DRY_SVC | N79: =AGR_SVC!O127 -> 0.00017990249 | O79: =AGR_SVC!AQ127 -> 0.00017617162 | P79: =AGR_SVC!BE127 -> 0.0001725897 | Q79: =AGR_SVC!BS127 -> 0.00020505408 | R79: =AGR_SVC!CG127 -> 0.00025151809 | S79: =AGR_SVC!CU127 -> 0.00032352152 | T79: =AGR_SVC!AC127 -> 0.00045009339
D80: =AGR_Comm!D97 -> AGR_OTH_SVC | N80: =AGR_SVC!R127 -> 0.0010377116 | O80: =AGR_SVC!AT127 -> 0.0010555305 | P80: =AGR_SVC!BH127 -> 0.0010735147 | Q80: =AGR_SVC!BV127 -> 0.0012211348 | R80: =AGR_SVC!CJ127 -> 0.0014067727 | S80: =AGR_SVC!CX127 -> 0.0016470187 | T80: =AGR_SVC!AF127 -> 0.0019697509
E81: AGR_DEM_CROP_RYE | AC81: =Z142/10 -> 3.57 | AD81: 3.82 | AE81: 3.847567 | AF81: 3.875333 | AG81: 3.9032993 | AH81: 3.9314674 | AI81: 3.9598388
E82: AGR_RESID_CROP_RYE | U82: =AN82*$AU$82 -> 0.82467 | V82: =AO82*$AU$82 -> 0.88242 | W82: =AP82*$AU$82 -> 0.88878798 | X82: =AQ82*$AU$82 -> 0.89520191 | Y82: =AR82*$AU$82 -> 0.90166213 | Z82: =AS82*$AU$82 -> 0.90816897 | AA82: =AT82*$AU$82 -> 0.91472277 | AN82: =((AF152)/AF151)*$AE$128*0.33 -> 1.64934 | AO82: =((AG152)/AG151)*$AE$128*0.33 -> 1.76484 | AP82: =((AH152)/AH151)*$AE$128*0.33 -> 1.777576 | AQ82: =((AI152)/AI151)*$AE$128*0.33 -> 1.7904038 | AR82: =((AJ152)/AJ151)*$AE$128*0.33 -> 1.8033243 | AS82: =((AK152)/AK151)*$AE$128*0.33 -> 1.8163379 | AT82: =((AL152)/AL151)*$AE$128*0.33 -> 1.8294455 | AU82: 0.5 | AW82: =U82*G76 -> 562.57421
F83: AGR_N2O | AK83: 0.00296 | AL83: 0.00296
B84: AGR_LAND_CROP_MILL-BUCK | C84: AGR_LAND_CROP_MILL-BUCK | G84: =Y154+Y156 -> 116.38 | H84: 83.955171 | I84: 70.408306 | J84: 61.630597 | K84: 52.972615 | L84: 44.433114 | M84: 36.010858 | AB84: 1 | AJ84: 1
D85: =AGR_Comm!D63 -> AGR_LAND | N85: 1 | O85: 1 | P85: 1 | Q85: 1 | R85: 1 | S85: 1 | T85: 1
D86: =AGR_Comm!D93 -> AGR_MACH_WORK | N86: =AGR_SVC!N128 -> 0.0022831872 | O86: =AGR_SVC!AP128 -> 0.0022778029 | P86: =AGR_SVC!BD128 -> 0.0020805788 | Q86: =AGR_SVC!BR128 -> 0.0020985629 | R86: =AGR_SVC!CF128 -> 0.0021139181 | S86: =AGR_SVC!CT128 -> 0.0021253756 | T86: =AGR_SVC!AB128 -> 0.0021308278
D87: =AGR_Comm!D94 -> AGR_DRY_SVC | N87: =AGR_SVC!O128 -> 0.00012850178 | O87: =AGR_SVC!AQ128 -> 0.00012583687 | P87: =AGR_SVC!BE128 -> 0.00012327836 | Q87: =AGR_SVC!BS128 -> 0.0001464672 | R87: =AGR_SVC!CG128 -> 0.00017965578 | S87: =AGR_SVC!CU128 -> 0.0002310868 | T87: =AGR_SVC!AC128 -> 0.00032149528
D88: =AGR_Comm!D97 -> AGR_OTH_SVC | N88: =AGR_SVC!R128 -> 0.0010377116 | O88: =AGR_SVC!AT128 -> 0.0010555305 | P88: =AGR_SVC!BH128 -> 0.0010735147 | Q88: =AGR_SVC!BV128 -> 0.0012211348 | R88: =AGR_SVC!CJ128 -> 0.0014067727 | S88: =AGR_SVC!CX128 -> 0.0016470187 | T88: =AGR_SVC!AF128 -> 0.0019697509
E89: AGR_DEM_CROP_MILL-BUCK | AC89: =(Z154+Z156)/2/10 -> 1.705 | AD89: 1.87 | AE89: 1.8832155 | AF89: 1.8965245 | AG89: 1.9099275 | AH89: 1.9234252 | AI89: 1.9370183
E90: AGR_RESID_CROP_MILL-BUCK | U90: =AN90*$AU$90 -> 0.44667379 | V90: =AO90*$AU$90 -> 0.524535 | W90: =AP90*$AU$90 -> 0.52824196 | X90: =AQ90*$AU$90 -> 0.53197512 | Y90: =AR90*$AU$90 -> 0.53573466 | Z90: =AS90*$AU$90 -> 0.53952077 | AA90: =AT90*$AU$90 -> 0.54333364 | AN90: =(((AF154))/(AF153))*$AF$128*0.33 -> 0.89334757 | AO90: =(((AG154))/(AG153))*$AF$128*0.33 -> 1.04907 | AP90: =(((AH154))/(AH153))*$AF$128*0.33 -> 1.0564839 | AQ90: =(((AI154))/(AI153))*$AF$128*0.33 -> 1.0639502 | AR90: =(((AJ154))/(AJ153))*$AF$128*0.33 -> 1.0714693 | AS90: =(((AK154))/(AK153))*$AF$128*0.33 -> 1.0790415 | AT90: =(((AL154))/(AL153))*$AF$128*0.33 -> 1.0866673 | AU90: 0.5 | AW90: =U90*G84 -> 51.983895
F91: AGR_N2O | AK91: 4.68e-05 | AL91: 4.68e-05
B92: AGR_LAND_CROP_PULS-FEED | C92: AGR_LAND_CROP_PULS-FEED | G92: =Y164 -> 43.309 | H92: 37.813 | I92: 40.751431 | J92: 32.192783 | K92: 23.946337 | L92: 16.003288 | M92: 8.3550509 | AB92: 1 | AJ92: 1
D93: AGR_LAND | N93: 1 | O93: 1 | P93: 1 | Q93: 1 | R93: 1 | S93: 1 | T93: 1
E94: AGR_DEM_CROP_PULS-FEED | AC94: =Z164/10 -> 17.99 | AD94: 18.6 | AE94: 18.962338 | AF94: 19.331734 | AG94: 19.708326 | AH94: 20.092254 | AI94: 20.483662
B95: \I: | E95: AGR_RESID_CROP_PULS-FEED | U95: =AN95*AU95 -> 0 | AN95: 0 | AU95: 0 | AW95: =U95*G92 -> 0
F96: AGR_N2O | AK96: 0.00159 | AL96: 0.00159
B97: AGR_LAND_CROP_PULS-EDIB | C97: AGR_LAND_CROP_PULS-EDIB | G97: =Y162 -> 206.142 | H97: 213.757 | I97: 230.36796 | J97: 237.18848 | K97: 243.66423 | L97: 249.8059 | M97: 255.62388 | AB97: 1 | AJ97: 1
D98: AGR_LAND | N98: 1 | O98: 1 | P98: 1 | Q98: 1 | R98: 1 | S98: 1 | T98: 1
E99: AGR_DEM_CROP_PULS-EDIB | AC99: =Z162/10 -> 2.49 | AD99: 2.53 | AE99: 2.5792857 | AF99: 2.6295315 | AG99: 2.6807562 | AH99: 2.7329787 | AI99: 2.7862185
B100: \I: | E100: AGR_RESID_CROP_PULS-EDIB | U100: =AN100*AU100 -> 0 | AN100: 0 | AU100: 0 | AW100: =U100*G97 -> 0
F101: AGR_N2O | AK101: 0.00159 | AL101: 0.00159
B102: AGR_LAND_CROP_POTATO | C102: AGR_LAND_CROP_POTATO | G102: =Y158 -> 196.151 | H102: 214.19 | I102: 171.58288 | J102: 183.72262 | K102: 195.5572 | L102: 207.09209 | M102: 218.33264 | AB102: 1 | AJ102: 1
D103: AGR_LAND | N103: 1 | O103: 1 | P103: 1 | Q103: 1 | R103: 1 | S103: 1 | T103: 1
E104: AGR_DEM_CROP_POTATO | AC104: =Z158/10 -> 30.2 | AD104: 32.7 | AE104: 33.08427 | AF104: 33.473055 | AG104: 33.866409 | AH104: 34.264385 | AI104: 34.667038
B105: \I: | E105: AGR_RESID_CROP_POTATO | U105: =AN105*AU105 -> 0 | AN105: 0 | AU105: 0 | AW105: =U105*G102 -> 0
F106: AGR_N2O | AK106: 0.00081 | AL106: 0.00081
B107: AGR_LAND_CROP_OIL | C107: AGR_LAND_CROP_OIL | G107: =Y160 -> 1104.548 | H107: 1199.678 | I107: 1273.7649 | J107: 1153.6466 | K107: 1036.18 | L107: 921.31945 | M107: 809.01979 | AB107: 1 | AJ107: 1
...

Sheet AGR_LIV
E2: ~FI_T:PL
B3: TechName | C3: * TechDesc | D3: Comm-IN | E3: Comm-OUT | F3: Comm-OUT-A | G3: Stock~2024 | H3: Stock~2025 | I3: Stock~2030 | J3: Stock~2035 | K3: Stock~2040 | L3: Stock~2045 | M3: Stock~2050 | N3: Input~2024 | O3: Input~2025 | P3: Input~2030 | Q3: Input~2035 | R3: Input~2040 | S3: Input~2045 | T3: Input~2050 | U3: OUTPUT | V3: Cap2Act | W3: AFA | Y3: Uzysk manure | Z3: Współczynnik zebrania | AB3: Produkcja odpadów max
B4: * Technology name | C4: Technology description | D4: Commodity input | E4: Commodity output | G4: Thousands Animals | H4: Thousands Animals | I4: Thousands Animals | J4: Thousands Animals | K4: Thousands Animals | L4: Thousands Animals | M4: Thousands Animals | N4: Fuel Input per 1000 Animals/Final Energy Demand [PJ/1000 Animals] | U4: kt/1000 animals | V4: Animals per year | AB4: kt | AD4: %
B5: AGR_EX_LIV_CAT_DAIRY | C5: AGR_LIV_CAT_DAIRY | G5: =K75/1000 -> 2101.159 | H5: 2091.035 | I5: 1970.9299 | J5: 1654.0253 | K5: 1426.6884 | L5: 1242.5278 | M5: 1080.1438 | V5: 1 | W5: 1
D6: =$D$70 -> AGR_LIVESTOCK_FOOD | N6: 1 | O6: 1 | P6: 1 | Q6: 1 | R6: 1 | S6: 1 | T6: 1
D7: =AGR_Comm!$D$93 -> AGR_MACH_WORK | N7: =AGR_SVC!N139 -> 0.00024603962 | O7: =AGR_SVC!AP139 -> 0.00024074424 | P7: =AGR_SVC!BD139 -> 0.00023137146 | Q7: =AGR_SVC!BR139 -> 0.00024705137 | R7: =AGR_SVC!CF139 -> 0.00025320281 | S7: =AGR_SVC!CT139 -> 0.00025259298 | T7: =AGR_SVC!AB139 -> 0.000246695
D8: =AGR_Comm!$D$95 -> AGR_LIV_HT | N8: =AGR_SVC!P139 -> 0.00010790472 | O8: =AGR_SVC!AR139 -> 0.00010539017 | P8: =AGR_SVC!BF139 -> 0.00010674852 | Q8: =AGR_SVC!BT139 -> 0.00012116691 | R8: =AGR_SVC!CH139 -> 0.00013347865 | S8: =AGR_SVC!CV139 -> 0.00014522954 | T8: =AGR_SVC!AD139 -> 0.00015782254
D9: =AGR_Comm!$D$96 -> AGR_LIV_ELC_SVC | N9: =AGR_SVC!Q139 -> 0.0003666136 | O9: =AGR_SVC!AS139 -> 0.00040364576 | P9: =AGR_SVC!BG139 -> 0.00064163976 | Q9: =AGR_SVC!BU139 -> 0.0010188578 | R9: =AGR_SVC!CI139 -> 0.0014760099 | S9: =AGR_SVC!CW139 -> 0.002033271 | T9: =AGR_SVC!AE139 -> 0.0027283268
D10: =AGR_Comm!$D$97 -> AGR_OTH_SVC | N10: =AGR_SVC!R139 -> 0.00037755319 | O10: =AGR_SVC!AT139 -> 0.00037446317 | P10: =AGR_SVC!BH139 -> 0.00040066884 | Q10: =AGR_SVC!BV139 -> 0.00048147075 | R10: =AGR_SVC!CJ139 -> 0.00056286953 | S10: =AGR_SVC!CX139 -> 0.00065166672 | T10: =AGR_SVC!AF139 -> 0.00075581473
E11: AGR_DEM_LIV_CAT_DAIRY
E12: AGR_LIV_MANURE_CAT_DAIRY | U12: =Y12*Z12 -> 7.0925 | Y12: 14.185 | Z12: 0.5 | AB12: =U12*M5 -> 7660.9201 | AD12: =AB12/AB64 -> 0.38035369
F13: AGR_CH4_ENT | U13: 0.1056
F14: AGR_CH4_MAN | U14: =0.01438 -> 0.01438
F15: AGR_N2O | U15: =120/1000000 -> 0.00012
B16: AGR_EX_LIV_CAT_NON-DAIRY | C16: AGR_LIV_CAT_NON-DAIRY | G16: =(J75-K75)/1000 -> 4089.768 | H16: 4052.27 | I16: 3819.5153 | J16: 3205.3778 | K16: 2764.8157 | L16: 2407.9263 | M16: 2093.2382 | V16: 1 | W16: 1
D17: =$D$70 -> AGR_LIVESTOCK_FOOD | N17: 1 | O17: 1 | P17: 1 | Q17: 1 | R17: 1 | S17: 1 | T17: 1
D18: =AGR_Comm!$D$93 -> AGR_MACH_WORK | N18: =AGR_SVC!N140 -> 0.00018452971 | O18: =AGR_SVC!AP140 -> 0.00018055818 | P18: =AGR_SVC!BD140 -> 0.00017352859 | Q18: =AGR_SVC!BR140 -> 0.00018528853 | R18: =AGR_SVC!CF140 -> 0.00018990211 | S18: =AGR_SVC!CT140 -> 0.00018944473 | T18: =AGR_SVC!AB140 -> 0.00018502125
D19: =AGR_Comm!$D$95 -> AGR_LIV_HT | N19: =AGR_SVC!P140 -> 5.3952361e-05 | O19: =AGR_SVC!AR140 -> 5.2695086e-05 | P19: =AGR_SVC!BF140 -> 5.3374258e-05 | Q19: =AGR_SVC!BT140 -> 6.0583457e-05 | R19: =AGR_SVC!CH140 -> 6.6739327e-05 | S19: =AGR_SVC!CV140 -> 7.2614772e-05 | T19: =AGR_SVC!AD140 -> 7.8911272e-05
D20: =AGR_Comm!$D$96 -> AGR_LIV_ELC_SVC | N20: =AGR_SVC!Q140 -> 7.3322719e-05 | O20: =AGR_SVC!AS140 -> 8.0729152e-05 | P20: =AGR_SVC!BG140 -> 0.00012832795 | Q20: =AGR_SVC!BU140 -> 0.00020377156 | R20: =AGR_SVC!CI140 -> 0.00029520198 | S20: =AGR_SVC!CW140 -> 0.0004066542 | T20: =AGR_SVC!AE140 -> 0.00054566536
D21: =AGR_Comm!$D$97 -> AGR_OTH_SVC | N21: =AGR_SVC!R140 -> 0.00020765425 | O21: =AGR_SVC!AT140 -> 0.00020595474 | P21: =AGR_SVC!BH140 -> 0.00022036786 | Q21: =AGR_SVC!BV140 -> 0.00026480891 | R21: =AGR_SVC!CJ140 -> 0.00030957824 | S21: =AGR_SVC!CX140 -> 0.00035841669 | T21: =AGR_SVC!AF140 -> 0.0004156981
E22: AGR_DEM_LIV_CAT_NON-DAIRY
E23: AGR_LIV_MANURE_CAT_NON-DAIRY | U23: =Y23*Z23 -> 2.937 | Y23: 5.874 | Z23: 0.5 | AB23: =U23*M16 -> 6147.8407 | AD23: =AB23/AB64 -> 0.30523147
F24: AGR_CH4_ENT | U24: 0.0531
F25: AGR_CH4_MAN | U25: 0.00858
F26: AGR_N2O | U26: 0.000144
B27: AGR_EX_LIV_SHEEP | C27: AGR_LIV_SHEEP | G27: =N75/1000 -> 269.538 | H27: 267.894 | I27: 252.50667 | J27: 211.90628 | K27: 182.7809 | L27: 159.18707 | M27: 138.38317 | V27: 1 | W27: 1
D28: =$D$70 -> AGR_LIVESTOCK_FOOD | N28: 1 | O28: 1 | P28: 1 | Q28: 1 | R28: 1 | S28: 1 | T28: 1
E29: AGR_DEM_LIV_SHEEP
B30: \I: | E30: AGR_LIV_MANURE_SHEEP | U30: =Y30*Z30 -> 0.342 | Y30: 0.684 | Z30: 0.5 | AB30: =U30*M27 -> 47.327044
F31: AGR_CH4_ENT | U31: 0.008
F32: AGR_CH4_MAN | U32: 0.00113
F33: AGR_N2O | U33: 1.8e-05
B34: AGR_EX_LIV_SWINE | C34: AGR_LIV_SWINE | G34: =L75/1000 -> 9078.25 | H34: 9225.221 | I34: 8695.3417 | J34: 7297.2231 | K34: 6294.2588 | L34: 5481.7798 | M34: 4765.3748 | V34: 1 | W34: 1
D35: =$D$70 -> AGR_LIVESTOCK_FOOD | N35: 1 | O35: 1 | P35: 1 | Q35: 1 | R35: 1 | S35: 1 | T35: 1
D36: =AGR_Comm!$D$93 -> AGR_MACH_WORK | N36: =AGR_SVC!N141 -> 4.4287131e-05 | O36: =AGR_SVC!AP141 -> 4.3333964e-05 | P36: =AGR_SVC!BD141 -> 4.1646863e-05 | Q36: =AGR_SVC!BR141 -> 4.4469246e-05 | R36: =AGR_SVC!CF141 -> 4.5576506e-05 | S36: =AGR_SVC!CT141 -> 4.5466736e-05 | T36: =AGR_SVC!AB141 -> 4.44051e-05
D37: =AGR_Comm!$D$95 -> AGR_LIV_HT | N37: =AGR_SVC!P141 -> 0.00033450464 | O37: =AGR_SVC!AR141 -> 0.00032670953 | P37: =AGR_SVC!BF141 -> 0.0003309204 | Q37: =AGR_SVC!BT141 -> 0.00037561743 | R37: =AGR_SVC!CH141 -> 0.00041378383 | S37: =AGR_SVC!CV141 -> 0.00045021158 | T37: =AGR_SVC!AD141 -> 0.00048924988
D38: =AGR_Comm!$D$96 -> AGR_LIV_ELC_SVC | N38: =AGR_SVC!Q141 -> 9.1653399e-05 | O38: =AGR_SVC!AS141 -> 0.00010091144 | P38: =AGR_SVC!BG141 -> 0.00016040994 | Q38: =AGR_SVC!BU141 -> 0.00025471445 | R38: =AGR_SVC!CI141 -> 0.00036900248 | S38: =AGR_SVC!CW141 -> 0.00050831775 | T38: =AGR_SVC!AE141 -> 0.00068208169
D39: =AGR_Comm!$D$97 -> AGR_OTH_SVC | N39: =AGR_SVC!R141 -> 0.00030204255 | O39: =AGR_SVC!AT141 -> 0.00029957054 | P39: =AGR_SVC!BH141 -> 0.00032053507 | Q39: =AGR_SVC!BV141 -> 0.0003851766 | R39: =AGR_SVC!CJ141 -> 0.00045029562 | S39: =AGR_SVC!CX141 -> 0.00052133337 | T39: =AGR_SVC!AF141 -> 0.00060465178
E40: AGR_DEM_LIV_SWINE
E41: AGR_LIV_MANURE_SWINE | U41: =Y41*Z41 -> 1.033 | Y41: 2.066 | Z41: 0.5 | AB41: =U41*M34 -> 4922.6322 | AD41: =AB41/AB64 -> 0.24440162
F42: AGR_CH4_ENT | U42: 0.0015
F43: AGR_CH4_MAN | U43: 0.00424
F44: AGR_N2O | U44: 0.00026
B45: AGR_EX_LIV_GOAT | C45: AGR_LIV_GOAT | G45: =P75/1000 -> 64.18 | H45: 64.18 | I45: 60.493622 | J45: 50.76689 | K45: 43.789252 | L45: 38.136824 | M45: 33.152784 | V45: 1 | W45: 1
D46: =$D$70 -> AGR_LIVESTOCK_FOOD | N46: 1 | O46: 1 | P46: 1 | Q46: 1 | R46: 1 | S46: 1 | T46: 1
E47: AGR_DEM_LIV_GOAT
B48: \I: | E48: AGR_LIV_MANURE_GOAT | U48: =Y48*Z48 -> 0 | Y48: 0.765 | Z48: 0 | AB48: =U48*M45 -> 0
F49: AGR_CH4_ENT | U49: 0.005
F50: AGR_CH4_MAN | U50: 0.00161 | AF50: file:///C:/Users/gabry/Downloads/2022_Estimation-of-CH4-emissions-from-manure-management-in-China_CCAC_CH4dla_cattle__shieep_swine_goat.pdf
F51: AGR_N2O | U51: 1.8e-05
B52: AGR_EX_LIV_POULTRY | C52: AGR_LIV_POULTRY | G52: =K79/1000 -> 268862.57 | H52: 272993.99 | I52: 257313.73 | J52: 215940.42 | K52: 186260.56 | L52: 162217.57 | M52: 141017.62 | V52: 1 | W52: 1
D53: =$D$70 -> AGR_LIVESTOCK_FOOD | N53: 1 | O53: 1 | P53: 1 | Q53: 1 | R53: 1 | S53: 1 | T53: 1
D54: =AGR_Comm!$D$93 -> AGR_MACH_WORK | N54: =AGR_SVC!N142 -> 2.4603962e-06 | O54: =AGR_SVC!AP142 -> 2.4074424e-06 | P54: =AGR_SVC!BD142 -> 2.3137146e-06 | Q54: =AGR_SVC!BR142 -> 2.4705137e-06 | R54: =AGR_SVC!CF142 -> 2.5320281e-06 | S54: =AGR_SVC!CT142 -> 2.5259298e-06 | T54: =AGR_SVC!AB142 -> 2.46695e-06
D55: =AGR_Comm!$D$95 -> AGR_LIV_HT | N55: =AGR_SVC!P142 -> 2.6976181e-05 | O55: =AGR_SVC!AR142 -> 2.6347543e-05 | P55: =AGR_SVC!BF142 -> 2.6687129e-05 | Q55: =AGR_SVC!BT142 -> 3.0291728e-05 | R55: =AGR_SVC!CH142 -> 3.3369664e-05 | S55: =AGR_SVC!CV142 -> 3.6307386e-05 | T55: =AGR_SVC!AD142 -> 3.9455636e-05
D56: =AGR_Comm!$D$96 -> AGR_LIV_ELC_SVC | N56: =AGR_SVC!Q142 -> 5.4992039e-06 | O56: =AGR_SVC!AS142 -> 6.0546864e-06 | P56: =AGR_SVC!BG142 -> 9.6245965e-06 | Q56: =AGR_SVC!BU142 -> 1.5282867e-05 | R56: =AGR_SVC!CI142 -> 2.2140149e-05 | S56: =AGR_SVC!CW142 -> 3.0499065e-05 | T56: =AGR_SVC!AE142 -> 4.0924902e-05
D57: =AGR_Comm!$D$97 -> AGR_OTH_SVC | N57: =AGR_SVC!R142 -> 7.5510638e-06 | O57: =AGR_SVC!AT142 -> 7.4892634e-06 | P57: =AGR_SVC!BH142 -> 8.0133768e-06 | Q57: =AGR_SVC!BV142 -> 9.629415e-06 | R57: =AGR_SVC!CJ142 -> 1.1257391e-05 | S57: =AGR_SVC!CX142 -> 1.3033334e-05 | T57: =AGR_SVC!AF142 -> 1.5116295e-05
E58: AGR_DEM_LIV_POULTRY
E59: AGR_LIV_MANURE_POULTRY | U59: =Y59*Z59 -> 0.01 | Y59: 0.02 | Z59: 0.5 | AB59: =U59*M52 -> 1410.1762 | AD59: =AB59/AB64 -> 0.070013223
F60: AGR_CH4_MAN | U60: =0.012/1000 -> 1.2e-05
F61: AGR_N2O | U61: 0.00025
AB63: =SUM(AB12:AB59) -> 20188.896
AB64: =AB63-AB30 -> 20141.569
D67: ~FI_T: PL | I67: Dane wejściowe
B68: TechName | C68: *TechDesc | D68: Comm-OUT | E68: Cost | I68: Zwierzęta gospodarskie w 2024 r. | N68: GUS
B69: * Technology name | C69: Technology description | D69: Commodity output | E69: 100 IPI / thousand vehicle
B70: =AGR_Proc!D31 -> AGR_IMP_DUMMY_FOOD_LIV | C70: =AGR_Proc!E31 -> Dummy Energy Import | D70: =AGR_Comm!D62 -> AGR_LIVESTOCK_FOOD | E70: 0.001 | I70: TABL. 3. ZWIERZĘTA GOSPODARSKIE WEDŁUG REGIONÓW I WOJEWÓDZTW W GRUDNIU 2024 R. a/
I72: Regiony/Województwa | J72: Bydło | L72: Świnie | N72: Owce | O72: Drób kurzy | P72: Kozyb Goats
J73: ogółem | K73: w tym krowy | L73: ogółem | M73: w tym lochy
J74: w sztukach
I75: Polska................................................. | J75: 6190927 | K75: 2101159 | L75: 9078250 | M75: 599707 | N75: 269538 | O75: 244679548 | P75: 64180
I76: TABL. 12. DRÓB WEDŁUG STANU W GRUDNIU ORAZ WEDŁUG WOJEWÓDZTW W 2024 R.
I77: Województwa | J77: Drób ogółem | L77: W tym drób kurzy
J78: w sztukach
I79: Polska.......................................................... | J79: 214987216 | K79: 268862574 | L79: 185713737 | M79: 244679548

Sheet AGR_SVC
B2: Usługi rolnicze | Agricultural services | AG2: Zmienić wartości dla roku bazowego i 2050 w dużych tabelach niżej - interpolacja i obliczenie nowych wartości formułami
E4: ~FI_T:PL | AO4: Interpolacja
B5: TechName | C5: *TechDesc | D5: Comm-IN | E5: Comm-OUT | F5: Share-I~2024 | G5: Share-I~2025 | H5: Share-I~2030 | I5: Share-I~2035 | J5: Share-I~2040 | K5: Share-I~2045 | L5: Share-I~2050 | M5: Stock~2024 | N5: Stock~2025 | O5: Stock~2030 | P5: Stock~2035 | Q5: Stock~2040 | R5: Stock~2045 | S5: Stock~2050 | T5: ACTFLO | U5: CEFF | V5: VAROM | W5: FIXOM | X5: Cap2Act | Y5: Share-I~0 | AA5: Check | AC5: Check | AF5: Paliwo/nośnik | AG5: 2024 | AH5: 2025 | AI5: 2030 | AJ5: 2035 | AK5: 2040 | AL5: 2045 | AM5: 2050
B6: * Technology name | C6: Technology description | D6: Commodity input | E6: Commodity output | F6: Fuel share | U6: % | X6: PJ/PJ | AA6: 2024 | AC6: 2050
B7: =AGR_Proc!D72 -> AGR_PRC_MECH_WORK | C7: Mechanical Work for Agriculture | D7: =SECTF!E12 -> AGR_OIL_GSL | F7: =N65/N70 -> 0.0012003485 | G7: =AP65/AP70 -> 0.0012226855 | H7: =BD65/BD70 -> 0.0013490979 | I7: =BR65/BR70 -> 0.0015067234 | J7: =CF65/CF70 -> 0.0017087503 | K7: =CT65/CT70 -> 0.0019770157 | L7: =AB65/AB70 -> 0.0023504832 | M7: =N104 -> 23.352102 | N7: =AP104 -> 22.920578 | O7: =BD104 -> 20.762963 | P7: =BR104 -> 18.605347 | Q7: =CF104 -> 16.447731 | R7: =CT104 -> 14.290116 | S7: =AB104 -> 12.1325 | U7: =N84 -> 0.25 | X7: 1 | Y7: 1 | AA7: =M7*X7/(F7*U7+F8*U8+F9*U9) -> 77.330809 | AB7: =AA7=N72 -> TRUE | AC7: =S7*X7/(L7*U7+L8*U8+L9*U9) -> 38.29 | AD7: =AC7=AB72 -> TRUE | AF7: Węgiel kamienny en. | AG7: =G57 -> 13000 | AH7: =ROUND(AG7+AO7, 6) -> 12500 | AI7: =ROUND(AH7+(5*AO7),6) -> 10000 | AJ7: =ROUND(AI7+(5*AO7),6) -> 7500 | AK7: =ROUND(AJ7+(5*AO7),6) -> 5000 | AL7: =ROUND(AK7+(5*AO7),6) -> 2500 | AM7: =U57 -> 0 | AO7: =(AM7-AG7)/26 -> -500
D8: =SECTF!E14 -> AGR_OIL_DSL | F8: =N66/N70 -> 0.99472624 | G8: =AP66/AP70 -> 0.99412364 | H8: =BD66/BD70 -> 0.9907133 | I8: =BR66/BR70 -> 0.98646091 | J8: =CF66/CF70 -> 0.98101066 | K8: =CT66/CT70 -> 0.97377344 | L8: =AB66/AB70 -> 0.96369809 | U8: =N85 -> 0.3 | Y8: 1 | AF8: Węgiel brunatny | AG8: =G58 -> 160 | AH8: =ROUND(AG8+AO8, 6) -> 153.84615 | AI8: =ROUND(AH8+(5*AO8),6) -> 123.07692 | AJ8: =ROUND(AI8+(5*AO8),6) -> 92.307692 | AK8: =ROUND(AJ8+(5*AO8),6) -> 61.538461 | AL8: =ROUND(AK8+(5*AO8),6) -> 30.76923 | AM8: =U58 -> 0 | AO8: =(AM8-AG8)/26 -> -6.1538462
D9: =SECTF!E30 -> AGR_ELC | F9: =N68/N70 -> 0.0040734088 | G9: =AP68/AP70 -> 0.0046536747 | H9: =BD68/BD70 -> 0.0079375973 | I9: =BR68/BR70 -> 0.012032365 | J9: =CF68/CF70 -> 0.017280589 | K9: =CT68/CT70 -> 0.024249544 | L9: =AB68/AB70 -> 0.033951423 | U9: =N87 -> 0.8 | Y9: 1 | AF9: Gaz ziemny razem | AG9: =G59 -> 1847.8184 | AH9: =ROUND(AG9+AO9, 6) -> 1815.21 | AI9: =ROUND(AH9+(5*AO9),6) -> 1652.168 | AJ9: =ROUND(AI9+(5*AO9),6) -> 1489.126 | AK9: =ROUND(AJ9+(5*AO9),6) -> 1326.084 | AL9: =ROUND(AK9+(5*AO9),6) -> 1163.042 | AM9: =U59 -> 1000 | AO9: =(AM9-AG9)/26 -> -32.6084
E10: =AGR_Comm!D93 -> AGR_MACH_WORK | AF10: Torf i drewno | AG10: =G60 -> 16349.378 | AH10: =ROUND(AG10+AO10, 6) -> 16105.171 | AI10: =ROUND(AH10+(5*AO10),6) -> 14884.137 | AJ10: =ROUND(AI10+(5*AO10),6) -> 13663.103 | AK10: =ROUND(AJ10+(5*AO10),6) -> 12442.069 | AL10: =ROUND(AK10+(5*AO10),6) -> 11221.034 | AM10: =U60 -> 10000 | AO10: =(AM10-AG10)/26 -> -244.20685
B11: =AGR_Proc!D73 -> AGR_PRC_DRY_SVC | C11: Crop Drying | D11: =SECTF!E8 -> AGR_HC | F11: =O57/O70 -> 0.17413256 | G11: =AQ57/AQ70 -> 0.16811989 | H11: =BE57/BE70 -> 0.13730349 | I11: =BS57/BS70 -> 0.10517308 | J11: =CG57/CG70 -> 0.071642804 | K11: =CU57/CU70 -> 0.036619123 | L11: =AC57/AC70 -> 0 | M11: =O104 -> 5.5134243 | N11: =AQ104 -> 5.5054657 | O11: =BE104 -> 5.4656725 | P11: =BS104 -> 5.4258794 | Q11: =CG104 -> 5.3860863 | R11: =CU104 -> 5.3462931 | S11: =AC104 -> 5.3065 | U11: =O76 -> 0.65 | X11: 1 | Y11: 1 | AF11: Biogaz | AG11: =G61 -> 556.87786 | AH11: =ROUND(AG11+AO11, 6) -> 823.92102 | AI11: =ROUND(AH11+(5*AO11),6) -> 2159.1368 | AJ11: =ROUND(AI11+(5*AO11),6) -> 3494.3526 | AK11: =ROUND(AJ11+(5*AO11),6) -> 4829.5684 | AL11: =ROUND(AK11+(5*AO11),6) -> 6164.7842 | AM11: =U61 -> 7500 | AO11: =(AM11-AG11)/26 -> 267.04316
D12: =SECTF!E10 -> AGR_BC | F12: =O58/O70 -> 0.00214317 | G12: =AQ58/AQ70 -> 0.0020691679 | H12: =BE58/BE70 -> 0.0016898891 | I12: =BS58/BS70 -> 0.001294438 | J12: =CG58/CG70 -> 0.00088175758 | K12: =CU58/CU70 -> 0.00045069689 | L12: =AC58/AC70 -> 0 | U12: =O77 -> 0.6 | Y12: 1 | AF12: Paliwa odpadowe i ciekłe bio. | AG12: =G62 -> 41.77884 | AH12: =ROUND(AG12+AO12, 6) -> 136.32581 | AI12: =ROUND(AH12+(5*AO12),6) -> 609.06065 | AJ12: =ROUND(AI12+(5*AO12),6) -> 1081.7955 | AK12: =ROUND(AJ12+(5*AO12),6) -> 1554.5303 | AL12: =ROUND(AK12+(5*AO12),6) -> 2027.2652 | AM12: =U62 -> 2500 | AO12: =(AM12-AG12)/26 -> 94.546968
D13: =SECTF!E20 -> AGR_NAT_GAS | F13: =O59/O70 -> 0.11138031 | G13: =AQ59/AQ70 -> 0.10986225 | H13: =BE59/BE70 -> 0.10208179 | I13: =BS59/BS70 -> 0.093969585 | J13: =CG59/CG70 -> 0.085503938 | K13: =CU59/CU70 -> 0.076661241 | L13: =AC59/AC70 -> 0.06741573 | U13: =O78 -> 0.8 | Y13: 1 | AF13: Brykiety, koks i półkoks | AG13: =G63 -> 47.0832 | AH13: =ROUND(AG13+AO13, 6) -> 45.272308 | AI13: =ROUND(AH13+(5*AO13),6) -> 36.217846 | AJ13: =ROUND(AI13+(5*AO13),6) -> 27.163384 | AK13: =ROUND(AJ13+(5*AO13),6) -> 18.108922 | AL13: =ROUND(AK13+(5*AO13),6) -> 9.05446 | AM13: =U63 -> 0 | AO13: =(AM13-AG13)/26 -> -1.8108923
D14: =SECTF!E24 -> AGR_BIOM | F14: =O60/O70 -> 0.21899685 | G14: =AQ60/AQ70 -> 0.21660797 | H14: =BE60/BE70 -> 0.2043644 | I14: =BS60/BS70 -> 0.19159876 | J14: =CG60/CG70 -> 0.17827693 | K14: =CU60/CU70 -> 0.16436177 | L14: =AC60/AC70 -> 0.14981273 | U14: =O79 -> 0.68 | Y14: 1 | AF14: Gaz ciekły | AG14: =G64 -> 1840 | AH14: =ROUND(AG14+AO14, 6) -> 1788.4615 | AI14: =ROUND(AH14+(5*AO14),6) -> 1530.7692 | AJ14: =ROUND(AI14+(5*AO14),6) -> 1273.0769 | AK14: =ROUND(AJ14+(5*AO14),6) -> 1015.3846 | AL14: =ROUND(AK14+(5*AO14),6) -> 757.69231 | AM14: =U64 -> 500 | AO14: =(AM14-AG14)/26 -> -51.538462
D15: =SECTF!E22 -> AGR_BIOG | F15: =O61/O70 -> 0.0074592743 | G15: =AQ61/AQ70 -> 0.011081401 | H15: =BE61/BE70 -> 0.029645702 | I15: =BS61/BS70 -> 0.049001579 | J15: =CG61/CG70 -> 0.069200764 | K15: =CU61/CU70 -> 0.090299597 | L15: =AC61/AC70 -> 0.11235955 | U15: =O80 -> 0.75 | Y15: 1 | AF15: Benzyny silnikowe i lotnicze | AG15: =G65 -> 103.13769 | AH15: =ROUND(AG15+AO15, 6) -> 103.01701 | AI15: =ROUND(AH15+(5*AO15),6) -> 102.41361 | AJ15: =ROUND(AI15+(5*AO15),6) -> 101.81021 | AK15: =ROUND(AJ15+(5*AO15),6) -> 101.20681 | AL15: =ROUND(AK15+(5*AO15),6) -> 100.6034 | AM15: =U65 -> 100 | AO15: =(AM15-AG15)/26 -> -0.12068046
D16: =SECTF!E33 -> AGR_OTH_FUE | F16: =(O62+O63)/O70 -> 0.0011902903 | G16: =(AQ62+AQ63)/AQ70 -> 0.0024424205 | H16: =(BE62+BE63)/BE70 -> 0.0088598989 | I16: =(BS62+BS63)/BS70 -> 0.015551017 | J16: =(CG62+CG63)/CG70 -> 0.022533657 | K16: =(CU62+CU63)/CU70 -> 0.029827296 | L16: =(AC62+AC63)/AC70 -> 0.037453184 | U16: =(O81+O82)/2 -> 0.65 | Y16: 1 | AF16: Oleje napędowe | AG16: =G66 -> 85469.984 | AH16: =ROUND(AG16+AO16, 6) -> 83759.6 | AI16: =ROUND(AH16+(5*AO16),6) -> 75207.68 | AJ16: =ROUND(AI16+(5*AO16),6) -> 66655.76 | AK16: =ROUND(AJ16+(5*AO16),6) -> 58103.84 | AL16: =ROUND(AK16+(5*AO16),6) -> 49551.92 | AM16: =U66 -> 41000 | AO16: =(AM16-AG16)/26 -> -1710.384
D17: =SECTF!E16 -> AGR_OIL_LPG | F17: =O64/O70 -> 0.086262591 | G17: =AQ64/AQ70 -> 0.08418927 | H17: =BE64/BE70 -> 0.073562985 | I17: =BS64/BS70 -> 0.062483599 | J17: =CG64/CG70 -> 0.0509215 | K17: =CU64/CU70 -> 0.038844439 | L17: =AC64/AC70 -> 0.026217228 | U17: =O83 -> 0.8 | Y17: 1 | AF17: Oleje opałowe | AG17: =G67 -> 3094.6173 | AH17: =ROUND(AG17+AO17, 6) -> 2975.5936 | AI17: =ROUND(AH17+(5*AO17),6) -> 2380.4749 | AJ17: =ROUND(AI17+(5*AO17),6) -> 1785.3562 | AK17: =ROUND(AJ17+(5*AO17),6) -> 1190.2374 | AL17: =ROUND(AK17+(5*AO17),6) -> 595.11872 | AM17: =U67 -> 0 | AO17: =(AM17-AG17)/26 -> -119.02374
D18: =SECTF!E14 -> AGR_OIL_DSL | F18: =O66/O70 -> 0.11448544 | G18: =AQ66/AQ70 -> 0.11265324 | H18: =BE66/BE70 -> 0.10326277 | I18: =BS66/BS70 -> 0.093471892 | J18: =CG66/CG70 -> 0.08325444 | K18: =CU66/CU70 -> 0.072581915 | L18: =AC66/AC70 -> 0.061423221 | U18: =O85 -> 0.75 | Y18: 1 | AA18: =M11*X11/(F11*U11+F12*U12+F13*U13+F14*U14+F15*U15+F16*U16+F17*U17+F18*U18+F19*U19+F20*U20) -> 7.4655769 | AB18: =AA18=O72 -> TRUE | AC18: =S11*X11/(L11*U11+L12*U12+L13*U13+L14*U14+L15*U15+L16*U16+L17*U17+L18*U18+L19*U19+L20*U20) -> 6.675 | AD18: =AC18=AC72 -> TRUE | AF18: Energia elektryczna | AG18: =G68 -> 6300 | AH18: =ROUND(AG18+AO18, 6) -> 7057.6923 | AI18: =ROUND(AH18+(5*AO18),6) -> 10846.154 | AJ18: =ROUND(AI18+(5*AO18),6) -> 14634.615 | AK18: =ROUND(AJ18+(5*AO18),6) -> 18423.077 | AL18: =ROUND(AK18+(5*AO18),6) -> 22211.538 | AM18: =U68 -> 26000 | AO18: =(AM18-AG18)/26 -> 757.69231
D19: =SECTF!E18 -> AGR_OIL_FUE | F19: =O67/O70 -> 0.16580727 | G19: =AQ67/AQ70 -> 0.16008207 | H19: =BE67/BE70 -> 0.130739 | I19: =BS67/BS70 -> 0.10014475 | J19: =CG67/CG70 -> 0.068217558 | K19: =CU67/CU70 -> 0.034868361 | L19: =AC67/AC70 -> 0 | U19: =O86 -> 0.75 | Y19: 1 | AF19: Ciepło | AG19: =G69 -> 620 | AH19: =ROUND(AG19+AO19, 6) -> 711.53846 | AI19: =ROUND(AH19+(5*AO19),6) -> 1169.2308 | AJ19: =ROUND(AI19+(5*AO19),6) -> 1626.9231 | AK19: =ROUND(AJ19+(5*AO19),6) -> 2084.6154 | AL19: =ROUND(AK19+(5*AO19),6) -> 2542.3077 | AM19: =U69 -> 3000 | AO19: =(AM19-AG19)/26 -> 91.538462
D20: =SECTF!E30 -> AGR_ELC | F20: =O68/O70 -> 0.11814224 | G20: =AQ68/AQ70 -> 0.13289231 | H20: =BE68/BE70 -> 0.20849007 | I20: =BS68/BS70 -> 0.28731129 | J20: =CG68/CG70 -> 0.36956665 | K20: =CU68/CU70 -> 0.45548556 | L20: =AC68/AC70 -> 0.54531835 | U20: =O87 -> 0.85 | Y20: 1 | AF20: Suma | AG20: =SUM(AG7:AG19) -> 129430.68 | AH20: =SUM(AH7:AH19) -> 127975.65 | AI20: =SUM(AI7:AI19) -> 120700.52 | AJ20: =SUM(AJ7:AJ19) -> 113425.39 | AK20: =SUM(AK7:AK19) -> 106150.26 | AL20: =SUM(AL7:AL19) -> 98875.13 | AM20: =SUM(AM7:AM19) -> 91600
E21: =AGR_Comm!D94 -> AGR_DRY_SVC
B22: =AGR_Proc!D74 -> AGR_PRC_LIV_HT | C22: Livestock Space Heating | D22: =SECTF!E8 -> AGR_HC | F22: =P57/P70 -> 0.39642403 | G22: =AR57/AR70 -> 0.38534184 | H22: =BF57/BF70 -> 0.32608831 | I22: =BT57/BT70 -> 0.25956632 | J22: =CH57/CH70 -> 0.18435111 | K22: =CV57/CV70 -> 0.098619453 | L22: =AD57/AD70 -> 0 | M22: =P104 -> 10.73698 | N22: =AR104 -> 10.640598 | O22: =BF104 -> 10.158688 | P22: =BT104 -> 9.6767787 | Q22: =CH104 -> 9.1948691 | R22: =CV104 -> 8.7129596 | S22: =AD104 -> 8.23105 | U22: =P76 -> 0.7 | X22: 1 | Y22: 1
D23: =SECTF!E10 -> AGR_BC | F23: =P58/P70 -> 0.0043369467 | G23: =AR58/AR70 -> 0.0042157056 | H23: =BF58/BF70 -> 0.0035674618 | I23: =BT58/BT70 -> 0.0028396999 | J23: =CH58/CH70 -> 0.0020168326 | K23: =CV58/CV70 -> 0.0010789136 | L23: =AD58/AD70 -> 0 | U23: =P77 -> 0.6 | Y23: 1
D24: =SECTF!E20 -> AGR_NAT_GAS | F24: =P59/P70 -> 0.037565109 | G24: =AR59/AR70 -> 0.037305406 | H24: =BF59/BF70 -> 0.035916844 | I24: =BT59/BT70 -> 0.034357952 | J24: =CH59/CH70 -> 0.032595341 | K24: =CV59/CV70 -> 0.030586284 | L24: =AD59/AD70 -> 0.028275212 | U24: =P78 -> 0.85 | Y24: 1
D25: =SECTF!E24 -> AGR_BIOM | F25: =P60/P70 -> 0.38776927 | G25: =AR60/AR70 -> 0.38615088 | H25: =BF60/BF70 -> 0.37749779 | I25: =BT60/BT70 -> 0.36778325 | J25: =CH60/CH70 -> 0.35679919 | K25: =CV60/CV70 -> 0.34427937 | L25: =AD60/AD70 -> 0.32987747 | U25: =P79 -> 0.7 | Y25: 1
D26: =SECTF!E22 -> AGR_BIOG | F26: =P61/P70 -> 0.020755192 | G26: =AR61/AR70 -> 0.031043588 | H26: =BF61/BF70 -> 0.08605291 | I26: =BT61/BT70 -> 0.14781006 | J26: =CH61/CH70 -> 0.21763776 | K26: =CV61/CV70 -> 0.29722863 | L26: =AD61/AD70 -> 0.38878417 | U26: =P80 -> 0.8 | Y26: 1
D27: =SECTF!E33 -> AGR_OTH_FUE | F27: =(P62+P63)/P70 -> 0.0025682162 | G27: =(AR62+AR63)/Q70 -> 0.018703739 | H27: =(BF62+BF63)/BF70 -> 0.018835026 | I27: =(BT62+BT63)/BT70 -> 0.034219818 | J27: =(CH62+CH63)/CH70 -> 0.051615126 | K27: =(CV62+CV63)/CV70 -> 0.071442612 | L27: =(AD62+AD63)/AD70 -> 0.094250707 | U27: =(P81+P82)/2 -> 0.7 | Y27: 1
D28: =SECTF!E16 -> AGR_OIL_LPG | F28: =P64/P70 -> 0.056109248 | G28: =AR64/AR70 -> 0.055133525 | H28: =BF64/BF70 -> 0.049916595 | I28: =BT64/BT70 -> 0.044059719 | J28: =CH64/CH70 -> 0.037437456 | K28: =CV64/CV70 -> 0.02988928 | L28: =AD64/AD70 -> 0.021206409 | U28: =P83 -> 0.85 | Y28: 1
D29: =SECTF!E18 -> AGR_OIL_FUE | F29: =P67/P70 -> 0.073397135 | G29: =AR67/AR70 -> 0.071345289 | H29: =BF67/BF70 -> 0.060374613 | I29: =BT67/BT70 -> 0.048058198 | J29: =CH67/CH70 -> 0.034132247 | K29: =CV67/CV70 -> 0.018259199 | L29: =AD67/AD70 -> 0 | U29: =P86 -> 0.8 | Y29: 1 | AA29: =M22*X22/(F22*U22+F23*U23+F24*U24+F25*U25+F26*U26+F27*U27+F28*U28+F29*U29+F30*U30+F31*U31) -> 14.756926 | AB29: =AA29=P72 -> TRUE | AC29: =S22*X22/(L22*U22+L23*U23+L24*U24+L25*U25+L26*U26+L27*U27+L28*U28+L29*U29+L30*U30+L31*U31) -> 10.61 | AD29: =AC29=AD72 -> TRUE
D30: =SECTF!E30 -> AGR_ELC | F30: =P68/P70 -> 0.0042691819 | G30: =AR68/AR70 -> 0.0048348874 | H30: =BF68/BF70 -> 0.0078595643 | I30: =BT68/BT70 -> 0.011255269 | J30: =CH68/CH70 -> 0.015094732 | K30: =CV68/CV70 -> 0.01947102 | L30: =AD68/AD70 -> 0.024505184 | U30: =P87 -> 0.98 | Y30: 1
D31: =SECTF!E32 -> AGR_DH | F31: =P69/P70 -> 0.016805668 | G31: =AR69/AR70 -> 0.019497638 | H31: =BF69/BF70 -> 0.033890887 | I31: =BT69/BT70 -> 0.050049712 | J31: =CH69/CH70 -> 0.068320205 | K31: =CV69/CV70 -> 0.089145242 | L31: =AD69/AD70 -> 0.11310085 | U31: =P88 -> 0.9 | Y31: 1 | AA31: =M33*X33/(F33*U33+F34*U34) -> 4.0046998 | AB31: =AA31=Q72 -> TRUE | AC31: =S33*X33/(L33*U33+L34*U34) -> 13.41 | AD31: =AC31=AE72 -> TRUE
E32: =AGR_Comm!D95 -> AGR_LIV_HT
B33: =AGR_Proc!D75 -> AGR_PRC_LIV_ELC_SVC | C33: Livestock Electricity Services | D33: =SECTF!E14 -> AGR_OIL_DSL | F33: =Q66/Q70 -> 0.21342419 | G33: =AS66/AS70 -> 0.19182574 | H33: =BG66/BG70 -> 0.12179078 | I33: =BU66/BU70 -> 0.083488082 | J33: =CI66/CI70 -> 0.059334576 | K33: =CW66/CW70 -> 0.042712428 | L33: =AE66/AE70 -> 0.030574198 | M33: =Q104 -> 3.380769 | N33: =AS104 -> 3.7549971 | O33: =BG104 -> 5.6261377 | P33: =BU104 -> 7.4972782 | Q33: =CI104 -> 9.3684188 | R33: =CW104 -> 11.239559 | S33: =AE104 -> 13.1107 | U33: =Q85 -> 0.27 | X33: 1 | Y33: 1
D34: =SECTF!E30 -> AGR_ELC | F34: =Q68/Q70 -> 0.78657581 | G34: =AS68/AS70 -> 0.80817426 | H34: =BG68/BG70 -> 0.87820922 | I34: =BU68/BU70 -> 0.91651192 | J34: =CI68/CI70 -> 0.94066542 | K34: =CW68/CW70 -> 0.95728757 | L34: =AE68/AE70 -> 0.9694258 | U34: =Q87 -> 1 | Y34: 1
E35: =AGR_Comm!D96 -> AGR_LIV_ELC_SVC
B36: =AGR_Proc!D76 -> AGR_PRC_OTH_SVC | C36: Other Services for Agriculture | D36: =SECTF!E8 -> AGR_HC | F36: =R57/R70 -> 0.22610737 | G36: =AT57/AT70 -> 0.21846893 | H36: =BH57/BH70 -> 0.17913374 | I36: =BV57/BV70 -> 0.13778648 | J36: =CJ57/CJ70 -> 0.094268684 | K36: =CX57/CX70 -> 0.048404848 | L36: =AF57/AF70 -> 0 | M36: =R104 -> 16.036933 | N36: =AT104 -> 16.06432 | O36: =BH104 -> 16.201256 | P36: =BV104 -> 16.338192 | Q36: =CJ104 -> 16.475128 | R36: =CX104 -> 16.612064 | S36: =AF104 -> 16.749 | U36: =R76 -> 0.7 | X36: 1 | Y36: 1
D37: =SECTF!E10 -> AGR_BC | F37: =R58/R70 -> 0.0030920667 | G37: =AT58/AT70 -> 0.0029876092 | H37: =BH58/BH70 -> 0.0024496922 | I37: =BV58/BV70 -> 0.0018842595 | J37: =CJ58/CJ70 -> 0.0012891444 | K37: =CX58/CX70 -> 0.00066194662 | L37: =AF58/AF70 -> 0 | U37: =R77 -> 0.6 | Y37: 1
D38: =SECTF!E20 -> AGR_NAT_GAS | F38: =R59/R70 -> 0.01785493 | G38: =AT59/AT70 -> 0.017625199 | H38: =BH59/BH70 -> 0.016442169 | I38: =BV59/BV70 -> 0.015198624 | J38: =CJ59/CJ70 -> 0.013889799 | K38: =CX59/CX70 -> 0.012510416 | L38: =AF59/AF70 -> 0.01105461 | U38: =R78 -> 0.85 | Y38: 1
D39: =SECTF!E24 -> AGR_BIOM | F39: =R60/R70 -> 0.3475544 | G39: =AT60/AT70 -> 0.3440291 | H39: =BH60/BH70 -> 0.32587515 | I39: =BV60/BV70 -> 0.30679257 | J39: =CJ60/CJ70 -> 0.28670826 | K39: =CX60/CX70 -> 0.2655412 | L39: =AF60/AF70 -> 0.24320141 | U39: =R79 -> 0.7 | Y39: 1
D40: =SECTF!E22 -> AGR_BIOG | F40: =R61/R70 -> 0.0075333276 | G40: =AT61/AT70 -> 0.011200071 | H40: =BH61/BH70 -> 0.030082443 | I40: =BV61/BV70 -> 0.049930692 | J40: =CJ61/CJ70 -> 0.070820876 | K40: =CX61/CX70 -> 0.092837248 | L40: =AF61/AF70 -> 0.1160734 | U40: =R80 -> 0.8 | Y40: 1
D41: =SECTF!E33 -> AGR_OTH_FUE | F41: =(R62+R63)/R70 -> 0.0016263057 | G41: =(AT62+AT63)/AT70 -> 0.003438621 | H41: =(BH62+BH63)/BH70 -> 0.012771374 | I41: =(BV62+BV63)/BV70 -> 0.02258152 | J41: =(CJ62+CJ63)/CJ70 -> 0.032906649 | K41: =(CX62+CX63)/CX70 -> 0.043788406 | L41: =(AF62+AF63)/AF70 -> 0.055273049 | U41: =(R81+R82)/2 -> 0.7 | Y41: 1
D42: =SECTF!E16 -> AGR_OIL_LPG | F42: =R64/R70 -> 0.014223507 | G42: =AT64/AT70 -> 0.013892383 | H42: =BH64/BH70 -> 0.012187219 | I42: =BV64/BV70 -> 0.010394832 | J42: =CJ64/CJ70 -> 0.008508353 | K42: =CX64/CX70 -> 0.0065201744 | L42: =AF64/AF70 -> 0.0044218439 | U42: =R83 -> 0.85 | Y42: 1
D43: =SECTF!E12 -> AGR_OIL_GSL | F43: =R65/R70 -> 0.00039863577 | G43: =AT65/AT70 -> 0.00040010695 | H43: =BH65/BH70 -> 0.00040768297 | I43: =BV65/BV70 -> 0.00041564651 | J43: =CJ65/CJ70 -> 0.00042402811 | K43: =CX65/CX70 -> 0.00043286155 | L43: =AF65/AF70 -> 0.00044218439 | U43: =R84 -> 0.25 | Y43: 1
D44: =SECTF!E14 -> AGR_OIL_DSL | F44: =R66/R70 -> 0.26427889 | G44: =AT66/AT70 -> 0.26025059 | H44: =BH66/BH70 -> 0.23950637 | I44: =BV66/BV70 -> 0.21770103 | J44: =CJ66/CJ70 -> 0.19475102 | K44: =CX66/CX70 -> 0.17056378 | L44: =AF66/AF70 -> 0.14503648 | U44: =R85 -> 0.3 | Y44: 1
D45: =SECTF!E18 -> AGR_OIL_FUE | F45: =R67/R70 -> 0.029902385 | G45: =AT67/AT70 -> 0.028892211 | H45: =BH67/BH70 -> 0.023690188 | I45: =BV67/BV70 -> 0.018222069 | J45: =CJ67/CJ70 -> 0.012466902 | K45: =CX67/CX70 -> 0.0064014736 | L45: =AF67/AF70 -> 0 | U45: =R86 -> 0.8 | Y45: 1 | AA45: =M36*X36/(F36*U36+F37*U37+F38*U38+F39*U39+F40*U40+F41*U41+F42*U42+F43*U43+F44*U44+F45*U45+F46*U46+F47*U47) -> 25.872664 | AB45: =AA45=R72 -> TRUE | AC45: =S36*X36/(L36*U36+L37*U37+L38*U38+L39*U39+L40*U40+L41*U41+L42*U42+L43*U43+L44*U44+L45*U45+L46*U46+L47*U47) -> 22.615 | AD45: =AC45=AF72 -> TRUE
D46: =SECTF!E30 -> AGR_ELC | F46: =R68/R70 -> 0.073050075 | G46: =AT68/AT70 -> 0.082233944 | H46: =BH68/BH70 -> 0.12952748 | I46: =BV68/BV70 -> 0.17924019 | J46: =CJ68/CJ70 -> 0.23156256 | K46: =CX68/CX70 -> 0.28670564 | L46: =AF68/AF70 -> 0.34490382 | U46: =R87 -> 0.9 | Y46: 1
D47: =SECTF!E32 -> AGR_DH | F47: =R69/R70 -> 0.01437811 | G47: =AT69/AT70 -> 0.016581231 | H47: =BH69/BH70 -> 0.027926492 | I47: =BV69/BV70 -> 0.039852089 | J47: =CJ69/CJ70 -> 0.05240372 | K47: =CX69/CX70 -> 0.065632009 | L47: =AF69/AF70 -> 0.07959319 | U47: =R88 -> 0.9 | Y47: 1
E48: =AGR_Comm!D97 -> AGR_OTH_SVC
F53: Rok bazowy 2024 | T53: Prognoza 2050 | AH53: 2025 | AV53: 2030 | BJ53: 2035 | BX53: 2040 | CL53: 2045
B54: GUS gospodarka_paliwowo-energetyczna_w_latach_2023-2024._tablice_w_formacie_xlsx | F54: Dane wejściowe GUS | I54: Udział paliwa/nośnika w dost. usługi | N54: Energia finalna | T54: Dane wejściowe | V54: Udział paliwa/nośnika w dost. usługi | AB54: Energia finalna | AH54: Dane wejściowe GUS | AK54: Udział paliwa/nośnika w dost. usługi | AP54: Energia finalna | AV54: Dane wejściowe GUS | AY54: Udział paliwa/nośnika w dost. usługi | BD54: Energia finalna | BJ54: Dane wejściowe GUS | BM54: Udział paliwa/nośnika w dost. usługi | BR54: Energia finalna | BX54: Dane wejściowe GUS | CA54: Udział paliwa/nośnika w dost. usługi | CF54: Energia finalna | CL54: Dane wejściowe GUS | CO54: Udział paliwa/nośnika w dost. usługi | CT54: Energia finalna
B55: 2024 | C55: Jednostka miary | D55: Rolnictwo | F55: Paliwo/nośnik | G55: TJ | I55: AGR_MACH_WORK | J55: AGR_DRY_SVC | K55: AGR_LIV_HT | L55: AGR_LIV_ELC_SVC | M55: AGR_OTH_SVC | N55: AGR_MACH_WORK | O55: AGR_DRY_SVC | P55: AGR_LIV_HT | Q55: AGR_LIV_ELC_SVC | R55: AGR_OTH_SVC | T55: Paliwo/nośnik | U55: TJ | W55: AGR_MACH_WORK | X55: AGR_DRY_SVC | Y55: AGR_LIV_HT | Z55: AGR_LIV_ELC_SVC | AA55: AGR_OTH_SVC | AB55: AGR_MACH_WORK | AC55: AGR_DRY_SVC | AD55: AGR_LIV_HT | AE55: AGR_LIV_ELC_SVC | AF55: AGR_OTH_SVC | AH55: Paliwo/nośnik | AI55: TJ | AK55: AGR_MACH_WORK | AL55: AGR_DRY_SVC | AM55: AGR_LIV_HT | AN55: AGR_LIV_ELC_SVC | AO55: AGR_OTH_SVC | AP55: AGR_MACH_WORK | AQ55: AGR_DRY_SVC | AR55: AGR_LIV_HT | AS55: AGR_LIV_ELC_SVC | AT55: AGR_OTH_SVC | AV55: Paliwo/nośnik | AW55: TJ | AY55: AGR_MACH_WORK | AZ55: AGR_DRY_SVC | BA55: AGR_LIV_HT | BB55: AGR_LIV_ELC_SVC | BC55: AGR_OTH_SVC | BD55: AGR_MACH_WORK | BE55: AGR_DRY_SVC | BF55: AGR_LIV_HT | BG55: AGR_LIV_ELC_SVC | BH55: AGR_OTH_SVC | BJ55: Paliwo/nośnik | BK55: TJ | BM55: AGR_MACH_WORK | BN55: AGR_DRY_SVC | BO55: AGR_LIV_HT | BP55: AGR_LIV_ELC_SVC | BQ55: AGR_OTH_SVC | BR55: AGR_MACH_WORK | BS55: AGR_DRY_SVC | BT55: AGR_LIV_HT | BU55: AGR_LIV_ELC_SVC | BV55: AGR_OTH_SVC | BX55: Paliwo/nośnik | BY55: TJ | CA55: AGR_MACH_WORK | CB55: AGR_DRY_SVC | CC55: AGR_LIV_HT | CD55: AGR_LIV_ELC_SVC | CE55: AGR_OTH_SVC | CF55: AGR_MACH_WORK | CG55: AGR_DRY_SVC | CH55: AGR_LIV_HT | CI55: AGR_LIV_ELC_SVC | CJ55: AGR_OTH_SVC | CL55: Paliwo/nośnik | CM55: TJ | CO55: AGR_MACH_WORK | CP55: AGR_DRY_SVC | CQ55: AGR_LIV_HT | CR55: AGR_LIV_ELC_SVC | CS55: AGR_OTH_SVC | CT55: AGR_MACH_WORK | CU55: AGR_DRY_SVC | CV55: AGR_LIV_HT | CW55: AGR_LIV_ELC_SVC | CX55: AGR_OTH_SVC
B56: Energia ogółem | C56: TJ | D56: 129449.39 | H56: % | I56: % | N56: TJ | V56: % | W56: % | AB56: TJ | AJ56: % | AK56: % | AP56: TJ | AX56: % | AY56: % | BD56: TJ | BL56: % | BM56: % | BR56: TJ | BZ56: % | CA56: % | CF56: TJ | CN56: % | CO56: % | CT56: TJ
B57: Energia pierwotna | C57: TJ | D57: 31955.871 | F57: Węgiel kamienny en. | G57: =D58 -> 13000 | H57: =G57/$G$70 -> 0.10043987 | I57: 0 | J57: 0.1 | K57: 0.45 | L57: 0 | M57: 0.45 | N57: =I57*$G$57 -> 0 | O57: =J57*$G$57 -> 1300 | P57: =K57*$G$57 -> 5850 | Q57: =L57*$G$57 -> 0 | R57: =M57*$G$57 -> 5850 | T57: Węgiel kamienny en. | U57: 0 | V57: =U57/$U$70 -> 0 | W57: 0 | X57: 0.1 | Y57: 0.45 | Z57: 0 | AA57: 0.45 | AB57: =W57*U57 -> 0 | AC57: =X57*U57 -> 0 | AD57: =Y57*U57 -> 0 | AE57: =Z57*U57 -> 0 | AF57: =AA57*U57 -> 0 | AH57: Węgiel kamienny en. | AI57: =AH7 -> 12500 | AJ57: =AI57/$G$70 -> 0.096576797 | AK57: 0 | AL57: 0.1 | AM57: 0.45 | AN57: 0 | AO57: 0.45 | AP57: =AK57*$AI$57 -> 0 | AQ57: =AL57*$AI$57 -> 1250 | AR57: =AM57*$AI$57 -> 5625 | AS57: =AN57*$AI$57 -> 0 | AT57: =AO57*$AI$57 -> 5625 | AV57: Węgiel kamienny en. | AW57: =AI7 -> 10000 | AX57: =AW57/$G$70 -> 0.077261437 | AY57: 0 | AZ57: 0.1 | BA57: 0.45 | BB57: 0 | BC57: 0.45 | BD57: =AY57*AW57 -> 0 | BE57: =AZ57*AW57 -> 1000 | BF57: =BA57*AW57 -> 4500 | BG57: =BB57*AW57 -> 0 | BH57: =BC57*AW57 -> 4500 | BJ57: Węgiel kamienny en. | BK57: =AJ7 -> 7500 | BL57: =BK57/$G$70 -> 0.057946078 | BM57: 0 | BN57: 0.1 | BO57: 0.45 | BP57: 0 | BQ57: 0.45 | BR57: =BM57*BK57 -> 0 | BS57: =BN57*BK57 -> 750 | BT57: =BO57*BK57 -> 3375 | BU57: =BP57*BK57 -> 0 | BV57: =BQ57*BK57 -> 3375 | BX57: Węgiel kamienny en. | BY57: =AK7 -> 5000 | BZ57: =BY57/$G$70 -> 0.038630719 | CA57: 0 | CB57: 0.1 | CC57: 0.45 | CD57: 0 | CE57: 0.45 | CF57: =CA57*BY57 -> 0 | CG57: =CB57*BY57 -> 500 | CH57: =CC57*BY57 -> 2250 | CI57: =CD57*BY57 -> 0 | CJ57: =CE57*BY57 -> 2250 | CL57: Węgiel kamienny en. | CM57: =AL7 -> 2500 | CN57: =CM57/$G$70 -> 0.019315359 | CO57: 0 | CP57: 0.1 | CQ57: 0.45 | CR57: 0 | CS57: 0.45 | CT57: =CO57*CM57 -> 0 | CU57: =CP57*CM57 -> 250 | CV57: =CQ57*CM57 -> 1125 | CW57: =CR57*CM57 -> 0 | CX57: =CS57*CM57 -> 1125
B58: Węgiel kamienny energetyczny | C58: TJ | D58: 13000 | F58: Węgiel brunatny | G58: =D59 -> 160 | H58: =G58/$G$70 -> 0.001236183 | I58: 0 | J58: 0.1 | K58: 0.4 | L58: 0 | M58: 0.5 | N58: =I58*$G$58 -> 0 | O58: =J58*$G$58 -> 16 | P58: =K58*$G$58 -> 64 | Q58: =L58*$G$58 -> 0 | R58: =M58*$G$58 -> 80 | T58: Węgiel brunatny | U58: 0 | V58: =U58/$U$70 -> 0 | W58: 0 | X58: 0.1 | Y58: 0.4 | Z58: 0 | AA58: 0.5 | AB58: =W58*U58 -> 0 | AC58: =X58*U58 -> 0 | AD58: =Y58*U58 -> 0 | AE58: =Z58*U58 -> 0 | AF58: =AA58*U58 -> 0 | AH58: Węgiel brunatny | AI58: =AH8 -> 153.84615 | AJ58: =AI58/$G$70 -> 0.0011886375 | AK58: 0 | AL58: 0.1 | AM58: 0.4 | AN58: 0 | AO58: 0.5 | AP58: =AK58*$AI$58 -> 0 | AQ58: =AL58*$AI$58 -> 15.384615 | AR58: =AM58*$AI$58 -> 61.538462 | AS58: =AN58*$AI$58 -> 0 | AT58: =AO58*$AI$58 -> 76.923077 | AV58: Węgiel brunatny | AW58: =AI8 -> 123.07692 | AX58: =AW58/$G$70 -> 0.00095091 | AY58: 0 | AZ58: 0.1 | BA58: 0.4 | BB58: 0 | BC58: 0.5 | BD58: =AY58*AW58 -> 0 | BE58: =AZ58*AW58 -> 12.307692 | BF58: =BA58*AW58 -> 49.230769 | BG58: =BB58*AW58 -> 0 | BH58: =BC58*AW58 -> 61.538461 | BJ58: Węgiel brunatny | BK58: =AJ8 -> 92.307692 | BL58: =BK58/$G$70 -> 0.00071318249 | BM58: 0 | BN58: 0.1 | BO58: 0.4 | BP58: 0 | BQ58: 0.5 | BR58: =BM58*BK58 -> 0 | BS58: =BN58*BK58 -> 9.2307692 | BT58: =BO58*BK58 -> 36.923077 | BU58: =BP58*BK58 -> 0 | BV58: =BQ58*BK58 -> 46.153846 | BX58: Węgiel brunatny | BY58: =AK8 -> 61.538461 | BZ58: =BY58/$G$70 -> 0.00047545499 | CA58: 0 | CB58: 0.1 | CC58: 0.4 | CD58: 0 | CE58: 0.5 | CF58: =CA58*BY58 -> 0 | CG58: =CB58*BY58 -> 6.1538461 | CH58: =CC58*BY58 -> 24.615384 | CI58: =CD58*BY58 -> 0 | CJ58: =CE58*BY58 -> 30.76923 | CL58: Węgiel brunatny | CM58: =AL8 -> 30.76923 | CN58: =CM58/$G$70 -> 0.00023772749 | CO58: 0 | CP58: 0.1 | CQ58: 0.4 | CR58: 0 | CS58: 0.5 | CT58: =CO58*CM58 -> 0 | CU58: =CP58*CM58 -> 3.076923 | CV58: =CQ58*CM58 -> 12.307692 | CW58: =CR58*CM58 -> 0 | CX58: =CS58*CM58 -> 15.384615
B59: Węgiel brunatny | C59: TJ | D59: 160 | F59: Gaz ziemny razem | G59: =D60+D61 -> 1847.8184 | H59: =G59/$G$70 -> 0.014276511 | I59: 0 | J59: 0.45 | K59: 0.3 | L59: 0 | M59: 0.25 | N59: =I59*$G$59 -> 0 | O59: =J59*$G$59 -> 831.51828 | P59: =K59*$G$59 -> 554.34552 | Q59: =L59*$G$59 -> 0 | R59: =M59*$G$59 -> 461.9546 | T59: Gaz ziemny razem | U59: 1000 | V59: =U59/$U$70 -> 0.010917031 | W59: 0 | X59: 0.45 | Y59: 0.3 | Z59: 0 | AA59: 0.25 | AB59: =W59*U59 -> 0 | AC59: =X59*U59 -> 450 | AD59: =Y59*U59 -> 300 | AE59: =Z59*U59 -> 0 | AF59: =AA59*U59 -> 250 | AH59: Gaz ziemny razem | AI59: =AH9 -> 1815.21 | AJ59: =AI59/$G$70 -> 0.014024573 | AK59: 0 | AL59: 0.45 | AM59: 0.3 | AN59: 0 | AO59: 0.25 | AP59: =AK59*$AI$59 -> 0 | AQ59: =AL59*$AI$59 -> 816.8445 | AR59: =AM59*$AI$59 -> 544.563 | AS59: =AN59*$AI$59 -> 0 | AT59: =AO59*$AI$59 -> 453.8025 | AV59: Gaz ziemny razem | AW59: =AI9 -> 1652.168 | AX59: =AW59/$G$70 -> 0.012764887 | AY59: 0 | AZ59: 0.45 | BA59: 0.3 | BB59: 0 | BC59: 0.25 | BD59: =AY59*AW59 -> 0 | BE59: =AZ59*AW59 -> 743.4756 | BF59: =BA59*AW59 -> 495.6504 | BG59: =BB59*AW59 -> 0 | BH59: =BC59*AW59 -> 413.042 | BJ59: Gaz ziemny razem | BK59: =AJ9 -> 1489.126 | BL59: =BK59/$G$70 -> 0.011505201 | BM59: 0 | BN59: 0.45 | BO59: 0.3 | BP59: 0 | BQ59: 0.25 | BR59: =BM59*BK59 -> 0 | BS59: =BN59*BK59 -> 670.1067 | BT59: =BO59*BK59 -> 446.7378 | BU59: =BP59*BK59 -> 0 | BV59: =BQ59*BK59 -> 372.2815 | BX59: Gaz ziemny razem | BY59: =AK9 -> 1326.084 | BZ59: =BY59/$G$70 -> 0.010245516 | CA59: 0 | CB59: 0.45 | CC59: 0.3 | CD59: 0 | CE59: 0.25 | CF59: =CA59*BY59 -> 0 | CG59: =CB59*BY59 -> 596.7378 | CH59: =CC59*BY59 -> 397.8252 | CI59: =CD59*BY59 -> 0 | CJ59: =CE59*BY59 -> 331.521 | CL59: Gaz ziemny razem | CM59: =AL9 -> 1163.042 | CN59: =CM59/$G$70 -> 0.0089858296 | CO59: 0 | CP59: 0.45 | CQ59: 0.3 | CR59: 0 | CS59: 0.25 | CT59: =CO59*CM59 -> 0 | CU59: =CP59*CM59 -> 523.3689 | CV59: =CQ59*CM59 -> 348.9126 | CW59: =CR59*CM59 -> 0 | CX59: =CS59*CM59 -> 290.7605
B60: Gaz ziemny wysokometanowy | C60: TJ | D60: 1553.57 | F60: Torf i drewno | G60: =D62 -> 16349.378 | H60: =G60/$G$70 -> 0.12631765 | I60: 0 | J60: 0.1 | K60: 0.35 | L60: 0 | M60: 0.55 | N60: =I60*$G$60 -> 0 | O60: =J60*$G$60 -> 1634.9378 | P60: =K60*$G$60 -> 5722.2824 | Q60: =L60*$G$60 -> 0 | R60: =M60*$G$60 -> 8992.158 | T60: Torf i drewno | U60: 10000 | V60: =U60/$U$70 -> 0.10917031 | W60: 0 | X60: 0.1 | Y60: 0.35 | Z60: 0 | AA60: 0.55 | AB60: =W60*U60 -> 0 | AC60: =X60*U60 -> 1000 | AD60: =Y60*U60 -> 3500 | AE60: =Z60*U60 -> 0 | AF60: =AA60*U60 -> 5500 | AH60: Torf i drewno | AI60: =AH10 -> 16105.171 | AJ60: =AI60/$G$70 -> 0.12443087 | AK60: 0 | AL60: 0.1 | AM60: 0.35 | AN60: 0 | AO60: 0.55 | AP60: =AK60*$AI$60 -> 0 | AQ60: =AL60*$AI$60 -> 1610.5171 | AR60: =AM60*$AI$60 -> 5636.81 | AS60: =AN60*$AI$60 -> 0 | AT60: =AO60*$AI$60 -> 8857.8442 | AV60: Torf i drewno | AW60: =AI10 -> 14884.137 | AX60: =AW60/$G$70 -> 0.11499698 | AY60: 0 | AZ60: 0.1 | BA60: 0.35 | BB60: 0 | BC60: 0.55 | BD60: =AY60*AW60 -> 0 | BE60: =AZ60*AW60 -> 1488.4137 | BF60: =BA60*AW60 -> 5209.448 | BG60: =BB60*AW60 -> 0 | BH60: =BC60*AW60 -> 8186.2754 | BJ60: Torf i drewno | BK60: =AJ10 -> 13663.103 | BL60: =BK60/$G$70 -> 0.1055631 | BM60: 0 | BN60: 0.1 | BO60: 0.35 | BP60: 0 | BQ60: 0.55 | BR60: =BM60*BK60 -> 0 | BS60: =BN60*BK60 -> 1366.3103 | BT60: =BO60*BK60 -> 4782.086 | BU60: =BP60*BK60 -> 0 | BV60: =BQ60*BK60 -> 7514.7065 | BX60: Torf i drewno | BY60: =AK10 -> 12442.069 | BZ60: =BY60/$G$70 -> 0.09612921 | CA60: 0 | CB60: 0.1 | CC60: 0.35 | CD60: 0 | CE60: 0.55 | CF60: =CA60*BY60 -> 0 | CG60: =CB60*BY60 -> 1244.2069 | CH60: =CC60*BY60 -> 4354.724 | CI60: =CD60*BY60 -> 0 | CJ60: =CE60*BY60 -> 6843.1377 | CL60: Torf i drewno | CM60: =AL10 -> 11221.034 | CN60: =CM60/$G$70 -> 0.086695323 | CO60: 0 | CP60: 0.1 | CQ60: 0.35 | CR60: 0 | CS60: 0.55 | CT60: =CO60*CM60 -> 0 | CU60: =CP60*CM60 -> 1122.1034 | CV60: =CQ60*CM60 -> 3927.362 | CW60: =CR60*CM60 -> 0 | CX60: =CS60*CM60 -> 6171.5688
B61: Gaz ziemny zaazotowany | C61: TJ | D61: 294.2484 | F61: BVogaz | G61: =D63 -> 556.87786 | H61: =G61/$G$70 -> 0.0043025184 | I61: 0 | J61: 0.1 | K61: 0.55 | L61: 0 | M61: 0.35 | N61: =I61*$G$61 -> 0 | O61: =J61*$G$61 -> 55.687786 | P61: =K61*$G$61 -> 306.28282 | Q61: =L61*$G$61 -> 0 | R61: =M61*$G$61 -> 194.90725 | T61: Biogaz | U61: 7500 | V61: =U61/$U$70 -> 0.081877729 | W61: 0 | X61: 0.1 | Y61: 0.55 | Z61: 0 | AA61: 0.35 | AB61: =W61*U61 -> 0 | AC61: =X61*U61 -> 750 | AD61: =Y61*U61 -> 4125 | AE61: =Z61*U61 -> 0 | AF61: =AA61*U61 -> 2625 | AH61: BVogaz | AI61: =AH11 -> 823.92102 | AJ61: =AI61/$G$70 -> 0.0063657322 | AK61: 0 | AL61: 0.1 | AM61: 0.55 | AN61: 0 | AO61: 0.35 | AP61: =AK61*$AI$61 -> 0 | AQ61: =AL61*$AI$61 -> 82.392102 | AR61: =AM61*$AI$61 -> 453.15656 | AS61: =AN61*$AI$61 -> 0 | AT61: =AO61*$AI$61 -> 288.37236 | AV61: BVogaz | AW61: =AI11 -> 2159.1368 | AX61: =AW61/$G$70 -> 0.016681801 | AY61: 0 | AZ61: 0.1 | BA61: 0.55 | BB61: 0 | BC61: 0.35 | BD61: =AY61*AW61 -> 0 | BE61: =AZ61*AW61 -> 215.91368 | BF61: =BA61*AW61 -> 1187.5252 | BG61: =BB61*AW61 -> 0 | BH61: =BC61*AW61 -> 755.69788 | BJ61: BVogaz | BK61: =AJ11 -> 3494.3526 | BL61: =BK61/$G$70 -> 0.02699787 | BM61: 0 | BN61: 0.1 | BO61: 0.55 | BP61: 0 | BQ61: 0.35 | BR61: =BM61*BK61 -> 0 | BS61: =BN61*BK61 -> 349.43526 | BT61: =BO61*BK61 -> 1921.8939 | BU61: =BP61*BK61 -> 0 | BV61: =BQ61*BK61 -> 1223.0234 | BX61: BVogaz | BY61: =AK11 -> 4829.5684 | BZ61: =BY61/$G$70 -> 0.03731394 | CA61: 0 | CB61: 0.1 | CC61: 0.55 | CD61: 0 | CE61: 0.35 | CF61: =CA61*BY61 -> 0 | CG61: =CB61*BY61 -> 482.95684 | CH61: =CC61*BY61 -> 2656.2626 | CI61: =CD61*BY61 -> 0 | CJ61: =CE61*BY61 -> 1690.3489 | CL61: BVogaz | CM61: =AL11 -> 6164.7842 | CN61: =CM61/$G$70 -> 0.047630009 | CO61: 0 | CP61: 0.1 | CQ61: 0.55 | CR61: 0 | CS61: 0.35 | CT61: =CO61*CM61 -> 0 | CU61: =CP61*CM61 -> 616.47842 | CV61: =CQ61*CM61 -> 3390.6313 | CW61: =CR61*CM61 -> 0 | CX61: =CS61*CM61 -> 2157.6745
B62: Torf i drewno | C62: TJ | D62: 16349.378 | F62: Paliwa odpadowe i ciekłe BVo. | G62: =D64+D65 -> 41.77884 | H62: =G62/$G$70 -> 0.00032278932 | I62: 0 | J62: 0.1 | K62: 0.4 | L62: 0 | M62: 0.5 | N62: =I62*$G$62 -> 0 | O62: =J62*$G$62 -> 4.177884 | P62: =K62*$G$62 -> 16.711536 | Q62: =L62*$G$62 -> 0 | R62: =M62*$G$62 -> 20.88942 | T62: Paliwa odpadowe i ciekłe BVo. | U62: 2500 | V62: =U62/$U$70 -> 0.027292576 | W62: 0 | X62: 0.1 | Y62: 0.4 | Z62: 0 | AA62: 0.5 | AB62: =W62*U62 -> 0 | AC62: =X62*U62 -> 250 | AD62: =Y62*U62 -> 1000 | AE62: =Z62*U62 -> 0 | AF62: =AA62*U62 -> 1250 | AH62: Paliwa odpadowe i ciekłe BVo. | AI62: =AH12 -> 136.32581 | AJ62: =AI62/$G$70 -> 0.0010532728 | AK62: 0 | AL62: 0.1 | AM62: 0.4 | AN62: 0 | AO62: 0.5 | AP62: =AK62*$AI$62 -> 0 | AQ62: =AL62*$AI$62 -> 13.632581 | AR62: =AM62*$AI$62 -> 54.530323 | AS62: =AN62*$AI$62 -> 0 | AT62: =AO62*$AI$62 -> 68.162904 | AV62: Paliwa odpadowe i ciekłe BVo. | AW62: =AI12 -> 609.06065 | AX62: =AW62/$G$70 -> 0.0047056901 | AY62: 0 | AZ62: 0.1 | BA62: 0.4 | BB62: 0 | BC62: 0.5 | BD62: =AY62*AW62 -> 0 | BE62: =AZ62*AW62 -> 60.906065 | BF62: =BA62*AW62 -> 243.62426 | BG62: =BB62*AW62 -> 0 | BH62: =BC62*AW62 -> 304.53032 | BJ62: Paliwa odpadowe i ciekłe BVo. | BK62: =AJ12 -> 1081.7955 | BL62: =BK62/$G$70 -> 0.0083581074 | BM62: 0 | BN62: 0.1 | BO62: 0.4 | BP62: 0 | BQ62: 0.5 | BR62: =BM62*BK62 -> 0 | BS62: =BN62*BK62 -> 108.17955 | BT62: =BO62*BK62 -> 432.71819 | BU62: =BP62*BK62 -> 0 | BV62: =BQ62*BK62 -> 540.89774 | BX62: Paliwa odpadowe i ciekłe BVo. | BY62: =AK12 -> 1554.5303 | BZ62: =BY62/$G$70 -> 0.012010525 | CA62: 0 | CB62: 0.1 | CC62: 0.4 | CD62: 0 | CE62: 0.5 | CF62: =CA62*BY62 -> 0 | CG62: =CB62*BY62 -> 155.45303 | CH62: =CC62*BY62 -> 621.81213 | CI62: =CD62*BY62 -> 0 | CJ62: =CE62*BY62 -> 777.26516 | CL62: Paliwa odpadowe i ciekłe BVo. | CM62: =AL12 -> 2027.2652 | CN62: =CM62/$G$70 -> 0.015662942 | CO62: 0 | CP62: 0.1 | CQ62: 0.4 | CR62: 0 | CS62: 0.5 | CT62: =CO62*CM62 -> 0 | CU62: =CP62*CM62 -> 202.72652 | CV62: =CQ62*CM62 -> 810.90606 | CW62: =CR62*CM62 -> 0 | CX62: =CS62*CM62 -> 1013.6326
B63: BVogaz | C63: TJ | D63: 556.87786 | F63: Brykiety, koks i półkoks | G63: =D67+D68 -> 47.0832 | H63: =G63/$G$70 -> 0.00036377157 | I63: 0 | J63: 0.1 | K63: 0.45 | L63: 0 | M63: 0.45 | N63: =I63*$G$63 -> 0 | O63: =J63*$G$63 -> 4.70832 | P63: =K63*$G$63 -> 21.18744 | Q63: =L63*$G$63 -> 0 | R63: =M63*$G$63 -> 21.18744 | T63: Brykiety, koks i półkoks | U63: 0 | V63: =U63/$U$70 -> 0 | W63: 0 | X63: 0.1 | Y63: 0.45 | Z63: 0 | AA63: 0.45 | AB63: =W63*U63 -> 0 | AC63: =X63*U63 -> 0 | AD63: =Y63*U63 -> 0 | AE63: =Z63*U63 -> 0 | AF63: =AA63*U63 -> 0 | AH63: Brykiety, koks i półkoks | AI63: =AH13 -> 45.272308 | AJ63: =AI63/$G$70 -> 0.00034978036 | AK63: 0 | AL63: 0.1 | AM63: 0.45 | AN63: 0 | AO63: 0.45 | AP63: =AK63*$AI$63 -> 0 | AQ63: =AL63*$AI$63 -> 4.5272308 | AR63: =AM63*$AI$63 -> 20.372539 | AS63: =AN63*$AI$63 -> 0 | AT63: =AO63*$AI$63 -> 20.372539 | AV63: Brykiety, koks i półkoks | AW63: =AI13 -> 36.217846 | AX63: =AW63/$G$70 -> 0.00027982428 | AY63: 0 | AZ63: 0.1 | BA63: 0.45 | BB63: 0 | BC63: 0.45 | BD63: =AY63*AW63 -> 0 | BE63: =AZ63*AW63 -> 3.6217846 | BF63: =BA63*AW63 -> 16.298031 | BG63: =BB63*AW63 -> 0 | BH63: =BC63*AW63 -> 16.298031 | BJ63: Brykiety, koks i półkoks | BK63: =AJ13 -> 27.163384 | BL63: =BK63/$G$70 -> 0.00020986821 | BM63: 0 | BN63: 0.1 | BO63: 0.45 | BP63: 0 | BQ63: 0.45 | BR63: =BM63*BK63 -> 0 | BS63: =BN63*BK63 -> 2.7163384 | BT63: =BO63*BK63 -> 12.223523 | BU63: =BP63*BK63 -> 0 | BV63: =BQ63*BK63 -> 12.223523 | BX63: Brykiety, koks i półkoks | BY63: =AK13 -> 18.108922 | BZ63: =BY63/$G$70 -> 0.00013991213 | CA63: 0 | CB63: 0.1 | CC63: 0.45 | CD63: 0 | CE63: 0.45 | CF63: =CA63*BY63 -> 0 | CG63: =CB63*BY63 -> 1.8108922 | CH63: =CC63*BY63 -> 8.1490149 | CI63: =CD63*BY63 -> 0 | CJ63: =CE63*BY63 -> 8.1490149 | CL63: Brykiety, koks i półkoks | CM63: =AL13 -> 9.05446 | CN63: =CM63/$G$70 -> 6.9956059e-05 | CO63: 0 | CP63: 0.1 | CQ63: 0.45 | CR63: 0 | CS63: 0.45 | CT63: =CO63*CM63 -> 0 | CU63: =CP63*CM63 -> 0.905446 | CV63: =CQ63*CM63 -> 4.074507 | CW63: =CR63*CM63 -> 0 | CX63: =CS63*CM63 -> 4.074507
B64: Paliwa odpadowe stałe roślinne i zwierzęce | C64: TJ | D64: 37.37884 | F64: Gaz ciekły | G64: =D69 -> 1840 | H64: =G64/$G$70 -> 0.014216104 | I64: 0 | J64: 0.35 | K64: 0.45 | L64: 0 | M64: 0.2 | N64: =I64*$G$64 -> 0 | O64: =J64*$G$64 -> 644 | P64: =K64*$G$64 -> 828 | Q64: =L64*$G$64 -> 0 | R64: =M64*$G$64 -> 368 | T64: Gaz ciekły | U64: 500 | V64: =U64/$U$70 -> 0.0054585153 | W64: 0 | X64: 0.35 | Y64: 0.45 | Z64: 0 | AA64: 0.2 | AB64: =W64*U64 -> 0 | AC64: =X64*U64 -> 175 | AD64: =Y64*U64 -> 225 | AE64: =Z64*U64 -> 0 | AF64: =AA64*U64 -> 100 | AH64: Gaz ciekły | AI64: =AH14 -> 1788.4615 | AJ64: =AI64/$G$70 -> 0.013817911 | AK64: 0 | AL64: 0.35 | AM64: 0.45 | AN64: 0 | AO64: 0.2 | AP64: =AK64*$AI$64 -> 0 | AQ64: =AL64*$AI$64 -> 625.96154 | AR64: =AM64*$AI$64 -> 804.80769 | AS64: =AN64*$AI$64 -> 0 | AT64: =AO64*$AI$64 -> 357.69231 | AV64: Gaz ciekły | AW64: =AI14 -> 1530.7692 | AX64: =AW64/$G$70 -> 0.011826943 | AY64: 0 | AZ64: 0.35 | BA64: 0.45 | BB64: 0 | BC64: 0.2 | BD64: =AY64*AW64 -> 0 | BE64: =AZ64*AW64 -> 535.76923 | BF64: =BA64*AW64 -> 688.84615 | BG64: =BB64*AW64 -> 0 | BH64: =BC64*AW64 -> 306.15385 | BJ64: Gaz ciekły | BK64: =AJ14 -> 1273.0769 | BL64: =BK64/$G$70 -> 0.0098359753 | BM64: 0 | BN64: 0.35 | BO64: 0.45 | BP64: 0 | BQ64: 0.2 | BR64: =BM64*BK64 -> 0 | BS64: =BN64*BK64 -> 445.57692 | BT64: =BO64*BK64 -> 572.88461 | BU64: =BP64*BK64 -> 0 | BV64: =BQ64*BK64 -> 254.61538 | BX64: Gaz ciekły | BY64: =AK14 -> 1015.3846 | BZ64: =BY64/$G$70 -> 0.0078450075 | CA64: 0 | CB64: 0.35 | CC64: 0.45 | CD64: 0 | CE64: 0.2 | CF64: =CA64*BY64 -> 0 | CG64: =CB64*BY64 -> 355.38461 | CH64: =CC64*BY64 -> 456.92308 | CI64: =CD64*BY64 -> 0 | CJ64: =CE64*BY64 -> 203.07692 | CL64: Gaz ciekły | CM64: =AL14 -> 757.69231 | CN64: =CM64/$G$70 -> 0.0058540397 | CO64: 0 | CP64: 0.35 | CQ64: 0.45 | CR64: 0 | CS64: 0.2 | CT64: =CO64*CM64 -> 0 | CU64: =CP64*CM64 -> 265.19231 | CV64: =CQ64*CM64 -> 340.96154 | CW64: =CR64*CM64 -> 0 | CX64: =CS64*CM64 -> 151.53846
B65: Paliwa ciekłe z BVomasy | C65: TJ | D65: 4.4 | F65: Benzyny silnikowe i lotnicze | G65: =D70+D71 -> 103.13769 | H65: =G65/$G$70 -> 0.00079685663 | I65: 0.9 | J65: 0 | K65: 0 | L65: 0 | M65: 0.1 | N65: =I65*$G$65 -> 92.823923 | O65: =J65*$G$65 -> 0 | P65: =K65*$G$65 -> 0 | Q65: =L65*$G$65 -> 0 | R65: =M65*$G$65 -> 10.313769 | T65: Benzyny silnikowe i lotnicze | U65: 100 | V65: =U65/$U$70 -> 0.0010917031 | W65: 0.9 | X65: 0 | Y65: 0 | Z65: 0 | AA65: 0.1 | AB65: =W65*U65 -> 90 | AC65: =X65*U65 -> 0 | AD65: =Y65*U65 -> 0 | AE65: =Z65*U65 -> 0 | AF65: =AA65*U65 -> 10 | AH65: Benzyny silnikowe i lotnicze | AI65: =AH15 -> 103.01701 | AJ65: =AI65/$G$70 -> 0.00079592424 | AK65: 0.9 | AL65: 0 | AM65: 0 | AN65: 0 | AO65: 0.1 | AP65: =AK65*$AI$65 -> 92.715311 | AQ65: =AL65*$AI$65 -> 0 | AR65: =AM65*$AI$65 -> 0 | AS65: =AN65*$AI$65 -> 0 | AT65: =AO65*$AI$65 -> 10.301701 | AV65: Benzyny silnikowe i lotnicze | AW65: =AI15 -> 102.41361 | AX65: =AW65/$G$70 -> 0.00079126227 | AY65: 0.9 | AZ65: 0 | BA65: 0 | BB65: 0 | BC65: 0.1 | BD65: =AY65*AW65 -> 92.172249 | BE65: =AZ65*AW65 -> 0 | BF65: =BA65*AW65 -> 0 | BG65: =BB65*AW65 -> 0 | BH65: =BC65*AW65 -> 10.241361 | BJ65: Benzyny silnikowe i lotnicze | BK65: =AJ15 -> 101.81021 | BL65: =BK65/$G$70 -> 0.0007866003 | BM65: 0.9 | BN65: 0 | BO65: 0 | BP65: 0 | BQ65: 0.1 | BR65: =BM65*BK65 -> 91.629187 | BS65: =BN65*BK65 -> 0 | BT65: =BO65*BK65 -> 0 | BU65: =BP65*BK65 -> 0 | BV65: =BQ65*BK65 -> 10.181021 | BX65: Benzyny silnikowe i lotnicze | BY65: =AK15 -> 101.20681 | BZ65: =BY65/$G$70 -> 0.00078193833 | CA65: 0.9 | CB65: 0 | CC65: 0 | CD65: 0 | CE65: 0.1 | CF65: =CA65*BY65 -> 91.086125 | CG65: =CB65*BY65 -> 0 | CH65: =CC65*BY65 -> 0 | CI65: =CD65*BY65 -> 0 | CJ65: =CE65*BY65 -> 10.120681 | CL65: Benzyny silnikowe i lotnicze | CM65: =AL15 -> 100.6034 | CN65: =CM65/$G$70 -> 0.00077727636 | CO65: 0.9 | CP65: 0 | CQ65: 0 | CR65: 0 | CS65: 0.1 | CT65: =CO65*CM65 -> 90.543064 | CU65: =CP65*CM65 -> 0 | CV65: =CQ65*CM65 -> 0 | CW65: =CR65*CM65 -> 0 | CX65: =CS65*CM65 -> 10.06034
B66: Energia pochodna | C66: TJ | D66: 97493.519 | F66: Oleje napędowe | G66: =D72+D73 -> 85469.984 | H66: =G66/$G$70 -> 0.66035338 | I66: 0.9 | J66: 0.01 | K66: 0 | L66: 0.01 | M66: 0.08 | N66: =I66*$G$66 -> 76922.986 | O66: =J66*$G$66 -> 854.69984 | P66: =K66*$G$66 -> 0 | Q66: =L66*$G$66 -> 854.69984 | R66: =M66*$G$66 -> 6837.5987 | T66: Oleje napędowe | U66: 41000 | V66: =U66/$U$70 -> 0.44759825 | W66: 0.9 | X66: 0.01 | Y66: 0 | Z66: 0.01 | AA66: 0.08 | AB66: =W66*U66 -> 36900 | AC66: =X66*U66 -> 410 | AD66: =Y66*U66 -> 0 | AE66: =Z66*U66 -> 410 | AF66: =AA66*U66 -> 3280 | AH66: Oleje napędowe | AI66: =AH16 -> 83759.6 | AJ66: =AI66/$G$70 -> 0.64713871 | AK66: 0.9 | AL66: 0.01 | AM66: 0 | AN66: 0.01 | AO66: 0.08 | AP66: =AK66*$AI$66 -> 75383.64 | AQ66: =AL66*$AI$66 -> 837.596 | AR66: =AM66*$AI$66 -> 0 | AS66: =AN66*$AI$66 -> 837.596 | AT66: =AO66*$AI$66 -> 6700.768 | AV66: Oleje napędowe | AW66: =AI16 -> 75207.68 | AX66: =AW66/$G$70 -> 0.58106534 | AY66: 0.9 | AZ66: 0.01 | BA66: 0 | BB66: 0.01 | BC66: 0.08 | BD66: =AY66*AW66 -> 67686.912 | BE66: =AZ66*AW66 -> 752.0768 | BF66: =BA66*AW66 -> 0 | BG66: =BB66*AW66 -> 752.0768 | BH66: =BC66*AW66 -> 6016.6144 | BJ66: Oleje napędowe | BK66: =AJ16 -> 66655.76 | BL66: =BK66/$G$70 -> 0.51499198 | BM66: 0.9 | BN66: 0.01 | BO66: 0 | BP66: 0.01 | BQ66: 0.08 | BR66: =BM66*BK66 -> 59990.184 | BS66: =BN66*BK66 -> 666.5576 | BT66: =BO66*BK66 -> 0 | BU66: =BP66*BK66 -> 666.5576 | BV66: =BQ66*BK66 -> 5332.4608 | BX66: Oleje napędowe | BY66: =AK16 -> 58103.84 | BZ66: =BY66/$G$70 -> 0.44891862 | CA66: 0.9 | CB66: 0.01 | CC66: 0 | CD66: 0.01 | CE66: 0.08 | CF66: =CA66*BY66 -> 52293.456 | CG66: =CB66*BY66 -> 581.0384 | CH66: =CC66*BY66 -> 0 | CI66: =CD66*BY66 -> 581.0384 | CJ66: =CE66*BY66 -> 4648.3072 | CL66: Oleje napędowe | CM66: =AL16 -> 49551.92 | CN66: =CM66/$G$70 -> 0.38284526 | CO66: 0.9 | CP66: 0.01 | CQ66: 0 | CR66: 0.01 | CS66: 0.08 | CT66: =CO66*CM66 -> 44596.728 | CU66: =CP66*CM66 -> 495.5192 | CV66: =CQ66*CM66 -> 0 | CW66: =CR66*CM66 -> 495.5192 | CX66: =CS66*CM66 -> 3964.1536
B67: Brykiety z węgla kamiennego | C67: TJ | D67: 46.4 | F67: Oleje opałowe | G67: =D74+D75 -> 3094.6173 | H67: =G67/$G$70 -> 0.023909458 | I67: 0 | J67: 0.4 | K67: 0.35 | L67: 0 | M67: 0.25 | N67: =I67*$G$67 -> 0 | O67: =J67*$G$67 -> 1237.8469 | P67: =K67*$G$67 -> 1083.1161 | Q67: =L67*$G$67 -> 0 | R67: =M67*$G$67 -> 773.65434 | T67: Oleje opałowe | U67: 0 | V67: =U67/$U$70 -> 0 | W67: 0 | X67: 0.4 | Y67: 0.35 | Z67: 0 | AA67: 0.25 | AB67: =W67*U67 -> 0 | AC67: =X67*U67 -> 0 | AD67: =Y67*U67 -> 0 | AE67: =Z67*U67 -> 0 | AF67: =AA67*U67 -> 0 | AH67: Oleje opałowe | AI67: =AH17 -> 2975.5936 | AJ67: =AI67/$G$70 -> 0.022989864 | AK67: 0 | AL67: 0.4 | AM67: 0.35 | AN67: 0 | AO67: 0.25 | AP67: =AK67*$AI$67 -> 0 | AQ67: =AL67*$AI$67 -> 1190.2374 | AR67: =AM67*$AI$67 -> 1041.4578 | AS67: =AN67*$AI$67 -> 0 | AT67: =AO67*$AI$67 -> 743.8984 | AV67: Oleje opałowe | AW67: =AI17 -> 2380.4749 | AX67: =AW67/$G$70 -> 0.018391891 | AY67: 0 | AZ67: 0.4 | BA67: 0.35 | BB67: 0 | BC67: 0.25 | BD67: =AY67*AW67 -> 0 | BE67: =AZ67*AW67 -> 952.18995 | BF67: =BA67*AW67 -> 833.16621 | BG67: =BB67*AW67 -> 0 | BH67: =BC67*AW67 -> 595.11872 | BJ67: Oleje opałowe | BK67: =AJ17 -> 1785.3562 | BL67: =BK67/$G$70 -> 0.013793918 | BM67: 0 | BN67: 0.4 | BO67: 0.35 | BP67: 0 | BQ67: 0.25 | BR67: =BM67*BK67 -> 0 | BS67: =BN67*BK67 -> 714.14247 | BT67: =BO67*BK67 -> 624.87466 | BU67: =BP67*BK67 -> 0 | BV67: =BQ67*BK67 -> 446.33904 | BX67: Oleje opałowe | BY67: =AK17 -> 1190.2374 | BZ67: =BY67/$G$70 -> 0.0091959455 | CA67: 0 | CB67: 0.4 | CC67: 0.35 | CD67: 0 | CE67: 0.25 | CF67: =CA67*BY67 -> 0 | CG67: =CB67*BY67 -> 476.09498 | CH67: =CC67*BY67 -> 416.58311 | CI67: =CD67*BY67 -> 0 | CJ67: =CE67*BY67 -> 297.55936 | CL67: Oleje opałowe | CM67: =AL17 -> 595.11872 | CN67: =CM67/$G$70 -> 0.0045979728 | CO67: 0 | CP67: 0.4 | CQ67: 0.35 | CR67: 0 | CS67: 0.25 | CT67: =CO67*CM67 -> 0 | CU67: =CP67*CM67 -> 238.04749 | CV67: =CQ67*CM67 -> 208.29155 | CW67: =CR67*CM67 -> 0 | CX67: =CS67*CM67 -> 148.77968
B68: Koks i półkoks | C68: TJ | D68: 0.6832 | F68: Energia elektryczna | G68: =D78 -> 6300 | H68: =G68/$G$70 -> 0.048674705 | I68: 0.05 | J68: 0.14 | K68: 0.01 | L68: 0.5 | M68: 0.3 | N68: =I68*$G$68 -> 315 | O68: =J68*$G$68 -> 882 | P68: =K68*$G$68 -> 63 | Q68: =L68*$G$68 -> 3150 | R68: =M68*$G$68 -> 1890 | T68: Energia elektryczna | U68: 26000 | V68: =U68/$U$70 -> 0.28384279 | W68: 0.05 | X68: 0.14 | Y68: 0.01 | Z68: 0.5 | AA68: 0.3 | AB68: =W68*U68 -> 1300 | AC68: =X68*U68 -> 3640 | AD68: =Y68*U68 -> 260 | AE68: =Z68*U68 -> 13000 | AF68: =AA68*U68 -> 7800 | AH68: Energia elektryczna | AI68: =AH18 -> 7057.6923 | AJ68: =AI68/$G$70 -> 0.054528745 | AK68: 0.05 | AL68: 0.14 | AM68: 0.01 | AN68: 0.5 | AO68: 0.3 | AP68: =AK68*$AI$68 -> 352.88462 | AQ68: =AL68*$AI$68 -> 988.07692 | AR68: =AM68*$AI$68 -> 70.576923 | AS68: =AN68*$AI$68 -> 3528.8462 | AT68: =AO68*$AI$68 -> 2117.3077 | AV68: Energia elektryczna | AW68: =AI18 -> 10846.154 | AX68: =AW68/$G$70 -> 0.083798943 | AY68: 0.05 | AZ68: 0.14 | BA68: 0.01 | BB68: 0.5 | BC68: 0.3 | BD68: =AY68*AW68 -> 542.30769 | BE68: =AZ68*AW68 -> 1518.4615 | BF68: =BA68*AW68 -> 108.46154 | BG68: =BB68*AW68 -> 5423.0769 | BH68: =BC68*AW68 -> 3253.8462 | BJ68: Energia elektryczna | BK68: =AJ18 -> 14634.615 | BL68: =BK68/$G$70 -> 0.11306914 | BM68: 0.05 | BN68: 0.14 | BO68: 0.01 | BP68: 0.5 | BQ68: 0.3 | BR68: =BM68*BK68 -> 731.73077 | BS68: =BN68*BK68 -> 2048.8462 | BT68: =BO68*BK68 -> 146.34615 | BU68: =BP68*BK68 -> 7317.3077 | BV68: =BQ68*BK68 -> 4390.3846 | BX68: Energia elektryczna | BY68: =AK18 -> 18423.077 | BZ68: =BY68/$G$70 -> 0.14233934 | CA68: 0.05 | CB68: 0.14 | CC68: 0.01 | CD68: 0.5 | CE68: 0.3 | CF68: =CA68*BY68 -> 921.15385 | CG68: =CB68*BY68 -> 2579.2308 | CH68: =CC68*BY68 -> 184.23077 | CI68: =CD68*BY68 -> 9211.5385 | CJ68: =CE68*BY68 -> 5526.9231 | CL68: Energia elektryczna | CM68: =AL18 -> 22211.538 | CN68: =CM68/$G$70 -> 0.17160954 | CO68: 0.05 | CP68: 0.14 | CQ68: 0.01 | CR68: 0.5 | CS68: 0.3 | CT68: =CO68*CM68 -> 1110.5769 | CU68: =CP68*CM68 -> 3109.6154 | CV68: =CQ68*CM68 -> 222.11538 | CW68: =CR68*CM68 -> 11105.769 | CX68: =CS68*CM68 -> 6663.4615
B69: Gaz ciekły | C69: TJ | D69: 1840 | F69: Ciepło | G69: =D79 -> 620 | H69: =G69/$G$70 -> 0.0047902091 | I69: 0 | J69: 0 | K69: 0.4 | L69: 0 | M69: 0.6 | N69: =I69*$G$69 -> 0 | O69: =J69*$G$69 -> 0 | P69: =K69*$G$69 -> 248 | Q69: =L69*$G$69 -> 0 | R69: =M69*$G$69 -> 372 | T69: Ciepło | U69: 3000 | V69: =U69/$U$70 -> 0.032751092 | W69: 0 | X69: 0 | Y69: 0.4 | Z69: 0 | AA69: 0.6 | AB69: =W69*U69 -> 0 | AC69: =X69*U69 -> 0 | AD69: =Y69*U69 -> 1200 | AE69: =Z69*U69 -> 0 | AF69: =AA69*U69 -> 1800 | AH69: Ciepło | AI69: =AH19 -> 711.53846 | AJ69: =AI69/$G$70 -> 0.0054974484 | AK69: 0 | AL69: 0 | AM69: 0.4 | AN69: 0 | AO69: 0.6 | AP69: =AK69*$AI$69 -> 0 | AQ69: =AL69*$AI$69 -> 0 | AR69: =AM69*$AI$69 -> 284.61538 | AS69: =AN69*$AI$69 -> 0 | AT69: =AO69*$AI$69 -> 426.92308 | AV69: Ciepło | AW69: =AI19 -> 1169.2308 | AX69: =AW69/$G$70 -> 0.009033645 | AY69: 0 | AZ69: 0 | BA69: 0.4 | BB69: 0 | BC69: 0.6 | BD69: =AY69*AW69 -> 0 | BE69: =AZ69*AW69 -> 0 | BF69: =BA69*AW69 -> 467.69231 | BG69: =BB69*AW69 -> 0 | BH69: =BC69*AW69 -> 701.53846 | BJ69: Ciepło | BK69: =AJ19 -> 1626.9231 | BL69: =BK69/$G$70 -> 0.012569842 | BM69: 0 | BN69: 0 | BO69: 0.4 | BP69: 0 | BQ69: 0.6 | BR69: =BM69*BK69 -> 0 | BS69: =BN69*BK69 -> 0 | BT69: =BO69*BK69 -> 650.76923 | BU69: =BP69*BK69 -> 0 | BV69: =BQ69*BK69 -> 976.15385 | BX69: Ciepło | BY69: =AK19 -> 2084.6154 | BZ69: =BY69/$G$70 -> 0.016106038 | CA69: 0 | CB69: 0 | CC69: 0.4 | CD69: 0 | CE69: 0.6 | CF69: =CA69*BY69 -> 0 | CG69: =CB69*BY69 -> 0 | CH69: =CC69*BY69 -> 833.84615 | CI69: =CD69*BY69 -> 0 | CJ69: =CE69*BY69 -> 1250.7692 | CL69: Ciepło | CM69: =AL19 -> 2542.3077 | CN69: =CM69/$G$70 -> 0.019642235 | CO69: 0 | CP69: 0 | CQ69: 0.4 | CR69: 0 | CS69: 0.6 | CT69: =CO69*CM69 -> 0 | CU69: =CP69*CM69 -> 0 | CV69: =CQ69*CM69 -> 1016.9231 | CW69: =CR69*CM69 -> 0 | CX69: =CS69*CM69 -> 1525.3846
B70: Benzyny silnikowe | C70: TJ | D70: 86.347292 | F70: Suma | G70: =SUM(G57:G69) -> 129430.68 | H70: =G70/$G$70 -> 1 | N70: =SUM(N57:N69) -> 77330.809 | O70: =SUM(O57:O69) -> 7465.5769 | P70: =SUM(P57:P69) -> 14756.926 | Q70: =SUM(Q57:Q69) -> 4004.6998 | R70: =SUM(R57:R69) -> 25872.664 | T70: Suma | U70: =SUM(U57:U69) -> 91600 | V70: =U70/$U$70 -> 1 | AB70: =SUM(AB57:AB69) -> 38290 | AC70: =SUM(AC57:AC69) -> 6675 | AD70: =SUM(AD57:AD69) -> 10610 | AE70: =SUM(AE57:AE69) -> 13410 | AF70: =SUM(AF57:AF69) -> 22615 | AH70: Suma | AI70: =SUM(AI57:AI69) -> 127975.65 | AJ70: =AI70/AI70 -> 1 | AP70: =SUM(AP57:AP69) -> 75829.24 | AQ70: =SUM(AQ57:AQ69) -> 7435.1701 | AR70: =SUM(AR57:AR69) -> 14597.429 | AS70: =SUM(AS57:AS69) -> 4366.4422 | AT70: =SUM(AT57:AT69) -> 25747.369 | AV70: Suma | AW70: =SUM(AW57:AW69) -> 120700.52 | AX70: =AW70/AW70 -> 1 | BD70: =SUM(BD57:BD69) -> 68321.392 | BE70: =SUM(BE57:BE69) -> 7283.136 | BF70: =SUM(BF57:BF69) -> 13799.943 | BG70: =SUM(BG57:BG69) -> 6175.1537 | BH70: =SUM(BH57:BH69) -> 25120.895 | BJ70: Suma | BK70: =SUM(BK57:BK69) -> 113425.39 | BL70: =BK70/BK70 -> 1 | BR70: =SUM(BR57:BR69) -> 60813.544 | BS70: =SUM(BS57:BS69) -> 7131.102 | BT70: =SUM(BT57:BT69) -> 13002.457 | BU70: =SUM(BU57:BU69) -> 7983.8653 | BV70: =SUM(BV57:BV69) -> 24494.421 | BX70: Suma | BY70: =SUM(BY57:BY69) -> 106150.26 | BZ70: =BY70/BY70 -> 1 | CF70: =SUM(CF57:CF69) -> 53305.696 | CG70: =SUM(CG57:CG69) -> 6979.068 | CH70: =SUM(CH57:CH69) -> 12204.971 | CI70: =SUM(CI57:CI69) -> 9792.5769 | CJ70: =SUM(CJ57:CJ69) -> 23867.948 | CL70: Suma | CM70: =SUM(CM57:CM69) -> 98875.13 | CN70: =CM70/CM70 -> 1 | CT70: =SUM(CT57:CT69) -> 45797.848 | CU70: =SUM(CU57:CU69) -> 6827.034 | CV70: =SUM(CV57:CV69) -> 11407.486 | CW70: =SUM(CW57:CW69) -> 11601.288 | CX70: =SUM(CX57:CX69) -> 23241.474
B71: Benzyny lotnicze | C71: TJ | D71: 16.7904 | M71: Zużycie energii przez usługę | N71: =N70/$G$70 -> 0.59746895 | O71: =O70/$G$70 -> 0.05768012 | P71: =P70/$G$70 -> 0.11401413 | Q71: =Q70/$G$70 -> 0.030940887 | R71: =R70/$G$70 -> 0.19989592 | AA71: Zużycie energii przez usługę | AB71: =AB70/$G$70 -> 0.29583404 | AC71: =AC70/$G$70 -> 0.051572009 | AD71: =AD70/$G$70 -> 0.081974385 | AE71: =AE70/$G$70 -> 0.10360759 | AF71: =AF70/$G$70 -> 0.17472674 | AO71: Zużycie energii przez usługę | AP71: =AP70/$AI$70 -> 0.59252866 | AQ71: =AQ70/$AI$70 -> 0.058098319 | AR71: =AR70/$AI$70 -> 0.11406411 | AS71: =AS70/$AI$70 -> 0.03411932 | AT71: =AT70/$AI$70 -> 0.20118959 | BC71: Zużycie energii przez usługę | BD71: =BD70/$AI$70 -> 0.53386244 | BE71: =BE70/$AI$70 -> 0.056910327 | BF71: =BF70/$AI$70 -> 0.10783257 | BG71: =BG70/$AI$70 -> 0.048252568 | BH71: =BH70/$AI$70 -> 0.19629434 | BQ71: Zużycie energii przez usługę | BR71: =BR70/BK70 -> 0.5361546 | BS71: =BS70/BK70 -> 0.062870421 | BT71: =BT70/BK70 -> 0.11463445 | BU71: =BU70/BK70 -> 0.070388696 | BV71: =BV70/BK70 -> 0.21595184 | CE71: Zużycie energii przez usługę | CF71: =CF70/BY70 -> 0.50217207 | CG71: =CG70/BY70 -> 0.065747065 | CH71: =CH70/BY70 -> 0.11497825 | CI71: =CI70/BY70 -> 0.092252029 | CJ71: =CJ70/BY70 -> 0.22485058 | CS71: Zużycie energii przez usługę | CT71: =CT70/CM70 -> 0.46318875 | CU71: =CU70/CM70 -> 0.06904703 | CV71: =CV70/CM70 -> 0.11537265 | CW71: =CW70/CM70 -> 0.11733273 | CX71: =CX70/CM70 -> 0.23505884
B72: Olej napędowy I | C72: TJ | D72: 85440 | M72: PJ | N72: =N70/1000 -> 77.330809 | O72: =O70/1000 -> 7.4655769 | P72: =P70/1000 -> 14.756926 | Q72: =Q70/1000 -> 4.0046998 | R72: =R70/1000 -> 25.872664 | AA72: PJ | AB72: =AB70/1000 -> 38.29 | AC72: =AC70/1000 -> 6.675 | AD72: =AD70/1000 -> 10.61 | AE72: =AE70/1000 -> 13.41 | AF72: =AF70/1000 -> 22.615 | AO72: PJ | AP72: =AP70/1000 -> 75.82924 | AQ72: =AQ70/1000 -> 7.4351701 | AR72: =AR70/1000 -> 14.597429 | AS72: =AS70/1000 -> 4.3664422 | AT72: =AT70/1000 -> 25.747369 | BC72: PJ | BD72: =BD70/1000 -> 68.321392 | BE72: =BE70/1000 -> 7.283136 | BF72: =BF70/1000 -> 13.799943 | BG72: =BG70/1000 -> 6.1751537 | BH72: =BH70/1000 -> 25.120895 | BQ72: PJ | BR72: =BR70/1000 -> 60.813544 | BS72: =BS70/1000 -> 7.131102 | BT72: =BT70/1000 -> 13.002457 | BU72: =BU70/1000 -> 7.9838653 | BV72: =BV70/1000 -> 24.494421 | CE72: PJ | CF72: =CF70/1000 -> 53.305696 | CG72: =CG70/1000 -> 6.979068 | CH72: =CH70/1000 -> 12.204971 | CI72: =CI70/1000 -> 9.7925769 | CJ72: =CJ70/1000 -> 23.867948 | CS72: PJ | CT72: =CT70/1000 -> 45.797848 | CU72: =CU70/1000 -> 6.827034 | CV72: =CV70/1000 -> 11.407486 | CW72: =CW70/1000 -> 11.601288 | CX72: =CX70/1000 -> 23.241474
B73: Oleje napędowe pozostałe | C73: TJ | D73: 29.9839 | N73: Energia użytkowa | AB73: Energia użytkowa | AP73: Energia użytkowa | BD73: Energia użytkowa | BR73: Energia użytkowa | CF73: Energia użytkowa | CT73: Energia użytkowa
B74: Lekki olej opałowy | C74: TJ | D74: 3074.5 | M74: Paliwo/nośnik | N74: AGR_MACH_WORK | O74: AGR_DRY_SVC | P74: AGR_LIV_HT | Q74: AGR_LIV_ELC_SVC | R74: AGR_OTH_SVC | U74: =U68/3.6 -> 7222.2222 | AA74: Paliwo/nośnik | AB74: AGR_MACH_WORK | AC74: AGR_DRY_SVC | AD74: AGR_LIV_HT | AE74: AGR_LIV_ELC_SVC | AF74: AGR_OTH_SVC | AO74: Paliwo/nośnik | AP74: AGR_MACH_WORK | AQ74: AGR_DRY_SVC | AR74: AGR_LIV_HT | AS74: AGR_LIV_ELC_SVC | AT74: AGR_OTH_SVC | BC74: Paliwo/nośnik | BD74: AGR_MACH_WORK | BE74: AGR_DRY_SVC | BF74: AGR_LIV_HT | BG74: AGR_LIV_ELC_SVC | BH74: AGR_OTH_SVC | BQ74: Paliwo/nośnik | BR74: AGR_MACH_WORK | BS74: AGR_DRY_SVC | BT74: AGR_LIV_HT | BU74: AGR_LIV_ELC_SVC | BV74: AGR_OTH_SVC | CE74: Paliwo/nośnik | CF74: AGR_MACH_WORK | CG74: AGR_DRY_SVC | CH74: AGR_LIV_HT | CI74: AGR_LIV_ELC_SVC | CJ74: AGR_OTH_SVC | CS74: Paliwo/nośnik | CT74: AGR_MACH_WORK | CU74: AGR_DRY_SVC | CV74: AGR_LIV_HT | CW74: AGR_LIV_ELC_SVC | CX74: AGR_OTH_SVC
B75: Ciężki olej opałowy | C75: TJ | D75: 20.11735 | N75: Sprawność [%] | AB75: Sprawność [%] | AP75: Sprawność [%] | BD75: Sprawność [%] | BR75: Sprawność [%] | CF75: Sprawność [%] | CT75: Sprawność [%]
B76: Produkty nieenergetyczne | C76: TJ | D76: 18.5915 | M76: Węgiel kamienny en. | O76: 0.65 | P76: 0.7 | R76: 0.7 | AA76: Węgiel kamienny en. | AC76: 0.65 | AD76: 0.7 | AF76: 0.7 | AO76: Węgiel kamienny en. | AQ76: 0.65 | AR76: 0.7 | AT76: 0.7 | BC76: Węgiel kamienny en. | BE76: 0.65 | BF76: 0.7 | BH76: 0.7 | BQ76: Węgiel kamienny en. | BS76: 0.65 | BT76: 0.7 | BV76: 0.7 | CE76: Węgiel kamienny en. | CG76: 0.65 | CH76: 0.7 | CJ76: 0.7 | CS76: Węgiel kamienny en. | CU76: 0.65 | CV76: 0.7 | CX76: 0.7
B77: Energia elektryczna | C77: GWh | D77: 1750 | M77: Węgiel brunatny | O77: 0.6 | P77: 0.6 | R77: 0.6 | AA77: Węgiel brunatny | AC77: 0.6 | AD77: 0.6 | AF77: 0.6 | AO77: Węgiel brunatny | AQ77: 0.6 | AR77: 0.6 | AT77: 0.6 | BC77: Węgiel brunatny | BE77: 0.6 | BF77: 0.6 | BH77: 0.6 | BQ77: Węgiel brunatny | BS77: 0.6 | BT77: 0.6 | BV77: 0.6 | CE77: Węgiel brunatny | CG77: 0.6 | CH77: 0.6 | CJ77: 0.6 | CS77: Węgiel brunatny | CU77: 0.6 | CV77: 0.6 | CX77: 0.6
C78: TJ | D78: 6300 | M78: Gaz ziemny razem | O78: 0.8 | P78: 0.85 | R78: 0.85 | AA78: Gaz ziemny razem | AC78: 0.8 | AD78: 0.85 | AF78: 0.85 | AO78: Gaz ziemny razem | AQ78: 0.8 | AR78: 0.85 | AT78: 0.85 | BC78: Gaz ziemny razem | BE78: 0.8 | BF78: 0.85 | BH78: 0.85 | BQ78: Gaz ziemny razem | BS78: 0.8 | BT78: 0.85 | BV78: 0.85 | CE78: Gaz ziemny razem | CG78: 0.8 | CH78: 0.85 | CJ78: 0.85 | CS78: Gaz ziemny razem | CU78: 0.8 | CV78: 0.85 | CX78: 0.85
B79: Ciepło | C79: TJ | D79: 620 | M79: Torf i drewno | O79: 0.68 | P79: 0.7 | R79: 0.7 | AA79: Torf i drewno | AC79: 0.68 | AD79: 0.7 | AF79: 0.7 | AO79: Torf i drewno | AQ79: 0.68 | AR79: 0.7 | AT79: 0.7 | BC79: Torf i drewno | BE79: 0.68 | BF79: 0.7 | BH79: 0.7 | BQ79: Torf i drewno | BS79: 0.68 | BT79: 0.7 | BV79: 0.7 | CE79: Torf i drewno | CG79: 0.68 | CH79: 0.7 | CJ79: 0.7 | CS79: Torf i drewno | CU79: 0.68 | CV79: 0.7 | CX79: 0.7
M80: BVogaz | O80: 0.75 | P80: 0.8 | R80: 0.8 | AA80: BVogaz | AC80: 0.75 | AD80: 0.8 | AF80: 0.8 | AO80: BVogaz | AQ80: 0.75 | AR80: 0.8 | AT80: 0.8 | BC80: BVogaz | BE80: 0.75 | BF80: 0.8 | BH80: 0.8 | BQ80: BVogaz | BS80: 0.75 | BT80: 0.8 | BV80: 0.8 | CE80: BVogaz | CG80: 0.75 | CH80: 0.8 | CJ80: 0.8 | CS80: BVogaz | CU80: 0.75 | CV80: 0.8 | CX80: 0.8
M81: Paliwa odpadowe i ciekłe BVo. | O81: 0.65 | P81: 0.7 | R81: 0.7 | AA81: Paliwa odpadowe i ciekłe BVo. | AC81: 0.65 | AD81: 0.7 | AF81: 0.7 | AO81: Paliwa odpadowe i ciekłe BVo. | AQ81: 0.65 | AR81: 0.7 | AT81: 0.7 | BC81: Paliwa odpadowe i ciekłe BVo. | BE81: 0.65 | BF81: 0.7 | BH81: 0.7 | BQ81: Paliwa odpadowe i ciekłe BVo. | BS81: 0.65 | BT81: 0.7 | BV81: 0.7 | CE81: Paliwa odpadowe i ciekłe BVo. | CG81: 0.65 | CH81: 0.7 | CJ81: 0.7 | CS81: Paliwa odpadowe i ciekłe BVo. | CU81: 0.65 | CV81: 0.7 | CX81: 0.7
M82: Brykiety, koks i półkoks | O82: 0.65 | P82: 0.7 | R82: 0.7 | AA82: Brykiety, koks i półkoks | AC82: 0.65 | AD82: 0.7 | AF82: 0.7 | AO82: Brykiety, koks i półkoks | AQ82: 0.65 | AR82: 0.7 | AT82: 0.7 | BC82: Brykiety, koks i półkoks | BE82: 0.65 | BF82: 0.7 | BH82: 0.7 | BQ82: Brykiety, koks i półkoks | BS82: 0.65 | BT82: 0.7 | BV82: 0.7 | CE82: Brykiety, koks i półkoks | CG82: 0.65 | CH82: 0.7 | CJ82: 0.7 | CS82: Brykiety, koks i półkoks | CU82: 0.65 | CV82: 0.7 | CX82: 0.7
M83: Gaz ciekły | O83: 0.8 | P83: 0.85 | R83: 0.85 | AA83: Gaz ciekły | AC83: 0.8 | AD83: 0.85 | AF83: 0.85 | AO83: Gaz ciekły | AQ83: 0.8 | AR83: 0.85 | AT83: 0.85 | BC83: Gaz ciekły | BE83: 0.8 | BF83: 0.85 | BH83: 0.85 | BQ83: Gaz ciekły | BS83: 0.8 | BT83: 0.85 | BV83: 0.85 | CE83: Gaz ciekły | CG83: 0.8 | CH83: 0.85 | CJ83: 0.85 | CS83: Gaz ciekły | CU83: 0.8 | CV83: 0.85 | CX83: 0.85
M84: Benzyny silnikowe i lotnicze | N84: 0.25 | R84: 0.25 | AA84: Benzyny silnikowe i lotnicze | AB84: 0.25 | AF84: 0.25 | AO84: Benzyny silnikowe i lotnicze | AP84: 0.25 | AT84: 0.25 | BC84: Benzyny silnikowe i lotnicze | BD84: 0.25 | BH84: 0.25 | BQ84: Benzyny silnikowe i lotnicze | BR84: 0.25 | BV84: 0.25 | CE84: Benzyny silnikowe i lotnicze | CF84: 0.25 | CJ84: 0.25 | CS84: Benzyny silnikowe i lotnicze | CT84: 0.25 | CX84: 0.25
M85: Oleje napędowe | N85: 0.3 | O85: 0.75 | Q85: 0.27 | R85: 0.3 | AA85: Oleje napędowe | AB85: 0.3 | AC85: 0.75 | AE85: 0.27 | AF85: 0.3 | AO85: Oleje napędowe | AP85: 0.3 | AQ85: 0.75 | AS85: 0.27 | AT85: 0.3 | BC85: Oleje napędowe | BD85: 0.3 | BE85: 0.75 | BG85: 0.27 | BH85: 0.3 | BQ85: Oleje napędowe | BR85: 0.3 | BS85: 0.75 | BU85: 0.27 | BV85: 0.3 | CE85: Oleje napędowe | CF85: 0.3 | CG85: 0.75 | CI85: 0.27 | CJ85: 0.3 | CS85: Oleje napędowe | CT85: 0.3 | CU85: 0.75 | CW85: 0.27 | CX85: 0.3
M86: Oleje opałowe | O86: 0.75 | P86: 0.8 | R86: 0.8 | AA86: Oleje opałowe | AC86: 0.75 | AD86: 0.8 | AF86: 0.8 | AO86: Oleje opałowe | AQ86: 0.75 | AR86: 0.8 | AT86: 0.8 | BC86: Oleje opałowe | BE86: 0.75 | BF86: 0.8 | BH86: 0.8 | BQ86: Oleje opałowe | BS86: 0.75 | BT86: 0.8 | BV86: 0.8 | CE86: Oleje opałowe | CG86: 0.75 | CH86: 0.8 | CJ86: 0.8 | CS86: Oleje opałowe | CU86: 0.75 | CV86: 0.8 | CX86: 0.8
M87: Energia elektryczna | N87: 0.8 | O87: 0.85 | P87: 0.98 | Q87: 1 | R87: 0.9 | AA87: Energia elektryczna | AB87: 0.8 | AC87: 0.85 | AD87: 0.98 | AE87: 1 | AF87: 0.9 | AO87: Energia elektryczna | AP87: 0.8 | AQ87: 0.85 | AR87: 0.98 | AS87: 1 | AT87: 0.9 | BC87: Energia elektryczna | BD87: 0.8 | BE87: 0.85 | BF87: 0.98 | BG87: 1 | BH87: 0.9 | BQ87: Energia elektryczna | BR87: 0.8 | BS87: 0.85 | BT87: 0.98 | BU87: 1 | BV87: 0.9 | CE87: Energia elektryczna | CF87: 0.8 | CG87: 0.85 | CH87: 0.98 | CI87: 1 | CJ87: 0.9 | CS87: Energia elektryczna | CT87: 0.8 | CU87: 0.85 | CV87: 0.98 | CW87: 1 | CX87: 0.9
M88: Ciepło | P88: 0.9 | R88: 0.9 | AA88: Ciepło | AD88: 0.9 | AF88: 0.9 | AO88: Ciepło | AR88: 0.9 | AT88: 0.9 | BC88: Ciepło | BF88: 0.9 | BH88: 0.9 | BQ88: Ciepło | BT88: 0.9 | BV88: 0.9 | CE88: Ciepło | CH88: 0.9 | CJ88: 0.9 | CS88: Ciepło | CV88: 0.9 | CX88: 0.9
N89: TJ | AB89: TJ | AP89: TJ | BD89: TJ | BR89: TJ | CF89: TJ | CT89: TJ
N90: =N57*N76 -> 0 | O90: =O57*O76 -> 845 | P90: =P57*P76 -> 4095 | Q90: =Q57*Q76 -> 0 | R90: =R57*R76 -> 4095 | AB90: =AB57*AB76 -> 0 | AC90: =AC57*AC76 -> 0 | AD90: =AD57*AD76 -> 0 | AE90: =AE57*AE76 -> 0 | AF90: =AF57*AF76 -> 0 | AP90: =AP57*AP76 -> 0 | AQ90: =AQ57*AQ76 -> 812.5 | AR90: =AR57*AR76 -> 3937.5 | AS90: =AS57*AS76 -> 0 | AT90: =AT57*AT76 -> 3937.5 | BD90: =BD57*BD76 -> 0 | BE90: =BE57*BE76 -> 650 | BF90: =BF57*BF76 -> 3150 | BG90: =BG57*BG76 -> 0 | BH90: =BH57*BH76 -> 3150 | BR90: =BR57*BR76 -> 0 | BS90: =BS57*BS76 -> 487.5 | BT90: =BT57*BT76 -> 2362.5 | BU90: =BU57*BU76 -> 0 | BV90: =BV57*BV76 -> 2362.5 | CF90: =CF57*CF76 -> 0 | CG90: =CG57*CG76 -> 325 | CH90: =CH57*CH76 -> 1575 | CI90: =CI57*CI76 -> 0 | CJ90: =CJ57*CJ76 -> 1575 | CT90: =CT57*CT76 -> 0 | CU90: =CU57*CU76 -> 162.5 | CV90: =CV57*CV76 -> 787.5 | CW90: =CW57*CW76 -> 0 | CX90: =CX57*CX76 -> 787.5
N91: =N58*N77 -> 0 | O91: =O58*O77 -> 9.6 | P91: =P58*P77 -> 38.4 | Q91: =Q58*Q77 -> 0 | R91: =R58*R77 -> 48 | AB91: =AB58*AB77 -> 0 | AC91: =AC58*AC77 -> 0 | AD91: =AD58*AD77 -> 0 | AE91: =AE58*AE77 -> 0 | AF91: =AF58*AF77 -> 0 | AP91: =AP58*AP77 -> 0 | AQ91: =AQ58*AQ77 -> 9.2307692 | AR91: =AR58*AR77 -> 36.923077 | AS91: =AS58*AS77 -> 0 | AT91: =AT58*AT77 -> 46.153846 | BD91: =BD58*BD77 -> 0 | BE91: =BE58*BE77 -> 7.3846154 | BF91: =BF58*BF77 -> 29.538462 | BG91: =BG58*BG77 -> 0 | BH91: =BH58*BH77 -> 36.923077 | BR91: =BR58*BR77 -> 0 | BS91: =BS58*BS77 -> 5.5384615 | BT91: =BT58*BT77 -> 22.153846 | BU91: =BU58*BU77 -> 0 | BV91: =BV58*BV77 -> 27.692308 | CF91: =CF58*CF77 -> 0 | CG91: =CG58*CG77 -> 3.6923077 | CH91: =CH58*CH77 -> 14.769231 | CI91: =CI58*CI77 -> 0 | CJ91: =CJ58*CJ77 -> 18.461538 | CT91: =CT58*CT77 -> 0 | CU91: =CU58*CU77 -> 1.8461538 | CV91: =CV58*CV77 -> 7.3846152 | CW91: =CW58*CW77 -> 0 | CX91: =CX58*CX77 -> 9.230769
N92: =N59*N78 -> 0 | O92: =O59*O78 -> 665.21462 | P92: =P59*P78 -> 471.19369 | Q92: =Q59*Q78 -> 0 | R92: =R59*R78 -> 392.66141 | AB92: =AB59*AB78 -> 0 | AC92: =AC59*AC78 -> 360 | AD92: =AD59*AD78 -> 255 | AE92: =AE59*AE78 -> 0 | AF92: =AF59*AF78 -> 212.5 | AP92: =AP59*AP78 -> 0 | AQ92: =AQ59*AQ78 -> 653.4756 | AR92: =AR59*AR78 -> 462.87855 | AS92: =AS59*AS78 -> 0 | AT92: =AT59*AT78 -> 385.73212 | BD92: =BD59*BD78 -> 0 | BE92: =BE59*BE78 -> 594.78048 | BF92: =BF59*BF78 -> 421.30284 | BG92: =BG59*BG78 -> 0 | BH92: =BH59*BH78 -> 351.0857 | BR92: =BR59*BR78 -> 0 | BS92: =BS59*BS78 -> 536.08536 | BT92: =BT59*BT78 -> 379.72713 | BU92: =BU59*BU78 -> 0 | BV92: =BV59*BV78 -> 316.43928 | CF92: =CF59*CF78 -> 0 | CG92: =CG59*CG78 -> 477.39024 | CH92: =CH59*CH78 -> 338.15142 | CI92: =CI59*CI78 -> 0 | CJ92: =CJ59*CJ78 -> 281.79285 | CT92: =CT59*CT78 -> 0 | CU92: =CU59*CU78 -> 418.69512 | CV92: =CV59*CV78 -> 296.57571 | CW92: =CW59*CW78 -> 0 | CX92: =CX59*CX78 -> 247.14642
N93: =N60*N79 -> 0 | O93: =O60*O79 -> 1111.7577 | P93: =P60*P79 -> 4005.5976 | Q93: =Q60*Q79 -> 0 | R93: =R60*R79 -> 6294.5106 | AB93: =AB60*AB79 -> 0 | AC93: =AC60*AC79 -> 680 | AD93: =AD60*AD79 -> 2450 | AE93: =AE60*AE79 -> 0 | AF93: =AF60*AF79 -> 3850 | AP93: =AP60*AP79 -> 0 | AQ93: =AQ60*AQ79 -> 1095.1516 | AR93: =AR60*AR79 -> 3945.767 | AS93: =AS60*AS79 -> 0 | AT93: =AT60*AT79 -> 6200.4909 | BD93: =BD60*BD79 -> 0 | BE93: =BE60*BE79 -> 1012.1213 | BF93: =BF60*BF79 -> 3646.6136 | BG93: =BG60*BG79 -> 0 | BH93: =BH60*BH79 -> 5730.3928 | BR93: =BR60*BR79 -> 0 | BS93: =BS60*BS79 -> 929.09099 | BT93: =BT60*BT79 -> 3347.4602 | BU93: =BU60*BU79 -> 0 | BV93: =BV60*BV79 -> 5260.2946 | CF93: =CF60*CF79 -> 0 | CG93: =CG60*CG79 -> 846.06066 | CH93: =CH60*CH79 -> 3048.3068 | CI93: =CI60*CI79 -> 0 | CJ93: =CJ60*CJ79 -> 4790.1964 | CT93: =CT60*CT79 -> 0 | CU93: =CU60*CU79 -> 763.03033 | CV93: =CV60*CV79 -> 2749.1534 | CW93: =CW60*CW79 -> 0 | CX93: =CX60*CX79 -> 4320.0982
N94: =N61*N80 -> 0 | O94: =O61*O80 -> 41.765839 | P94: =P61*P80 -> 245.02626 | Q94: =Q61*Q80 -> 0 | R94: =R61*R80 -> 155.9258 | AB94: =AB61*AB80 -> 0 | AC94: =AC61*AC80 -> 562.5 | AD94: =AD61*AD80 -> 3300 | AE94: =AE61*AE80 -> 0 | AF94: =AF61*AF80 -> 2100 | AP94: =AP61*AP80 -> 0 | AQ94: =AQ61*AQ80 -> 61.794076 | AR94: =AR61*AR80 -> 362.52525 | AS94: =AS61*AS80 -> 0 | AT94: =AT61*AT80 -> 230.69788 | BD94: =BD61*BD80 -> 0 | BE94: =BE61*BE80 -> 161.93526 | BF94: =BF61*BF80 -> 950.0202 | BG94: =BG61*BG80 -> 0 | BH94: =BH61*BH80 -> 604.55831 | BR94: =BR61*BR80 -> 0 | BS94: =BS61*BS80 -> 262.07645 | BT94: =BT61*BT80 -> 1537.5151 | BU94: =BU61*BU80 -> 0 | BV94: =BV61*BV80 -> 978.41873 | CF94: =CF61*CF80 -> 0 | CG94: =CG61*CG80 -> 362.21763 | CH94: =CH61*CH80 -> 2125.0101 | CI94: =CI61*CI80 -> 0 | CJ94: =CJ61*CJ80 -> 1352.2792 | CT94: =CT61*CT80 -> 0 | CU94: =CU61*CU80 -> 462.35882 | CV94: =CV61*CV80 -> 2712.505 | CW94: =CW61*CW80 -> 0 | CX94: =CX61*CX80 -> 1726.1396
N95: =N62*N81 -> 0 | O95: =O62*O81 -> 2.7156246 | P95: =P62*P81 -> 11.698075 | Q95: =Q62*Q81 -> 0 | R95: =R62*R81 -> 14.622594 | AB95: =AB62*AB81 -> 0 | AC95: =AC62*AC81 -> 162.5 | AD95: =AD62*AD81 -> 700 | AE95: =AE62*AE81 -> 0 | AF95: =AF62*AF81 -> 875 | AP95: =AP62*AP81 -> 0 | AQ95: =AQ62*AQ81 -> 8.8611775 | AR95: =AR62*AR81 -> 38.171226 | AS95: =AS62*AS81 -> 0 | AT95: =AT62*AT81 -> 47.714033 | BD95: =BD62*BD81 -> 0 | BE95: =BE62*BE81 -> 39.588942 | BF95: =BF62*BF81 -> 170.53698 | BG95: =BG62*BG81 -> 0 | BH95: =BH62*BH81 -> 213.17123 | BR95: =BR62*BR81 -> 0 | BS95: =BS62*BS81 -> 70.316706 | BT95: =BT62*BT81 -> 302.90274 | BU95: =BU62*BU81 -> 0 | BV95: =BV62*BV81 -> 378.62842 | CF95: =CF62*CF81 -> 0 | CG95: =CG62*CG81 -> 101.04447 | CH95: =CH62*CH81 -> 435.26849 | CI95: =CI62*CI81 -> 0 | CJ95: =CJ62*CJ81 -> 544.08561 | CT95: =CT62*CT81 -> 0 | CU95: =CU62*CU81 -> 131.77224 | CV95: =CV62*CV81 -> 567.63424 | CW95: =CW62*CW81 -> 0 | CX95: =CX62*CX81 -> 709.54281
N96: =N63*N82 -> 0 | O96: =O63*O82 -> 3.060408 | P96: =P63*P82 -> 14.831208 | Q96: =Q63*Q82 -> 0 | R96: =R63*R82 -> 14.831208 | AB96: =AB63*AB82 -> 0 | AC96: =AC63*AC82 -> 0 | AD96: =AD63*AD82 -> 0 | AE96: =AE63*AE82 -> 0 | AF96: =AF63*AF82 -> 0 | AP96: =AP63*AP82 -> 0 | AQ96: =AQ63*AQ82 -> 2.9427 | AR96: =AR63*AR82 -> 14.260777 | AS96: =AS63*AS82 -> 0 | AT96: =AT63*AT82 -> 14.260777 | BD96: =BD63*BD82 -> 0 | BE96: =BE63*BE82 -> 2.35416 | BF96: =BF63*BF82 -> 11.408621 | BG96: =BG63*BG82 -> 0 | BH96: =BH63*BH82 -> 11.408621 | BR96: =BR63*BR82 -> 0 | BS96: =BS63*BS82 -> 1.76562 | BT96: =BT63*BT82 -> 8.556466 | BU96: =BU63*BU82 -> 0 | BV96: =BV63*BV82 -> 8.556466 | CF96: =CF63*CF82 -> 0 | CG96: =CG63*CG82 -> 1.1770799 | CH96: =CH63*CH82 -> 5.7043104 | CI96: =CI63*CI82 -> 0 | CJ96: =CJ63*CJ82 -> 5.7043104 | CT96: =CT63*CT82 -> 0 | CU96: =CU63*CU82 -> 0.5885399 | CV96: =CV63*CV82 -> 2.8521549 | CW96: =CW63*CW82 -> 0 | CX96: =CX63*CX82 -> 2.8521549
N97: =N64*N83 -> 0 | O97: =O64*O83 -> 515.2 | P97: =P64*P83 -> 703.8 | Q97: =Q64*Q83 -> 0 | R97: =R64*R83 -> 312.8 | AB97: =AB64*AB83 -> 0 | AC97: =AC64*AC83 -> 140 | AD97: =AD64*AD83 -> 191.25 | AE97: =AE64*AE83 -> 0 | AF97: =AF64*AF83 -> 85 | AP97: =AP64*AP83 -> 0 | AQ97: =AQ64*AQ83 -> 500.76923 | AR97: =AR64*AR83 -> 684.08654 | AS97: =AS64*AS83 -> 0 | AT97: =AT64*AT83 -> 304.03846 | BD97: =BD64*BD83 -> 0 | BE97: =BE64*BE83 -> 428.61538 | BF97: =BF64*BF83 -> 585.51923 | BG97: =BG64*BG83 -> 0 | BH97: =BH64*BH83 -> 260.23077 | BR97: =BR64*BR83 -> 0 | BS97: =BS64*BS83 -> 356.46154 | BT97: =BT64*BT83 -> 486.95192 | BU97: =BU64*BU83 -> 0 | BV97: =BV64*BV83 -> 216.42308 | CF97: =CF64*CF83 -> 0 | CG97: =CG64*CG83 -> 284.30769 | CH97: =CH64*CH83 -> 388.38461 | CI97: =CI64*CI83 -> 0 | CJ97: =CJ64*CJ83 -> 172.61538 | CT97: =CT64*CT83 -> 0 | CU97: =CU64*CU83 -> 212.15385 | CV97: =CV64*CV83 -> 289.81731 | CW97: =CW64*CW83 -> 0 | CX97: =CX64*CX83 -> 128.80769
N98: =N65*N84 -> 23.205981 | O98: =O65*O84 -> 0 | P98: =P65*P84 -> 0 | Q98: =Q65*Q84 -> 0 | R98: =R65*R84 -> 2.5784423 | AB98: =AB65*AB84 -> 22.5 | AC98: =AC65*AC84 -> 0 | AD98: =AD65*AD84 -> 0 | AE98: =AE65*AE84 -> 0 | AF98: =AF65*AF84 -> 2.5 | AP98: =AP65*AP84 -> 23.178828 | AQ98: =AQ65*AQ84 -> 0 | AR98: =AR65*AR84 -> 0 | AS98: =AS65*AS84 -> 0 | AT98: =AT65*AT84 -> 2.5754253 | BD98: =BD65*BD84 -> 23.043062 | BE98: =BE65*BE84 -> 0 | BF98: =BF65*BF84 -> 0 | BG98: =BG65*BG84 -> 0 | BH98: =BH65*BH84 -> 2.5603403 | BR98: =BR65*BR84 -> 22.907297 | BS98: =BS65*BS84 -> 0 | BT98: =BT65*BT84 -> 0 | BU98: =BU65*BU84 -> 0 | BV98: =BV65*BV84 -> 2.5452552 | CF98: =CF65*CF84 -> 22.771531 | CG98: =CG65*CG84 -> 0 | CH98: =CH65*CH84 -> 0 | CI98: =CI65*CI84 -> 0 | CJ98: =CJ65*CJ84 -> 2.5301702 | CT98: =CT65*CT84 -> 22.635766 | CU98: =CU65*CU84 -> 0 | CV98: =CV65*CV84 -> 0 | CW98: =CW65*CW84 -> 0 | CX98: =CX65*CX84 -> 2.5150851
N99: =N66*N85 -> 23076.896 | O99: =O66*O85 -> 641.02488 | P99: =P66*P85 -> 0 | Q99: =Q66*Q85 -> 230.76896 | R99: =R66*R85 -> 2051.2796 | AB99: =AB66*AB85 -> 11070 | AC99: =AC66*AC85 -> 307.5 | AD99: =AD66*AD85 -> 0 | AE99: =AE66*AE85 -> 110.7 | AF99: =AF66*AF85 -> 984 | AP99: =AP66*AP85 -> 22615.092 | AQ99: =AQ66*AQ85 -> 628.197 | AR99: =AR66*AR85 -> 0 | AS99: =AS66*AS85 -> 226.15092 | AT99: =AT66*AT85 -> 2010.2304 | BD99: =BD66*BD85 -> 20306.074 | BE99: =BE66*BE85 -> 564.0576 | BF99: =BF66*BF85 -> 0 | BG99: =BG66*BG85 -> 203.06074 | BH99: =BH66*BH85 -> 1804.9843 | BR99: =BR66*BR85 -> 17997.055 | BS99: =BS66*BS85 -> 499.9182 | BT99: =BT66*BT85 -> 0 | BU99: =BU66*BU85 -> 179.97055 | BV99: =BV66*BV85 -> 1599.7382 | CF99: =CF66*CF85 -> 15688.037 | CG99: =CG66*CG85 -> 435.7788 | CH99: =CH66*CH85 -> 0 | CI99: =CI66*CI85 -> 156.88037 | CJ99: =CJ66*CJ85 -> 1394.4922 | CT99: =CT66*CT85 -> 13379.018 | CU99: =CU66*CU85 -> 371.6394 | CV99: =CV66*CV85 -> 0 | CW99: =CW66*CW85 -> 133.79018 | CX99: =CX66*CX85 -> 1189.2461
N100: =N67*N86 -> 0 | O100: =O67*O86 -> 928.38521 | P100: =P67*P86 -> 866.49286 | Q100: =Q67*Q86 -> 0 | R100: =R67*R86 -> 618.92347 | AB100: =AB67*AB86 -> 0 | AC100: =AC67*AC86 -> 0 | AD100: =AD67*AD86 -> 0 | AE100: =AE67*AE86 -> 0 | AF100: =AF67*AF86 -> 0 | AP100: =AP67*AP86 -> 0 | AQ100: =AQ67*AQ86 -> 892.67808 | AR100: =AR67*AR86 -> 833.16621 | AS100: =AS67*AS86 -> 0 | AT100: =AT67*AT86 -> 595.11872 | BD100: =BD67*BD86 -> 0 | BE100: =BE67*BE86 -> 714.14247 | BF100: =BF67*BF86 -> 666.53297 | BG100: =BG67*BG86 -> 0 | BH100: =BH67*BH86 -> 476.09498 | BR100: =BR67*BR86 -> 0 | BS100: =BS67*BS86 -> 535.60685 | BT100: =BT67*BT86 -> 499.89973 | BU100: =BU67*BU86 -> 0 | BV100: =BV67*BV86 -> 357.07123 | CF100: =CF67*CF86 -> 0 | CG100: =CG67*CG86 -> 357.07123 | CH100: =CH67*CH86 -> 333.26648 | CI100: =CI67*CI86 -> 0 | CJ100: =CJ67*CJ86 -> 238.04749 | CT100: =CT67*CT86 -> 0 | CU100: =CU67*CU86 -> 178.53562 | CV100: =CV67*CV86 -> 166.63324 | CW100: =CW67*CW86 -> 0 | CX100: =CX67*CX86 -> 119.02374
N101: =N68*N87 -> 252 | O101: =O68*O87 -> 749.7 | P101: =P68*P87 -> 61.74 | Q101: =Q68*Q87 -> 3150 | R101: =R68*R87 -> 1701 | AB101: =AB68*AB87 -> 1040 | AC101: =AC68*AC87 -> 3094 | AD101: =AD68*AD87 -> 254.8 | AE101: =AE68*AE87 -> 13000 | AF101: =AF68*AF87 -> 7020 | AP101: =AP68*AP87 -> 282.30769 | AQ101: =AQ68*AQ87 -> 839.86538 | AR101: =AR68*AR87 -> 69.165385 | AS101: =AS68*AS87 -> 3528.8462 | AT101: =AT68*AT87 -> 1905.5769 | BD101: =BD68*BD87 -> 433.84615 | BE101: =BE68*BE87 -> 1290.6923 | BF101: =BF68*BF87 -> 106.29231 | BG101: =BG68*BG87 -> 5423.0769 | BH101: =BH68*BH87 -> 2928.4615 | BR101: =BR68*BR87 -> 585.38462 | BS101: =BS68*BS87 -> 1741.5192 | BT101: =BT68*BT87 -> 143.41923 | BU101: =BU68*BU87 -> 7317.3077 | BV101: =BV68*BV87 -> 3951.3462 | CF101: =CF68*CF87 -> 736.92308 | CG101: =CG68*CG87 -> 2192.3462 | CH101: =CH68*CH87 -> 180.54615 | CI101: =CI68*CI87 -> 9211.5385 | CJ101: =CJ68*CJ87 -> 4974.2308 | CT101: =CT68*CT87 -> 888.46154 | CU101: =CU68*CU87 -> 2643.1731 | CV101: =CV68*CV87 -> 217.67308 | CW101: =CW68*CW87 -> 11105.769 | CX101: =CX68*CX87 -> 5997.1154
M102: Zużycie energii przez usługę | N102: =N69*N88 -> 0 | O102: =O69*O88 -> 0 | P102: =P69*P88 -> 223.2 | Q102: =Q69*Q88 -> 0 | R102: =R69*R88 -> 334.8 | AA102: Zużycie energii przez usługę | AB102: =AB69*AB88 -> 0 | AC102: =AC69*AC88 -> 0 | AD102: =AD69*AD88 -> 1080 | AE102: =AE69*AE88 -> 0 | AF102: =AF69*AF88 -> 1620 | AO102: Zużycie energii przez usługę | AP102: =AP69*AP88 -> 0 | AQ102: =AQ69*AQ88 -> 0 | AR102: =AR69*AR88 -> 256.15385 | AS102: =AS69*AS88 -> 0 | AT102: =AT69*AT88 -> 384.23077 | BC102: Zużycie energii przez usługę | BD102: =BD69*BD88 -> 0 | BE102: =BE69*BE88 -> 0 | BF102: =BF69*BF88 -> 420.92308 | BG102: =BG69*BG88 -> 0 | BH102: =BH69*BH88 -> 631.38462 | BQ102: Zużycie energii przez usługę | BR102: =BR69*BR88 -> 0 | BS102: =BS69*BS88 -> 0 | BT102: =BT69*BT88 -> 585.69231 | BU102: =BU69*BU88 -> 0 | BV102: =BV69*BV88 -> 878.53846 | CE102: Zużycie energii przez usługę | CF102: =CF69*CF88 -> 0 | CG102: =CG69*CG88 -> 0 | CH102: =CH69*CH88 -> 750.46154 | CI102: =CI69*CI88 -> 0 | CJ102: =CJ69*CJ88 -> 1125.6923 | CS102: Zużycie energii przez usługę | CT102: =CT69*CT88 -> 0 | CU102: =CU69*CU88 -> 0 | CV102: =CV69*CV88 -> 915.23077 | CW102: =CW69*CW88 -> 0 | CX102: =CX69*CX88 -> 1372.8462
M103: TJ | N103: =SUM(N90:N102) -> 23352.102 | O103: =SUM(O90:O102) -> 5513.4243 | P103: =SUM(P90:P102) -> 10736.98 | Q103: =SUM(Q90:Q102) -> 3380.769 | R103: =SUM(R90:R102) -> 16036.933 | AA103: TJ | AB103: =SUM(AB90:AB102) -> 12132.5 | AC103: =SUM(AC90:AC102) -> 5306.5 | AD103: =SUM(AD90:AD102) -> 8231.05 | AE103: =SUM(AE90:AE102) -> 13110.7 | AF103: =SUM(AF90:AF102) -> 16749 | AO103: TJ | AP103: =SUM(AP90:AP102) -> 22920.578 | AQ103: =SUM(AQ90:AQ102) -> 5505.4657 | AR103: =SUM(AR90:AR102) -> 10640.598 | AS103: =SUM(AS90:AS102) -> 3754.9971 | AT103: =SUM(AT90:AT102) -> 16064.32 | BC103: TJ | BD103: =SUM(BD90:BD102) -> 20762.963 | BE103: =SUM(BE90:BE102) -> 5465.6725 | BF103: =SUM(BF90:BF102) -> 10158.688 | BG103: =SUM(BG90:BG102) -> 5626.1377 | BH103: =SUM(BH90:BH102) -> 16201.256 | BQ103: TJ | BR103: =SUM(BR90:BR102) -> 18605.347 | BS103: =SUM(BS90:BS102) -> 5425.8794 | BT103: =SUM(BT90:BT102) -> 9676.7787 | BU103: =SUM(BU90:BU102) -> 7497.2782 | BV103: =SUM(BV90:BV102) -> 16338.192 | CE103: TJ | CF103: =SUM(CF90:CF102) -> 16447.731 | CG103: =SUM(CG90:CG102) -> 5386.0863 | CH103: =SUM(CH90:CH102) -> 9194.8691 | CI103: =SUM(CI90:CI102) -> 9368.4188 | CJ103: =SUM(CJ90:CJ102) -> 16475.128 | CS103: TJ | CT103: =SUM(CT90:CT102) -> 14290.116 | CU103: =SUM(CU90:CU102) -> 5346.2931 | CV103: =SUM(CV90:CV102) -> 8712.9596 | CW103: =SUM(CW90:CW102) -> 11239.559 | CX103: =SUM(CX90:CX102) -> 16612.064
M104: PJ | N104: =N103/1000 -> 23.352102 | O104: =O103/1000 -> 5.5134243 | P104: =P103/1000 -> 10.73698 | Q104: =Q103/1000 -> 3.380769 | R104: =R103/1000 -> 16.036933 | AA104: PJ | AB104: =AB103/1000 -> 12.1325 | AC104: =AC103/1000 -> 5.3065 | AD104: =AD103/1000 -> 8.23105 | AE104: =AE103/1000 -> 13.1107 | AF104: =AF103/1000 -> 16.749 | AO104: PJ | AP104: =AP103/1000 -> 22.920578 | AQ104: =AQ103/1000 -> 5.5054657 | AR104: =AR103/1000 -> 10.640598 | AS104: =AS103/1000 -> 3.7549971 | AT104: =AT103/1000 -> 16.06432 | BC104: PJ | BD104: =BD103/1000 -> 20.762963 | BE104: =BE103/1000 -> 5.4656725 | BF104: =BF103/1000 -> 10.158688 | BG104: =BG103/1000 -> 5.6261377 | BH104: =BH103/1000 -> 16.201256 | BQ104: PJ | BR104: =BR103/1000 -> 18.605347 | BS104: =BS103/1000 -> 5.4258794 | BT104: =BT103/1000 -> 9.6767787 | BU104: =BU103/1000 -> 7.4972782 | BV104: =BV103/1000 -> 16.338192 | CE104: PJ | CF104: =CF103/1000 -> 16.447731 | CG104: =CG103/1000 -> 5.3860863 | CH104: =CH103/1000 -> 9.1948691 | CI104: =CI103/1000 -> 9.3684188 | CJ104: =CJ103/1000 -> 16.475128 | CS104: PJ | CT104: =CT103/1000 -> 14.290116 | CU104: =CU103/1000 -> 5.3462931 | CV104: =CV103/1000 -> 8.7129596 | CW104: =CW103/1000 -> 11.239559 | CX104: =CX103/1000 -> 16.612064
M105: Przydział | AA105: Przydział | AO105: Przydział | BC105: Przydział | BQ105: Przydział | CE105: Przydział | CS105: Przydział
M106: CROP | N106: 0.9 | O106: 1 | P106: 0 | Q106: 0 | R106: 0.6 | AA106: CROP | AB106: 0.9 | AC106: 1 | AD106: 0 | AE106: 0 | AF106: 0.6 | AO106: CROP | AP106: 0.9 | AQ106: 1 | AR106: 0 | AS106: 0 | AT106: 0.6 | BC106: CROP | BD106: 0.9 | BE106: 1 | BF106: 0 | BG106: 0 | BH106: 0.6 | BQ106: CROP | BR106: 0.9 | BS106: 1 | BT106: 0 | BU106: 0 | BV106: 0.6 | CE106: CROP | CF106: 0.9 | CG106: 1 | CH106: 0 | CI106: 0 | CJ106: 0.6 | CS106: CROP | CT106: 0.9 | CU106: 1 | CV106: 0 | CW106: 0 | CX106: 0.6
...

Sheet AGR_BIOG
F2: ~FI_T:PL
B3: TechName | C3: *TechDesc | D3: Comm-IN | E3: Comm-OUT | F3: Stock~2024 | G3: Stock~2025 | H3: Stock~2030 | I3: Stock~2035 | J3: Stock~2040 | K3: Stock~2045 | L3: Stock~2050 | M3: * Gross Calorific Value | N3: ACTFLO | O3: CEFF | P3: Share-I | Q3: VAROM | R3: FIXOM | S3: Cap2Act | T3: FLO_COST | U3: AFA~FX | V3: Share-I~0
B4: * Technology name | C4: Technology description | D4: Commodity input | E4: Commodity output | F4: mln m3 biogazu na rok | G4: mln m3 biogazu na rok | H4: mln m3 biogazu na rok | I4: mln m3 biogazu na rok | J4: mln m3 biogazu na rok | K4: mln m3 biogazu na rok | L4: mln m3 biogazu na rok | M4: MJ / m3 | N4: PJ/mln m3 - | O4: mln m3 / kt | P4: kt animal manure / kt all manure | S4: kt/kt | T4: PLN /m3 | AA4: Produkcja biogazu | AF4: Wartości oryginalne ,,Biometan w miksie energetycznym Polski'' NCBR | AG4: Wartości użyte: obniżone do poziomu 95% jako osiągalne w skali przemysłowej na rzeczywistych instalacjach biometanowych. Źródło NCBR.
B5: =AGR_Proc!D26 -> AGR_EX_BIOG | C5: =AGR_Proc!E26 -> Agriculture Existing Biogass | F5: 374 | G5: 374 | H5: 374 | I5: 374 | J5: 374 | K5: 374 | L5: 374 | Q5: =E36*F42/1000*F48 -> 0.575 | S5: 1 | U5: 1 | AA5: mln m3 | AF5: 0.322 | AG5: =AF5*0.95 -> 0.3059
D6: AGR_RESID_CROP_WHEAT | O6: 0.3059 | P6: 0.0395034 | T6: =E36*$F$46/(O6*1000) -> 0.1471069 | V6: 3 | AA6: =O6*AGR_LAND!$U$34*AGR_LAND!$G$28 -> 557.27727 | AF6: 0.322 | AG6: =AF6*0.95 -> 0.3059
D7: AGR_RESID_CROP_BARLEY | O7: 0.3059 | P7: 0.0084102 | T7: =E36*$F$46/(O7*1000) -> 0.1471069 | V7: 3 | AA7: =O7*AGR_LAND!$U$42*AGR_LAND!$G$36 -> 121.8496 | AF7: 0.409 | AG7: =AF7*0.95 -> 0.38855
D8: AGR_RESID_CROP_MAIZE | O8: 0.38855 | P8: 0.0212706 | T8: =E36*$F$46/(O8*1000) -> 0.11581521 | V8: 3 | AA8: =O8*AGR_LAND!$U$50*AGR_LAND!$G$44 -> 783.15922 | AF8: 0.322 | AG8: =AF8*0.95 -> 0.3059
D9: AGR_RESID_CROP_CER-MIX | O9: 0.3059 | P9: 0.0065585 | T9: =E36*$F$46/(O9*1000) -> 0.1471069 | V9: 3 | AA9: =O9*AGR_LAND!$U$58*AGR_LAND!$G$52 -> 37.836349 | AF9: 0.322 | AG9: =AF9*0.95 -> 0.3059
D10: AGR_RESID_CROP_TRITICALE | O10: 0.3059 | P10: 0.0238757 | T10: =E36*$F$46/(O10*1000) -> 0.1471069 | V10: 3 | AA10: =O10*AGR_LAND!$U$66*AGR_LAND!$G$60 -> 280.21093 | AF10: 0.322 | AG10: =AF10*0.95 -> 0.3059
D11: AGR_RESID_CROP_OATS | O11: 0.3059 | P11: 0.0063897 | T11: =E36*$F$46/(O11*1000) -> 0.1471069 | V11: 3 | AA11: =O11*AGR_LAND!$U$74*AGR_LAND!$G$68 -> 91.345096 | AF11: 0.322 | AG11: =AF11*0.95 -> 0.3059
D12: AGR_RESID_CROP_RYE | O12: 0.3059 | P12: 0.0580063 | T12: =E36*$F$46/(O12*1000) -> 0.1471069 | V12: 3 | AA12: =AGR_LAND!$U$82*AGR_LAND!$G$76 -> 562.57421 | AF12: 0.322 | AG12: =AF12*0.95 -> 0.3059
D13: AGR_RESID_CROP_MILL-BUCK | O13: 0.3059 | P13: 0.0008202 | T13: =E36*$F$46/(O13*1000) -> 0.1471069 | V13: 3 | Y13: AGR_LIV_MANURE_RABBIT | AA13: =O13*AGR_LAND!$U$90*AGR_LAND!$G$84 -> 15.901874 | AF13: 0 | AG13: =AF13*0.95 -> 0
D14: AGR_LIV_MANURE_CAT_DAIRY | O14: 0.09785 | P14: 0.3757413 | T14: =E36*$F$45/(O14*1000) -> 0.59785386 | V14: 3 | Y14: AGR_LIV_MANURE_FUR | AA14: =#REF!*AGR_LAND!$U$95*AGR_LAND!$G$92 -> #REF! | AF14: 0 | AG14: =AF14*0.95 -> 0
D15: AGR_LIV_MANURE_CAT_NON-DAIRY | O15: 0.09785 | P15: 0.241698 | T15: =E36*$F$45/(O15*1000) -> 0.59785386 | V15: 3 | AA15: =#REF!*AGR_LAND!$U$100*AGR_LAND!$G$97 -> #REF! | AF15: 0 | AG15: =AF15*0.95 -> 0
D16: AGR_LIV_MANURE_SWINE | O16: 0.011875 | P16: 0.1680845 | T16: =E36*$F$45/(O16*1000) -> 4.9263158 | V16: 3 | X16: 0.071862 | Y16: AGR_RESID_CROP_PULS-FEED | AA16: =#REF!*AGR_LAND!$U$105*AGR_LAND!$G$102 -> #REF! | AF16: 0 | AG16: =AF16*0.95 -> 0
B17: =IF(O17>0,"","\I:") | D17: AGR_LIV_MANURE_POULTRY | O17: 0.08835 | P17: 0.0491548 | T17: =E36*$F$45/(O17*1000) -> 0.66213922 | V17: 3 | X17: 0.039538 | Y17: AGR_RESID_CROP_PULS-EDIB | AA17: =#REF!*AGR_LAND!$U$110*AGR_LAND!$G$107 -> #REF! | AF17: 0 | AG17: =AF17*0.95 -> 0
E18: =AGR_Comm!D14 -> PRI_BIOG_AGR | M18: 23 | N18: =M18/1000 -> 0.023 | AA18: =#REF!*AGR_LAND!$U$115*AGR_LAND!$G$112 -> #REF! | AC18: suma_land | AF18: 0 | AG18: =AF18*0.95 -> 0
AA19: =#REF!*AGR_LAND!U120*AGR_LAND!G117 -> #REF! | AC19: =SUM(AA6:AA19) -> #REF! | AF19: 0.103 | AG19: =AF19*0.95 -> 0.09785
AA20: =O14*AGR_LIV!$U$12*AGR_LIV!$G$5 -> 1458.2067 | AF20: 0.103 | AG20: =AF20*0.95 -> 0.09785
AA21: =O15*AGR_LIV!$U$23*AGR_LIV!$G$16 -> 1175.3398 | AF21: 0 | AG21: =AF21*0.95 -> 0
AA22: =#REF!*AGR_LIV!$U$30*AGR_LIV!$G$27 -> #REF! | AF22: =0.0125 -> 0.0125 | AG22: =AF22*0.95 -> 0.011875
AA23: =O16*AGR_LIV!$U$41*AGR_LIV!$G$34 -> 111.36176 | AF23: 0 | AG23: =AF23*0.95 -> 0
AA24: =#REF!*AGR_LIV!$U$48*AGR_LIV!$G$45 -> #REF! | AC24: suma_liv | AF24: =0.093 -> 0.093 | AG24: =AF24*0.95 -> 0.08835
X25: 0.060318 | Y25: AGR_RESID_CROP_POTATO | AA25: =O17*AGR_LIV!$U$59*AGR_LIV!$G$52 -> 237.54008 | AC25: =SUM(AA20:AA25) -> #REF!
X26: 0.051082 | Y26: AGR_RESID_CROP_STR-HAY
X27: 0.063204 | Y27: AGR_RESID_CROP_OIL | AA27: suma
X28: 0.038672 | Y28: AGR_RESID_CROP_FRUIT | AA28: =SUM(AA6:AA25) -> #REF!
X29: 0.04964 | Y29: AGR_RESID_CROP_VEG
L31: =L32*17695.67 -> 39.82499
L32: =N18*O15 -> 0.00225055
D36: EUR/PLN = | E36: 4.5
D38: Kategoria kosztu | E38: Instalacja średnia (3–8 MW) | F38: Instalacja duża (>14 MW)
D39: CAPEX – część biogazowa [€/kW] | E39: 4300 | F39: 1600
D40: CAPEX – upgrading [€/kW] | E40: 800 | F40: 300
D41: CAPEX – przyłącze i downstream [€/kW] | E41: 270 | F41: 100
D42: OPEX – część biogazowa [€/MWh] | E42: 20 | F42: 20
D43: OPEX – upgrading [€/MWh] | E43: 15 | F43: 10
D44: Gnojowica [€/t] | E44: 2 | F44: 3
D45: Obornik [€/t] | E45: 16 | F45: 13
D46: Odpadów pozbożowe | E46: 10 | F46: 10
D48: LHV | F48: =N18*1000/3.6 -> 6.3888889 | G48: kWh/m3

Sheet AGR_CHP
B2: EC Rolnicze | Combined Heat and Power Plants in Agriculture
E4: ~FI_T: PL
B5: TechName | C5: *TechDesc | D5: Comm-IN | E5: Comm-OUT | F5: Share~2020~2021~FX | G5: Share~2025~FX | H5: Share~2030~FX | I5: Share~2035~FX | J5: Share~2040~FX | K5: Share~2045~FX | L5: Share~2050~FX | M5: Stock~2020~2021 | N5: Stock~2025 | O5: Stock~2030 | P5: Stock~2035 | Q5: Stock~2040 | R5: Stock~2045 | S5: Stock~2050 | T5: EFF | U5: CHPR~FX | V5: CHPR~LO | W5: CHPR~UP | X5: CEH | Y5: BNDACT~2020~2021~UP | Z5: AFA | AA5: AFA~LO | AB5: Cap2Act | AC5: FIXOM | AD5: VAROM
B6: \I: | M6: GW | N6: GW | O6: GW | P6: GW | Q6: GW | R6: GW | S6: GW | T6: % | U6: % | V6: % | W6: % | X6: % | Y6: PJ | Z6: % | AA6: % | AB6: PJ/GW | AC6: zl/kW | AD6: zl/GJ
B7: =AGR_Proc!D22 -> CHPI_EX_BIOG_AGR | C7: =AGR_Proc!E22 -> Industrial Chp Plants for biogas from agriculture residues | D7: =SECTF!E22 -> AGR_BIOG | M7: 0.117868 | N7: 0.117868 | O7: 0.117868 | P7: 0.117868 | Q7: 0.117868 | R7: 0.117868 | S7: 0.117868 | T7: 0.4 | U7: 1 | Z7: 0.81 | AB7: 31.536 | AC7: 125 | AD7: 2.778
E8: =AGR_Comm!D100 -> ELC_GNC
E9: =AGR_Comm!D31 -> AGR_HT_OWN_USE
M12: =M7*AB7*Z7 -> 3.0108391

Sheet DIV
B2: Voltage Dividers
E3: NIEAKTYWNE~FI_T: PL
B5: TechName | C5: * TechDesc | D5: Comm-IN | E5: Comm-OUT | F5: Share-O~UP | G5: EFF
B6: \I: | F6: %
B8: =AGR_Proc!D23 -> ELC_VOLT_DIV_AGR_CHPI | C8: =AGR_Proc!E23 -> Voltage Divider - AGR CHPI | D8: =AGR_Comm!D100 -> ELC_GNC | G8: 1
E9: ELC_HV | F9: 0
E10: ELC_MV | F10: 1
E11: ELC_LV | F11: 0
B14: Heat Dividers
E15: NIEAKTYWNE~~FI_T: PL
B17: TechName | C17: * TechDesc | D17: Comm-IN | E17: Comm-OUT | F17: Share-O~UP | G17: EFF
B18: \I: | F18: %
B19: =AGR_Proc!D24 -> HT_DIV_AGR_CHPI | C19: =AGR_Proc!E24 -> Heat Divider - AGR CHPI | D19: =AGR_Comm!D30 -> HT_AGR_CHPI | G19: 1
E20: =AGR_Comm!D31 -> AGR_HT_OWN_USE | F20: 1
E21: HT_HT_I | F21: 0
E26: ~FI_T:PL
B27: TechName | C27: \I: TechDesc | D27: Comm-IN | E27: Comm-OUT | F27: EFF
B28: \I:
B29: =AGR_Proc!D20 -> AGR_DEM_OWN_HEAT | C29: Industrial Own Heat Consumption | D29: =AGR_Comm!D31 -> AGR_HT_OWN_USE | E29: =AGR_Comm!D92 -> AGR_DEM_HT_OWN_USE | F29: 1

Sheet AGR_FEC
B2: Final energy consumption
E4: ~FI_T: PL
B5: TechName | C5: * TechDesc | D5: Comm-IN | E5: Comm-OUT | F5: Input~2020 | G5: Input~2050
B6: * Technology name | C6: Technology description | D6: Commodity input | E6: Commodity output | F6: Fuel Input per 1 IPI | G6: Fuel Input per 1 IPI | J6: Agriculture Input [PJ] - see sheet ESTAT_2020
B7: =AGR_Proc!D21 -> AGR_DEM_AGR | C7: =AGR_Proc!E21 -> Agriculture Demand Process | D7: =AGR_Comm!D7 -> AGR_HC | F7: =IF(J7<>0,J7/100,"") -> 0.3131203 | G7: 0 | I7: AGR_HC | J7: 31.31203
B8: =IF(J8>0,"","\I:") | D8: =AGR_Comm!D8 -> AGR_BC | F8: =IF(J8<>0,J8/100,"") -> 0.0026657356 | G8: 0 | I8: AGR_BC | J8: 0.26657356
B9: =IF(J9>0,"","\I:") | D9: =AGR_Comm!D9 -> AGR_OIL_GSL | F9: =IF(J9<>0,J9/100,"") -> 0.00045719856 | G9: 0 | I9: AGR_OIL_GSL | J9: 0.045719856
B10: =IF(J10>0,"","\I:") | D10: =AGR_Comm!D10 -> AGR_OIL_DSL | F10: =IF(J10<>0,J10/100,"") -> 0.97438015 | G10: 0 | I10: AGR_OIL_DSL | J10: 97.438015
B11: =IF(J11>0,"","\I:") | D11: =AGR_Comm!D11 -> AGR_OIL_LPG | F11: =IF(J11<>0,J11/100,"") -> 0.028520063 | G11: 0 | I11: AGR_OIL_LPG | J11: 2.8520063
B12: =IF(J12>0,"","\I:") | D12: =AGR_Comm!D12 -> AGR_OIL_FUE | F12: =IF(J12<>0,J12/100,"") -> 0.0040888289 | G12: 0 | I12: AGR_OIL_FUE | J12: 0.40888289
B13: =IF(J13>0,"","\I:") | D13: =AGR_Comm!D13 -> AGR_NAT_GAS | F13: =IF(J13<>0,J13/100,"") -> 0.01805725 | G13: =IF(F17/SUM(F7:F13,F16:F17,F19)>=0.5,SUM(F7:F13,F16,F19),SUM(F7:F13,F16:F17,F19)/2) -> 0.70363612 | I13: AGR_NAT_GAS | J13: 1.805725
B14: =IF(J14>0,"","\I:") | D14: =OLD_AGR_Comm!D14 -> AGR_BIOG | F14: =IF(J14<>0,J14/100,"") -> 0.0037036433 | G14: =F14 -> 0.0037036433 | I14: AGR_BIOG | J14: 0.37036433
B15: =IF(J15>0,"","\I:") | D15: =AGR_Comm!D17 -> AGR_BIOM | F15: =IF(J15<>0,J15/100,"") -> 0.20068044 | G15: =F15 -> 0.20068044 | I15: AGR_BIOM | J15: 20.068044
B16: =IF(J16>0,"","\I:") -> \I: | D16: =AGR_Comm!D18 -> AGR_RDF | F16: =IF(J16<>0,J16/100,"") | I16: AGR_RDF | J16: 0
B17: =IF(J17>0,"","\I:") | D17: =AGR_Comm!D19 -> AGR_ELC | F17: =IF(J17<>0,J17/100,"") -> 0.065982712 | G17: =IF(F17/SUM(F7:F13,F16:F17,F19)>=0.5,F17,SUM(F7:F13,F16:F17,F19)/2) -> 0.70363612 | I17: AGR_ELC | J17: 6.5982712
B18: =IF(J18>0,"","\I:") | D18: =AGR_Comm!D20 -> AGR_DH | F18: =IF(J18<>0,J18/100,"") -> 0.0077501855 | G18: =F18 -> 0.0077501855 | I18: AGR_DH | J18: 0.77501855
B19: =IF(J19>0,"","\I:") -> \I: | D19: =AGR_Comm!D21 -> AGR_OTH_FUE | F19: =IF(J19<>0,J19/100,"") | I19: AGR_OTH_FUE | J19: 0
E20: =AGR_Comm!D22 -> AGR_DEM | J20: =SUM(J7:J19) -> 161.94065

Sheet EMI
B2: Emisje sektorowe | Sectoral emissions
C4: ~PRCCOMEMI: PL
B5: TechName | C5: CommName | D5: AGR_HC | E5: AGR_BC | F5: AGR_OIL_GSL | G5: AGR_OIL_DSL | H5: AGR_OIL_LPG | I5: AGR_OIL_FUE | J5: AGR_NAT_GAS | K5: AGR_BIOG | L5: AGR_BIOM | M5: AGR_RDF | N5: AGR_OTH_FUE
B6: \I: | D6: kt/PJ
B7: =AGR_Proc!$D$21 -> AGR_DEM_AGR | C7: =AGR_Comm!D23 -> AGR_CO2 | D7: 94.19 | E7: 109.08 | F7: 68.61 | G7: 73.33 | H7: 62.44 | I7: 76.59 | J7: 55.82 | K7: 0 | L7: 0 | M7: =D7*0.85 -> 80.0615 | N7: =D7 -> 94.19
B8: =AGR_Proc!$D$21 -> AGR_DEM_AGR | C8: =AGR_Comm!D24 -> AGR_SO2 | D8: 0.5330476 | E8: 0.5330476 | F8: 0.000747851 | G8: 0.000730596 | H8: 4.75959e-05 | I8: 0.000327596 | J8: 4.75959e-05 | K8: 4.75959e-06 | L8: 0.025047596 | M8: 0.025047596 | N8: 0.025047596
B9: =AGR_Proc!$D$21 -> AGR_DEM_AGR | C9: =AGR_Comm!D25 -> AGR_NOX | D9: 0.60670448 | E9: 0.60670448 | F9: 0.88470448 | G9: 0.85470448 | H9: 0.87470448 | I9: 0.50670448 | J9: 0.51470448 | K9: 0.51470448 | L9: 0.54470448 | M9: 0.54470448 | N9: 0.54470448
B10: =AGR_Proc!$D$21 -> AGR_DEM_AGR | C10: =AGR_Comm!D26 -> AGR_TSP | D10: 0.74417388 | E10: 0.74417388 | F10: 0.32875513 | G10: 0.33490388 | H10: 0.32828252 | I10: 0.33037388 | J10: 0.32917388 | K10: 0.32917388 | L10: 1.0489739 | M10: 1.0489739 | N10: 1.0489739
B11: =AGR_Proc!$D$21 -> AGR_DEM_AGR | C11: =AGR_Comm!D27 -> AGR_PM10 | D11: 0.55754892 | E11: 0.55754892 | F11: 0.19233017 | G11: 0.19847892 | H11: 0.19185756 | I11: 0.19394892 | J11: 0.20354892 | K11: 0.20354892 | L11: 0.87654892 | M11: 0.87654892 | N11: 0.87654892
B12: =AGR_Proc!$D$21 -> AGR_DEM_AGR | C12: =AGR_Comm!D28 -> AGR_PM2.5 | D12: 0.35625308 | E12: 0.35625308 | F12: 0.022034333 | G12: 0.028183083 | H12: 0.021561725 | I12: 0.023653083 | J12: 0.022453083 | K12: 0.022453083 | L12: 0.65625308 | M12: 0.65625308 | N12: 0.65625308
B13: \I: | D13: t/PJ
B14: =AGR_Proc!$D$21 -> AGR_DEM_AGR | C14: =AGR_Comm!D29 -> AGR_HG | D14: 0.003 | E14: 0.004 | F14: 6.81293E-05 | G14: 0.00018

Sheet ESTAT_2020
A2: Poland
I4: TOTAL | J4: C0000X0350-0370 | K4: C0110 | L4: C0121 | M4: C0129 | N4: C0210 | O4: C0220 | P4: C0320 | Q4: C0311 | R4: C0312 | S4: C0340 | T4: C0330 | U4: C0350-0370 | V4: C0360 | W4: C0350 | X4: C0371 | Y4: C0379 | Z4: P1000 | AA4: P1100 | AB4: P1200 | AC4: S2000 | AD4: O4000XBIO | AE4: O4100_TOT | AF4: O4200 | AG4: O4300 | AH4: O4400X4410 | AI4: O4500 | AJ4: O4610 | AK4: O4620 | AL4: O4630 | AM4: O4652XR5210B | AN4: O4651 | AO4: O4653 | AP4: O4661XR5230B | AQ4: O4669 | AR4: O4640 | AS4: O4671XR5220B | AT4: O4680 | AU4: O4691 | AV4: O4692 | AW4: O4695 | AX4: O4694 | AY4: O4693 | AZ4: O4699 | BA4: G3000 | BB4: RA000 | BC4: RA100 | BD4: RA500 | BE4: RA300 | BF4: RA420 | BG4: RA410 | BH4: RA200 | BI4: R5110-5150_W6000RI | BJ4: R5160 | BK4: R5300 | BL4: W6210 | BM4: R5210P | BN4: R5210B | BO4: R5220P | BP4: R5220B | BQ4: R5230P | BR4: R5230B | BS4: R5290 | BT4: RA600 | BU4: W6100_6220 | BV4: W6100 | BW4: W6220 | BX4: N900H | BY4: H8000 | BZ4: E7000 | CA4: FE | CB4: BIOE
D5: ktoe | F5: 2020 | I5: Total | J5: Solid fossil fuels | K5: Anthracite | L5: Coking coal | M5: Other bituminous coal | N5: Sub-bituminous coal | O5: Lignite | P5: Patent fuel | Q5: Coke oven coke | R5: Gas coke | S5: Coal tar | T5: Brown coal briquettes | U5: Manufactured gases | V5: Gas works gas | W5: Coke oven gas | X5: Blast furnace gas | Y5: Other recovered gases | Z5: Peat and peat products | AA5: Peat | AB5: Peat products | AC5: Oil shale and oil sands | AD5: Oil and petroleum products | AE5: Crude oil | AF5: Natural gas liquids | AG5: Refinery feedstocks | AH5: Additives and oxygenates (excluding biofuel portion) | AI5: Other hydrocarbons | AJ5: Refinery gas | AK5: Ethane | AL5: Liquefied petroleum gases | AM5: Motor gasoline (excluding biofuel portion) | AN5: Aviation gasoline | AO5: Gasoline-type jet fuel | AP5: Kerosene-type jet fuel (excluding biofuel portion) | AQ5: Other kerosene | AR5: Naphtha | AS5: Gas oil and diesel oil (excluding biofuel portion) | AT5: Fuel oil | AU5: White spirit and special boiling point industrial spirits | AV5: Lubricants | AW5: Bitumen | AX5: Petroleum coke | AY5: Paraffin waxes | AZ5: Other oil products | BA5: Natural gas | BB5: Renewables and biofuels | BC5: Hydro | BD5: Tide, wave, ocean | BE5: Wind | BF5: Solar photovoltaic | BG5: Solar thermal | BH5: Geothermal | BI5: Primary solid biofuels | BJ5: Charcoal | BK5: Biogases | BL5: Renewable municipal waste | BM5: Pure biogasoline | BN5: Blended biogasoline | BO5: Pure biodiesels | BP5: Blended biodiesels | BQ5: Pure bio jet kerosene | BR5: Blended bio jet kerosene | BS5: Other liquid biofuels | BT5: Ambient heat (heat pumps) | BU5: Non-renewable waste | BV5: Industrial waste (non-renewable) | BW5: Non-renewable municipal waste | BX5: Nuclear heat | BY5: Heat | BZ5: Electricity | CA5: Fossil energy | CB5: Bioenergy
A6: + | B6: Other sectors | H6: FC_OTH_E | I6: 32550.846 | J6: 6462.37 | K6: 0 | L6: 0.003 | M6: 6400.717 | N6: 0 | O6: 23.509 | P6: 0.044 | Q6: 36.678 | R6: 0 | S6: 0 | T6: 1.42 | U6: 13.924 | V6: 0 | W6: 13.924 | X6: 0 | Y6: 0 | Z6: 0 | AA6: 0 | AB6: 0 | AC6: 0 | AD6: 3409.873 | AE6: 0 | AF6: 0 | AG6: Z | AH6: Z | AI6: Z | AJ6: 0 | AK6: 0 | AL6: 672.399 | AM6: 1.092 | AN6: 0 | AO6: 0 | AP6: 0 | AQ6: 0.251 | AR6: 0 | AS6: 2726.365 | AT6: 9.766 | AU6: 0 | AV6: 0 | AW6: 0 | AX6: 0 | AY6: 0 | AZ6: 0 | BA6: 5028.639 | BB6: 5990.688 | BC6: Z | BD6: Z | BE6: Z | BF6: Z | BG6: 80.144 | BH6: 25.64 | BI6: 5511.311 | BJ6: 0 | BK6: 74.339 | BL6: 0.252 | BM6: 0 | BN6: 0 | BO6: 0 | BP6: 0 | BQ6: 0 | BR6: 0 | BS6: 1 | BT6: 298.003 | BU6: 33.232 | BV6: 4.076 | BW6: 29.155 | BX6: Z | BY6: 4747.023 | BZ6: 6865.097 | CA6: 24944.828 | CB6: 6302.671 | CD6: =BZ6*41.868/1000 -> 287.42788
B7: + | C7: Commercial & public services | H7: FC_OTH_CP_E | I7: 7580.285 | J7: 507.997 | K7: 0 | L7: 0.003 | M7: 496.81 | N7: 0 | O7: 1.345 | P7: 0 | Q7: 9.839 | R7: 0 | S7: 0 | T7: 0 | U7: 13.924 | V7: 0 | W7: 13.924 | X7: 0 | Y7: 0 | Z7: 0 | AA7: 0 | AB7: 0 | AC7: 0 | AD7: 386.387 | AE7: 0 | AF7: 0 | AG7: Z | AH7: Z | AI7: Z | AJ7: 0 | AK7: 0 | AL7: 54.935 | AM7: 0 | AN7: 0 | AO7: 0 | AP7: 0 | AQ7: 0.139 | AR7: 0 | AS7: 331.314 | AT7: 0 | AU7: 0 | AV7: 0 | AW7: 0 | AX7: 0 | AY7: 0 | AZ7: 0 | BA7: 1144.083 | BB7: 276.825 | BC7: Z | BD7: Z | BE7: Z | BF7: Z | BG7: 5.609 | BH7: 6.41 | BI7: 177.969 | BJ7: 0 | BK7: 65.493 | BL7: 0.252 | BM7: 0 | BN7: 0 | BO7: 0 | BP7: 0 | BQ7: 0 | BR7: 0 | BS7: 1 | BT7: 20.093 | BU7: 33.232 | BV7: 4.076 | BW7: 29.155 | BX7: Z | BY7: 1091.606 | BZ7: 4126.231 | CA7: 6463.535 | CB7: 543.99 | CD7: =BZ7*41.868/1000 -> 172.75704
B8: + | C8: Households | H8: FC_OTH_HH_E | I8: 21101.347 | J8: 5200.131 | K8: 0 | L8: 0 | M8: 5159.958 | N8: 0 | O8: 17.216 | P8: 0 | Q8: 22.957 | R8: 0 | S8: 0 | T8: 0 | U8: 0 | V8: 0 | W8: 0 | X8: 0 | Y8: 0 | Z8: 0 | AA8: 0 | AB8: 0 | AC8: 0 | AD8: 617.13 | AE8: 0 | AF8: 0 | AG8: Z | AH8: Z | AI8: Z | AJ8: 0 | AK8: 0 | AL8: 549.346 | AM8: 0 | AN8: 0 | AO8: 0 | AP8: 0 | AQ8: 0 | AR8: 0 | AS8: 67.784 | AT8: 0 | AU8: 0 | AV8: 0 | AW8: 0 | AX8: 0 | AY8: 0 | AZ8: 0 | BA8: 3841.427 | BB8: 5225.7 | BC8: Z | BD8: Z | BE8: Z | BF8: Z | BG8: 74.535 | BH8: 19.23 | BI8: 4854.025 | BJ8: 0 | BK8: 0 | BL8: 0 | BM8: 0 | BN8: 0 | BO8: 0 | BP8: 0 | BQ8: 0 | BR8: 0 | BS8: 0 | BT8: 277.91 | BU8: 0 | BV8: 0 | BW8: 0 | BX8: Z | BY8: 3636.906 | BZ8: 2580.053 | CA8: 15130.823 | CB8: 5260.746 | CD8: =BZ8*41.868/1000 -> 108.02166
B9: + | C9: Agriculture & forestry | H9: FC_OTH_AF_E | I9: 3867.885 | J9: 754.242 | K9: 0 | L9: 0 | M9: 743.949 | N9: 0 | O9: 4.947 | P9: 0.044 | Q9: 3.882 | R9: 0 | S9: 0 | T9: 1.42 | U9: 0 | V9: 0 | W9: 0 | X9: 0 | Y9: 0 | Z9: 0 | AA9: 0 | AB9: 0 | AC9: 0 | AD9: 2406.243 | AE9: 0 | AF9: 0 | AG9: Z | AH9: Z | AI9: Z | AJ9: 0 | AK9: 0 | AL9: 68.119 | AM9: 1.092 | AN9: 0 | AO9: 0 | AP9: 0 | AQ9: 0 | AR9: 0 | AS9: 2327.267 | AT9: 9.766 | AU9: 0 | AV9: 0 | AW9: 0 | AX9: 0 | AY9: 0 | AZ9: 0 | BA9: 43.129 | BB9: 488.163 | BC9: Z | BD9: Z | BE9: Z | BF9: Z | BG9: 0 | BH9: 0 | BI9: 479.317 | BJ9: 0 | BK9: 8.846 | BL9: 0 | BM9: 0 | BN9: 0 | BO9: 0 | BP9: 0 | BQ9: 0 | BR9: 0 | BS9: 0 | BT9: Z | BU9: 0 | BV9: 0 | BW9: 0 | BX9: Z | BY9: 18.511 | BZ9: 157.597 | CA9: 3349.365 | CB9: 497.871 | CD9: =BZ9*41.868/1000 -> 6.5982712
B10: + | C10: Fishing | H10: FC_OTH_FISH_E | I10: 1.217 | J10: 0 | K10: 0 | L10: 0 | M10: 0 | N10: 0 | O10: 0 | P10: 0 | Q10: 0 | R10: 0 | S10: 0 | T10: 0 | U10: 0 | V10: 0 | W10: 0 | X10: 0 | Y10: 0 | Z10: 0 | AA10: 0 | AB10: 0 | AC10: 0 | AD10: 0 | AE10: 0 | AF10: 0 | AG10: Z | AH10: Z | AI10: Z | AJ10: 0 | AK10: 0 | AL10: 0 | AM10: 0 | AN10: 0 | AO10: 0 | AP10: 0 | AQ10: 0 | AR10: 0 | AS10: 0 | AT10: 0 | AU10: 0 | AV10: 0 | AW10: 0 | AX10: 0 | AY10: 0 | AZ10: 0 | BA10: 0 | BB10: 0 | BC10: Z | BD10: Z | BE10: Z | BF10: Z | BG10: 0 | BH10: 0 | BI10: 0 | BJ10: 0 | BK10: 0 | BL10: 0 | BM10: 0 | BN10: 0 | BO10: 0 | BP10: 0 | BQ10: 0 | BR10: 0 | BS10: 0 | BT10: Z | BU10: 0 | BV10: 0 | BW10: 0 | BX10: Z | BY10: 0 | BZ10: 1.217 | CA10: 0.993 | CB10: 0.064 | CD10: =BZ10*41.868/1000 -> 0.050953356
B11: + | C11: Not elsewhere specified (other) | H11: FC_OTH_NSP_E | I11: 0.112 | J11: 0 | K11: 0 | L11: 0 | M11: 0 | N11: 0 | O11: 0 | P11: 0 | Q11: 0 | R11: 0 | S11: 0 | T11: 0 | U11: 0 | V11: 0 | W11: 0 | X11: 0 | Y11: 0 | Z11: 0 | AA11: 0 | AB11: 0 | AC11: 0 | AD11: 0.112 | AE11: 0 | AF11: 0 | AG11: Z | AH11: Z | AI11: Z | AJ11: 0 | AK11: 0 | AL11: 0 | AM11: 0 | AN11: 0 | AO11: 0 | AP11: 0 | AQ11: 0.112 | AR11: 0 | AS11: 0 | AT11: 0 | AU11: 0 | AV11: 0 | AW11: 0 | AX11: 0 | AY11: 0 | AZ11: 0 | BA11: 0 | BB11: 0 | BC11: Z | BD11: Z | BE11: Z | BF11: Z | BG11: 0 | BH11: 0 | BI11: 0 | BJ11: 0 | BK11: 0 | BL11: 0 | BM11: 0 | BN11: 0 | BO11: 0 | BP11: 0 | BQ11: 0 | BR11: 0 | BS11: 0 | BT11: 0 | BU11: 0 | BV11: 0 | BW11: 0 | BX11: Z | BY11: 0 | BZ11: 0 | CA11: 0.112 | CB11: 0 | CD11: =BZ11*41.868/1000 -> 0
I16: AGR_HC | J16: AGR_BC | K16: AGR_OIL_GSL | L16: AGR_OIL_DSL | M16: AGR_OIL_LPG | N16: AGR_OIL_FUE | O16: AGR_NAT_GAS | P16: AGR_BIOG | Q16: AGR_BIOM | R16: AGR_RDF | S16: AGR_ELC | T16: AGR_DH | U16: AGR_OTH_FUE
F17: ktoe | H17: =B6 -> Other sectors | I17: =K6+L6+M6+N6+P6+Q6+R6+S6+U6+V6+W6+X6+Y6 -> 6465.29 | J17: =O6+T6 -> 24.929 | K17: =AM6 -> 1.092 | L17: =AS6 -> 2726.365 | M17: =AL6 -> 672.399 | N17: =AT6 -> 9.766 | O17: =BA6 -> 5028.639 | P17: =BK6 -> 74.339 | Q17: =BI6 -> 5511.311 | R17: =BL6+BW6 -> 29.407 | S17: =BZ6 -> 6865.097 | T17: =BY6 -> 4747.023 | U17: =AQ6+BG6+BH6+BS6+BT6+BU6+BV6 -> 442.346 | W17: =SUM(I17:U17) -> 32598.003 | X17: =W17-I6 -> 47.157
H18: =C7 -> Commercial & public services | I18: =K7+L7+M7+N7+P7+Q7+R7+S7+U7+V7+W7+X7+Y7 -> 534.5 | J18: =O7+T7 -> 1.345 | K18: =AM7 -> 0 | L18: =AS7 -> 331.314 | M18: =AL7 -> 54.935 | N18: =AT7 -> 0 | O18: =BA7 -> 1144.083 | P18: =BK7 -> 65.493 | Q18: =BI7 -> 177.969 | R18: =BL7+BW7 -> 29.407 | S18: =BZ7 -> 4126.231 | T18: =BY7 -> 1091.606 | U18: =AQ7+BG7+BH7+BS7+BT7+BU7+BV7 -> 70.559 | W18: =SUM(I18:U18) -> 7627.442 | X18: =W18-I7 -> 47.157
H19: =C8 -> Households | I19: =K8+L8+M8+N8+P8+Q8+R8+S8+U8+V8+W8+X8+Y8 -> 5182.915 | J19: =O8+T8 -> 17.216 | K19: =AM8 -> 0 | L19: =AS8 -> 67.784 | M19: =AL8 -> 549.346 | N19: =AT8 -> 0 | O19: =BA8 -> 3841.427 | P19: =BK8 -> 0 | Q19: =BI8 -> 4854.025 | R19: =BL8+BW8 -> 0 | S19: =BZ8 -> 2580.053 | T19: =BY8 -> 3636.906 | U19: =AQ8+BG8+BH8+BS8+BT8+BU8+BV8 -> 371.675 | W19: =SUM(I19:U19) -> 21101.347 | X19: =W19-I8 -> 0
H20: =C9 -> Agriculture & forestry | I20: =K9+L9+M9+N9+P9+Q9+R9+S9+U9+V9+W9+X9+Y9 -> 747.875 | J20: =O9+T9 -> 6.367 | K20: =AM9 -> 1.092 | L20: =AS9 -> 2327.267 | M20: =AL9 -> 68.119 | N20: =AT9 -> 9.766 | O20: =BA9 -> 43.129 | P20: =BK9 -> 8.846 | Q20: =BI9 -> 479.317 | R20: =BL9+BW9 -> 0 | S20: =BZ9 -> 157.597 | T20: =BY9 -> 18.511 | U20: =AQ9+BG9+BH9+BS9+BU9+BV9 -> 0 | W20: =SUM(I20:U20) -> 3867.886 | X20: =W20-I9 -> 0.001
H21: =C10 -> Fishing | I21: =K10+L10+M10+N10+P10+Q10+R10+S10+U10+V10+W10+X10+Y10 -> 0 | J21: =O10+T10 -> 0 | K21: =AM10 -> 0 | L21: =AS10 -> 0 | M21: =AL10 -> 0 | N21: =AT10 -> 0 | O21: =BA10 -> 0 | P21: =BK10 -> 0 | Q21: =BI10 -> 0 | R21: =BL10+BW10 -> 0 | S21: =BZ10 -> 1.217 | T21: =BY10 -> 0 | U21: =AQ10+BG10+BH10+BS10+BU10+BV10 -> 0 | W21: =SUM(I21:U21) -> 1.217 | X21: =W21-I10 -> 0
H22: =C11 -> Not elsewhere specified (other) | I22: =K11+L11+M11+N11+P11+Q11+R11+S11+U11+V11+W11+X11+Y11 -> 0 | J22: =O11+T11 -> 0 | K22: =AM11 -> 0 | L22: =AS11 -> 0 | M22: =AL11 -> 0 | N22: =AT11 -> 0 | O22: =BA11 -> 0 | P22: =BK11 -> 0 | Q22: =BI11 -> 0 | R22: =BL11+BW11 -> 0 | S22: =BZ11 -> 0 | T22: =BY11 -> 0 | U22: =AQ11+BG11+BH11+BS11+BU11+BV11 -> 0.112
I24: =I16 -> AGR_HC | J24: =J16 -> AGR_BC | K24: =K16 -> AGR_OIL_GSL | L24: =L16 -> AGR_OIL_DSL | M24: =M16 -> AGR_OIL_LPG | N24: =N16 -> AGR_OIL_FUE | O24: =O16 -> AGR_NAT_GAS | P24: =P16 -> AGR_BIOG | ... U24: =U16 -> AGR_OTH_FUE
F25: PJ | H25: Commercial | I25: =I18*41.868/1000 -> 22.378446 | J25: =J18*41.868/1000 -> 0.05631246 | K25: =K18*41.868/1000 -> 0 | L25: =L18*41.868/1000 -> 13.871455 | M25: =M18*41.868/1000 -> 2.3000186 | N25: =N18*41.868/1000 -> 0 | O25: =O18*41.868/1000 -> 47.900467 | P25: =P18*41.868/1000 -> 2.7420609 | ... U25: =U18*41.868/1000 -> 2.9541642 | W25: =SUM(I25:U25) -> 319.34574
H26: Agriculture | I26: =I20*41.868/1000 -> 31.31203 | J26: =J20*41.868/1000 -> 0.26657356 | K26: =K20*41.868/1000 -> 0.045719856 | L26: =L20*41.868/1000 -> 97.438015 | M26: =M20*41.868/1000 -> 2.8520063 | N26: =N20*41.868/1000 -> 0.40888289 | O26: =O20*41.868/1000 -> 1.805725 | P26: =P20*41.868/1000 -> 0.37036433 | ... U26: =U20*41.868/1000 -> 0 | W26: =SUM(I26:U26) -> 161.94065

Sheet GUS_2020_HT_ELC
A1: Tabl. 4(94) Bilans całkowity (2020)
A2: Table 4(94) Complete balance (2020)
A3: WYSZCZEGÓLNIENIE | B3: Energia cieplna | C3: Energia elektryczna | D3: Energia cieplna | E3: Energia elektryczna
A4: SPECIFICATION | B4: Heat | C4: Electricity | D4: Heat | E4: Electricity
B5: PJ | D5: TWh
A6: Pozyskanie Primary production | B6: 1.130436 | D6: =IF(B6<>"",B6/3.6,"") -> 0.31401 | E6: =IF(C6<>"",C6/3.6,"") | F6: =IF(C6<>"",C6/3.6,"")
A7: Produkty z odzysku Recovered & recycled products | D7: =IF(B7<>"",B7/3.6,"") | E7: =IF(C7<>"",C7/3.6,"")
A8: Import Imports | C8: 74.231964 | D8: =IF(B8<>"",B8/3.6,"") | E8: =IF(C8<>"",C8/3.6,"") -> 20.61999
A9: Eksport Exports | C9: 26.502444 | D9: =IF(B9<>"",B9/3.6,"") | E9: =IF(C9<>"",C9/3.6,"") -> 7.36179
A10: Zmiana zapasów Change in stock | D10: =IF(B10<>"",B10/3.6,"") | E10: =IF(C10<>"",C10/3.6,"")
A11: Energia dostępna brutto Gross available energy | B11: 1.130436 | C11: 47.771388 | D11: =IF(B11<>"",B11/3.6,"") -> 0.31401 | E11: =IF(C11<>"",C11/3.6,"") -> 13.26983
A12: Międzynarodowy bunkier morski International maritime bunkers | D12: =IF(B12<>"",B12/3.6,"") | E12: =IF(C12<>"",C12/3.6,"")
A13: Krajowe zużycie brutto Gross inland consumption | B13: 1.130436 | C13: 47.771388 | D13: =IF(B13<>"",B13/3.6,"") -> 0.31401 | E13: =IF(C13<>"",C13/3.6,"") -> 13.26983
A14: Transport lotniczy międzynarodowy International aviation | D14: =IF(B14<>"",B14/3.6,"") | E14: =IF(C14<>"",C14/3.6,"")
A15: Całkowita podaż energii Total energy supply | B15: 1.130436 | C15: 47.771388 | D15: =IF(B15<>"",B15/3.6,"") -> 0.31401 | E15: =IF(C15<>"",C15/3.6,"") -> 13.26983
A16: Krajowe zużycie brutto (Europa 2020-2030) Gross inland consumption (Europe 2020-2030) | D16: =IF(B16<>"",B16/3.6,"") | E16: =IF(C16<>"",C16/3.6,"")
A17: Zużycie energii pierwotnej (Europa 2020-2030) Primary energy consumption (Europe 2020-2030) | D17: =IF(B17<>"",B17/3.6,"") | E17: =IF(C17<>"",C17/3.6,"")
A18: Zużycie końcowe energii (Europa 2020-2030) Final energy consumption (Europe 2020-2030) | D18: =IF(B18<>"",B18/3.6,"") | E18: =IF(C18<>"",C18/3.6,"")
A19: Wsad przemian Transformation input | B19: 1.758456 | C19: 4.270536 | D19: =IF(B19<>"",B19/3.6,"") -> 0.48846 | E19: =IF(C19<>"",C19/3.6,"") -> 1.18626
A20: Wytwarzanie energii elektrycznej i ciepła Electricity & heat generation | B20: 1.758456 | C20: 4.270536 | D20: =IF(B20<>"",B20/3.6,"") -> 0.48846 | E20: =IF(C20<>"",C20/3.6,"") -> 1.18626
A21: Elektrownie zawodowe Main activity producer electricity only | D21: =IF(B21<>"",B21/3.6,"") | E21: =IF(C21<>"",C21/3.6,"")
A22: Instalacje elektrociepłowni zawodowych Main activity producer CHP | D22: =IF(B22<>"",B22/3.6,"") | E22: =IF(C22<>"",C22/3.6,"")
A23: Ciepłownie zawodowe Main activity producer heat only | D23: =IF(B23<>"",B23/3.6,"") | E23: =IF(C23<>"",C23/3.6,"")
A24: Elektrownie przemysłowe Autoproducer electricity only | D24: =IF(B24<>"",B24/3.6,"") | E24: =IF(C24<>"",C24/3.6,"")
A25: Instalacje elektrociepłowni przemysłowych Autoproducer CHP | B25: 1.130436 | D25: =IF(B25<>"",B25/3.6,"") -> 0.31401 | E25: =IF(C25<>"",C25/3.6,"")
A26: Ciepłownie przemysłowe Autoproducer heat only | D26: =IF(B26<>"",B26/3.6,"") | E26: =IF(C26<>"",C26/3.6,"")
A27: Pompy ciepła Electrically driven heat pumps | C27: 0 | D27: =IF(B27<>"",B27/3.6,"") | E27: =IF(C27<>"",C27/3.6,"") -> 0
A28: Kotły elektryczne Electric boilers | D28: =IF(B28<>"",B28/3.6,"") | E28: =IF(C28<>"",C28/3.6,"")
A29: Elektrownie szczytowo-pompowe Electricity for pumped storage | C29: 4.270536 | D29: =IF(B29<>"",B29/3.6,"") | E29: =IF(C29<>"",C29/3.6,"") -> 1.18626
A30: Ciepło wykorzystane do produkcji energii elektrycznej Derived heat for electricity production | B30: 0.62802 | D30: =IF(B30<>"",B30/3.6,"") -> 0.17445 | E30: =IF(C30<>"",C30/3.6,"")
A31: Koksownie Coke ovens | D31: =IF(B31<>"",B31/3.6,"") | E31: =IF(C31<>"",C31/3.6,"")
A32: Wielkie piece Blast furnaces | D32: =IF(B32<>"",B32/3.6,"") | E32: =IF(C32<>"",C32/3.6,"")
A33: Gazownie Gas works | D33: =IF(B33<>"",B33/3.6,"") | E33: =IF(C33<>"",C33/3.6,"")
A34: Rafinerie Refineries & petrochemical industry | D34: =IF(B34<>"",B34/3.6,"") | E34: =IF(C34<>"",C34/3.6,"")
A35: Wsad do rafinerii Refinery intake | D35: =IF(B35<>"",B35/3.6,"") | E35: =IF(C35<>"",C35/3.6,"")
A36: Zwroty z sektora petrochemicznego Backflows from petrochemical industry | D36: =IF(B36<>"",B36/3.6,"") | E36: =IF(C36<>"",C36/3.6,"")
A37: Produkty przetwarzane Products transferred | D37: =IF(B37<>"",B37/3.6,"") | E37: =IF(C37<>"",C37/3.6,"")
A38: Produkty przeklasyfikowane Interproduct transfers | D38: =IF(B38<>"",B38/3.6,"") | E38: =IF(C38<>"",C38/3.6,"")
A39: Zużycie bezpośrednie Direct use | D39: =IF(B39<>"",B39/3.6,"") | E39: =IF(C39<>"",C39/3.6,"")
A40: Wsad do przemysłu petrochemicznego Petrochemical industry intake | D40: =IF(B40<>"",B40/3.6,"") | E40: =IF(C40<>"",C40/3.6,"")
A41: Brykietownie węgla kamiennego Patent fuel plants | D41: =IF(B41<>"",B41/3.6,"") | E41: =IF(C41<>"",C41/3.6,"")
A42: Brykietownie węgla brunatnego i torfu BKB & PB plants | D42: =IF(B42<>"",B42/3.6,"") | E42: =IF(C42<>"",C42/3.6,"")
... A48: Nigdzie indziej niewymienione Not elsewhere specified | D48: =IF(B48<>"",B48/3.6,"") | E48: =IF(C48<>"",C48/3.6,"")
A49: Uzysk przemian Transformation output | B49: 285.8747 | C49: 568.94425 | D49: =IF(B49<>"",B49/3.6,"") -> 79.40964 | E49: =IF(C49<>"",C49/3.6,"") -> 158.04007
A50: Wytwarzanie energii elektrycznej i ciepła Electricity & heat generation | B50: 285.8747 | C50: 568.94425 | D50: =IF(B50<>"",B50/3.6,"") -> 79.40964 | E50: =IF(C50<>"",C50/3.6,"") -> 158.04007
A51: Elektrownie zawodowe Main activity producer electricity only | C51: 82.521828 | D51: =IF(B51<>"",B51/3.6,"") | E51: =IF(C51<>"",C51/3.6,"") -> 22.92273
A52: Instalacje elektrociepłowni zawodowych Main activity producer CHP | B52: 169.81661 | C52: 415.79111 | D52: =IF(B52<>"",B52/3.6,"") -> 47.17128 | E52: =IF(C52<>"",C52/3.6,"") -> 115.49753
A53: Ciepłownie zawodowe Main activity producer heat only | B53: 93.909924 | D53: =IF(B53<>"",B53/3.6,"") -> 26.08609 | E53: =IF(C53<>"",C53/3.6,"")
A54: Elektrownie przemysłowe Autoproducer electricity only | C54: 7.075692 | D54: =IF(B54<>"",B54/3.6,"") | E54: =IF(C54<>"",C54/3.6,"") -> 1.96547
A55: Instalacje elektrociepłowni przemysłowych Autoproducer CHP | B55: 16.579728 | C55: 60.248052 | D55: =IF(B55<>"",B55/3.6,"") -> 4.60548 | E55: =IF(C55<>"",C55/3.6,"") -> 16.73557
A56: Ciepłownie przemysłowe Autoproducer heat only | B56: 4.898556 | D56: =IF(B56<>"",B56/3.6,"") -> 1.36071 | E56: =IF(C56<>"",C56/3.6,"")
A57: Pompy ciepła Electrically driven heat pumps | B57: 0 | D57: =IF(B57<>"",B57/3.6,"") -> 0 | E57: =IF(C57<>"",C57/3.6,"")
A58: Kotły elektryczne Electric boilers | D58: =IF(B58<>"",B58/3.6,"") | E58: =IF(C58<>"",C58/3.6,"")
A59: Elektrownie szczytowo-pompowe Electricity for pumped storage | C59: 2.93076 | D59: =IF(B59<>"",B59/3.6,"") | E59: =IF(C59<>"",C59/3.6,"") -> 0.8141
A60: Ciepło wykorzystane do produkcji energii elektrycznej Derived heat for electricity production | B60: 0.62802 | C60: 0.334944 | D60: =IF(B60<>"",B60/3.6,"") -> 0.17445 | E60: =IF(C60<>"",C60/3.6,"") -> 0.09304
A61: Koksownie Coke ovens | D61: =IF(B61<>"",B61/3.6,"") | E61: =IF(C61<>"",C61/3.6,"")
A62: Wielkie piece Blast furnaces | D62: =IF(B62<>"",B62/3.6,"") | E62: =IF(C62<>"",C62/3.6,"")
A63: Gazownie Gas works | D63: =IF(B63<>"",B63/3.6,"") | E63: =IF(C63<>"",C63/3.6,"")
A64: Rafinerie Refineries & petrochemical industry | D64: =IF(B64<>"",B64/3.6,"") | E64: =IF(C64<>"",C64/3.6,"")
A65: Uzysk rafinerii Refinery output | D65: =IF(B65<>"",B65/3.6,"") | E65: =IF(C65<>"",C65/3.6,"")
A66: Zwroty Backflows | D66: =IF(B66<>"",B66/3.6,"") | E66: =IF(C66<>"",C66/3.6,"")
A67: Produkty przetwarzane Products transferred | D67: =IF(B67<>"",B67/3.6,"") | E67: =IF(C67<>"",C67/3.6,"")
A68: Produkty przeklasyfikowane Interproduct transfers | D68: =IF(B68<>"",B68/3.6,"") | E68: =IF(C68<>"",C68/3.6,"")
A69: Dostawy produktów pierwotnych Primary products receips | D69: =IF(B69<>"",B69/3.6,"") | E69: =IF(C69<>"",C69/3.6,"")
A70: Zwroty z przemysłu petrochemicznego Petrochemical industry returns | D70: =IF(B70<>"",B70/3.6,"") | E70: =IF(C70<>"",C70/3.6,"")
A71: Brykietownie węgla kamiennego Patent fuel plants | D71: =IF(B71<>"",B71/3.6,"") | E71: =IF(C71<>"",C71/3.6,"")
A72: Brykietownie węgla brunatnego i torfu BKB & PB plants | D72: =IF(B72<>"",B72/3.6,"") | E72: =IF(C72<>"",C72/3.6,"")
... A78: Nigdzie indziej niewymienione Not elsewhere specified | D78: =IF(B78<>"",B78/3.6,"") | E78: =IF(C78<>"",C78/3.6,"")
A79: Sektor energetyczny Energy sector | B79: 25.288272 | C79: 87.50412 | D79: =IF(B79<>"",B79/3.6,"") -> 7.02452 | E79: =IF(C79<>"",C79/3.6,"") -> 24.3067
A80: Elektrownie, elektrociepłownie oraz ciepłownie Own use in electricity & heat generation | B80: 5.777784 | C80: 42.830964 | D80: =IF(B80<>"",B80/3.6,"") -> 1.60494 | E80: =IF(C80<>"",C80/3.6,"") -> 11.89749
A81: Kopalnie węgla Coal mines | B81: 2.972628 | C81: 16.998408 | D81: =IF(B81<>"",B81/3.6,"") -> 0.82573 | E81: =IF(C81<>"",C81/3.6,"") -> 4.72178
A82: Wydobycie ropy i gazu Oil & natural gas extraction plants | B82: 0.041868 | C82: 1.25604 | D82: =IF(B82<>"",B82/3.6,"") -> 0.01163 | E82: =IF(C82<>"",C82/3.6,"") -> 0.3489
A83: Brykietownie węgla kamiennego Patent fuel plants | C83: 0 | D83: =IF(B83<>"",B83/3.6,"") | E83: =IF(C83<>"",C83/3.6,"") -> 0
A84: Koksownie Coke ovens | B84: 0.795492 | C84: 2.386476 | D84: =IF(B84<>"",B84/3.6,"") -> 0.22097 | E84: =IF(C84<>"",C84/3.6,"") -> 0.66291
A85: Brykietownie węgla brunatnego i torfu BKB & PB plants | D85: =IF(B85<>"",B85/3.6,"") | E85: =IF(C85<>"",C85/3.6,"")
A86: Gazownie Gas works | B86: 0 | C86: 0.460548 | D86: =IF(B86<>"",B86/3.6,"") -> 0 | E86: =IF(C86<>"",C86/3.6,"") -> 0.12793
A87: Wielkie piece Blast furnaces | D87: =IF(B87<>"",B87/3.6,"") | E87: =IF(C87<>"",C87/3.6,"")
A88: Rafinerie ropy naftowej Petroleum refineries (oil refineries) | B88: 0.334944 | C88: 6.112728 | D88: =IF(B88<>"",B88/3.6,"") -> 0.09304 | E88: =IF(C88<>"",C88/3.6,"") -> 1.69798
A89: Przemysł jądrowy Nuclear industry | D89: =IF(B89<>"",B89/3.6,"") | E89: =IF(C89<>"",C89/3.6,"")
A90: Upłynnianie węgla Coal liquefaction plants | D90: =IF(B90<>"",B90/3.6,"") | E90: =IF(C90<>"",C90/3.6,"")
A91: Skraplanie (LNG) lub zgazowanie Liquefaction & regasification plants (LNG) | C91: 0.125604 | D91: =IF(B91<>"",B91/3.6,"") | E91: =IF(C91<>"",C91/3.6,"") -> 0.03489
A92: Zakłady zgazowania (biogaz) Gasification plants for biogas | D92: =IF(B92<>"",B92/3.6,"") | E92: =IF(C92<>"",C92/3.6,"")
A93: Instalacje przetwarzania gazu na paliwa ciekłe Gas-to-liquids (GTL) plants | D93: =IF(B93<>"",B93/3.6,"") | E93: =IF(C93<>"",C93/3.6,"")
A94: Zakłady produkcji węgla drzewnego Charcoal production plants | D94: =IF(B94<>"",B94/3.6,"") | E94: =IF(C94<>"",C94/3.6,"")
A95: Nigdzie indziej niewymienione Not elsewhere specified (energy) | B95: 15.365556 | C95: 17.291484 | D95: =IF(B95<>"",B95/3.6,"") -> 4.26821 | E95: =IF(C95<>"",C95/3.6,"") -> 4.80319
A96: Straty w dystrybucji Distribution losses | B96: 25.372008 | C96: 35.964612 | D96: =IF(B96<>"",B96/3.6,"") -> 7.04778 | E96: =IF(C96<>"",C96/3.6,"") -> 9.99017
A97: Zużycie finalne ogółem Available for final consumption | B97: 234.54454 | C97: 488.97637 | D97: =IF(B97<>"",B97/3.6,"") -> 65.15126 | E97: =IF(C97<>"",C97/3.6,"") -> 135.82677
A98: Zużycie nieenergetyczne Final non-energy consumption | D98: =IF(B98<>"",B98/3.6,"") | E98: =IF(C98<>"",C98/3.6,"")
A99: Zużycie nieenergetyczne w przemyśle/ energetyce/przemianach Non-energy use industry/transformation/energy | D99: =IF(B99<>"",B99/3.6,"") | E99: =IF(C99<>"",C99/3.6,"")
A100: W sektorze przemian Non-energy use in transformation sector | D100: =IF(B100<>"",B100/3.6,"") | E100: =IF(C100<>"",C100/3.6,"")
A101: W sektorze energetycznym Non-energy use in energy sector | D101: =IF(B101<>"",B101/3.6,"") | E101: =IF(C101<>"",C101/3.6,"")
A102: W sektorze przemysłu Non-energy use in industry sector | D102: =IF(B102<>"",B102/3.6,"") | E102: =IF(C102<>"",C102/3.6,"")
A103: Zużycie nieenergetyczne w sektorze transportowym Non-energy use in transport sector | D103: =IF(B103<>"",B103/3.6,"") | E103: =IF(C103<>"",C103/3.6,"")
A104: Zużycie nieenergetyczne w pozostałych sektorach Non-energy use in other sectors | D104: =IF(B104<>"",B104/3.6,"") | E104: =IF(C104<>"",C104/3.6,"")
A105: Zużycie końcowe energii Final energy consumption | B105: 234.54454 | C105: 488.97637 | D105: =IF(B105<>"",B105/3.6,"") -> 65.15126 | E105: =IF(C105<>"",C105/3.6,"") -> 135.82677
A106: Sektor przemysłowy Industry sector | B106: 35.79714 | C106: 195.52356 | D106: =IF(B106<>"",B106/3.6,"") -> 9.94365 | E106: =IF(C106<>"",C106/3.6,"") -> 54.3121
A107: Przemysł hutniczy Iron & steel | B107: 2.93076 | C107: 20.054772 | D107: =IF(B107<>"",B107/3.6,"") -> 0.8141 | E107: =IF(C107<>"",C107/3.6,"") -> 5.57077
A108: Przemysł chemiczny i petrochemiczny Chemical & petrochemical | B108: 14.611932 | C108: 33.033852 | D108: =IF(B108<>"",B108/3.6,"") -> 4.05887 | E108: =IF(C108<>"",C108/3.6,"") -> 9.17607
A109: Przemysł metali nieżelaznych Non-ferrous metals | B109: 0.921096 | C109: 8.206128 | D109: =IF(B109<>"",B109/3.6,"") -> 0.25586 | E109: =IF(C109<>"",C109/3.6,"") -> 2.27948
A110: Przemysł surowców niemetalicznych Non-metallic minerals | B110: 1.0467 | C110: 20.012904 | D110: =IF(B110<>"",B110/3.6,"") -> 0.29075 | E110: =IF(C110<>"",C110/3.6,"") -> 5.55914
...

Sheet OLD_AGR_Comm
B2: Definicja dóbr | Commodity Definition
B3: ~FI_Comm
B5: Csets | C5: Region | D5: CommName | E5: CommDesc | F5: Unit | G5: LimType | H5: CTSLvl | I5: PeakTS | J5: Ctype
B6: * Przynależność do zbioru dóbr | C6: Region | D6: Nazwa dobra | E6: Opis dobra | F6: Jednostka | G6: Znak w równaniu bilansu | H6: Poziom podokresów | I6: Monitorowanie szczytu | J6: Wskaźnik energii elektrycznej
B7: NRG | C7: PL | D7: AGR_HC | E7: Hard Coal | F7: PJ | H7: ANNUAL
B8: NRG | C8: PL | D8: AGR_BC | E8: Brown Coal | F8: PJ | H8: ANNUAL
B9: NRG | C9: PL | D9: AGR_OIL_GSL | E9: Gasoline | F9: PJ | H9: ANNUAL
B10: NRG | C10: PL | D10: AGR_OIL_DSL | E10: Diesel | F10: PJ | H10: ANNUAL
B11: NRG | C11: PL | D11: AGR_OIL_LPG | E11: LPG | F11: PJ | H11: ANNUAL
B12: NRG | C12: PL | D12: AGR_OIL_FUE | E12: Fuel Oil | F12: PJ | H12: ANNUAL
B13: NRG | C13: PL | D13: AGR_NAT_GAS | E13: Natural Gas | F13: PJ | H13: ANNUAL
B14: NRG | C14: PL | D14: AGR_BIOG | E14: Biogas AGR | F14: PJ | H14: ANNUAL
B15: \I: NRG | C15: PL | D15: AGR_BIO_CH4 | E15: Biometan AGR | F15: PJ | H15: ANNUAL
B16: NRG | C16: PL | D16: AGR_BIOM | E16: Biomass | F16: PJ | H16: ANNUAL
B17: NRG | C17: PL | D17: AGR_RDF | E17: RDF | F17: PJ | H17: ANNUAL
B18: NRG | C18: PL | D18: AGR_ELC | E18: Electricity | F18: PJ | H18: ANNUAL
... B21: DEM | C21: PL | D21: AGR_DEM | E21: Agriculture Demand | F21: IPI | H21: ANNUAL
B22: ENV | C22: PL | D22: AGR_CO2 | E22: Carbon Dioxide - Combustion (AGR) | F22: kt
B23: ENV | C23: PL | D23: AGR_SO2 | E23: Sulphur Dioxide - Combustion (AGR) | F23: kt
B24: ENV | C24: PL | D24: AGR_NOX | E24: Nitrogen Oxides - Combustion (AGR) | F24: kt
B25: ENV | C25: PL | D25: AGR_TSP | E25: Total Suspended Particulate - Combustion (AGR)
B26: ENV | C26: PL | D26: AGR_PM10 | E26: Particulate Matter <= 10 um - Combustion (AGR) | F26: kt
B27: ENV | C27: PL | D27: AGR_PM2.5 | E27: Particulate Matter <= 2.5 um - Combustion (AGR) | F27: kt
B28: ENV | C28: PL | D28: AGR_HG | E28: Mercury - Combustion (AGR) | F28: kt
B29: NRG | C29: PL | D29: ELC_GNC | E29: Generic Electricity - all voltages | F29: PJ | H29: DAYNITE | J29: ELC
B30: \I: | C30: PL | D30: ELC_AGR_CHPI | F30: PJ | H30: DAYNITE | J30: ELC
B31: NRG | C31: PL | D31: HT_AGR_CHPI | F31: PJ | H31: DAYNITE
B32: NRG | C32: PL | D32: AGR_HT_OWN_USE | F32: PJ | H32: ANNUAL
B33: \I: nowododane dobra dla biogazowni
B34: \I: NRG | C34: PL | D34: AGR_BIO_CH4 | E34: Agricultural Biomethane | F34: PJ
B35: ENV | C35: PL | D35: AGR_N2O | E35: Nitrous Oxide - Field (AGR) | F35: kt
B36: ENV | C36: PL | D36: AGR_CH4_ENT | E36: Methane - Livestock Enteric Digestion (AGR) | F36: kt
B37: ENV | C37: PL | D37: AGR_CH4_MAN | E37: Methane - Livestock Manure (AGR) | F37: kt
B38: ENV | C38: PL | D38: AGR_CH4_LAND | E38: Methane - LAND (AGR) | F38: kt
B39: NRG | C39: PL | D39: AGR_LIV_MANURE_CAT_DAIRY | E39: Animal Manure - Dairy Cattle | F39: kt
B40: NRG | C40: PL | D40: AGR_LIV_MANURE_CAT_NON-DAIRY | E40: Animal Manure - Non Dairy Cattle | F40: kt
B41: NRG | C41: PL | D41: AGR_LIV_MANURE_SHEEP | E41: Animal Manure - Sheep | F41: kt
B42: NRG | C42: PL | D42: AGR_LIV_MANURE_SWINE | E42: Animal Manure - Swine | F42: kt
B43: NRG | C43: PL | D43: AGR_LIV_MANURE_GOAT | E43: Animal Manure - Goat | F43: kt
B44: \I: | C44: PL | D44: AGR_LIV_MANURE_HORSE | E44: Animal Manure - Horse | F44: kt
B45: NRG | C45: PL | D45: AGR_LIV_MANURE_POULTRY | E45: Animal Manure - Poultry | F45: kt
... B62: NRG | C62: PL | D62: AGR_RESID_CROP_VEG | E62: Crop Residues | F62: kt
B63: MAT | C63: PL | D63: AGR_LIVESTOCK_FOOD | E63: Dummy Energy for Agriculture | F63: DUM | H63: ANNUAL
B64: MAT | C64: PL | D64: AGR_LAND | E64: Dummy Energy for Agriculture | F64: kha | H64: ANNUAL
B65: \I: | C65: PL | D65: AGR_DUMMY_NRG_CATTLE | E65: Dummy Energy for Agriculture | F65: DUM | H65: ANNUAL
B66: \I: | C66: PL | D66: AGR_DUMMY_NRG_LAND | E66: Dummy Energy for Agriculture | F66: DUM | H66: ANNUAL
B67: NRG | C67: PL | D67: AGR_DUMMY_DMD_LAND | E67: Dummy Land Demand for Agriculture | F67: DUM | H67: ANNUAL
B68: NRG | C68: PL | D68: AGR_DUMMY_LAND_RESIDUES | E68: Dummy Crop Residues for Biogas Production | F68: DUM | H68: ANNUAL
B69: DEM | C69: PL | D69: AGR_DEM_LIV_CAT_DAIRY | E69: AGR_DEM_LIV_CAT_DAIRY | F69: IPI | H69: ANNUAL
B70: DEM | C70: PL | D70: AGR_DEM_LIV_CAT_NON-DAIRY | E70: AGR_DEM_LIV_CAT_NON-DAIRY | F70: IPI | H70: ANNUAL
B71: DEM | C71: PL | D71: AGR_DEM_LIV_SHEEP | E71: AGR_DEM_LIV_SHEEP | F71: IPI | H71: ANNUAL
B72: DEM | C72: PL | D72: AGR_DEM_LIV_SWINE | E72: AGR_DEM_LIV_SWINE | F72: IPI | H72: ANNUAL
B73: DEM | C73: PL | D73: AGR_DEM_LIV_GOAT | E73: AGR_DEM_LIV_GOAT | F73: IPI | H73: ANNUAL
B74: \I: | C74: PL | D74: AGR_DEM_LIV_HORSE | E74: AGR_DEM_LIV_HORSE | F74: IPI | H74: ANNUAL
... B78: \I: | C78: PL | D78: AGR_DEM_LIV_INDIRECT | E78: AGR_DEM_LIV_INDIRECT | F78: IPI | H78: ANNUAL
B79: DEM | C79: PL | D79: AGR_DEM_CROP_WHEAT | E79: Crop Residues | F79: kt
B80: DEM | C80: PL | D80: AGR_DEM_CROP_BARLEY | E80: Crop Residues | F80: kt
B81: DEM | C81: PL | D81: AGR_DEM_CROP_MAIZE | E81: Crop Residues | F81: kt
B82: DEM | C82: PL | D82: AGR_DEM_CROP_CER-MIX | E82: Crop Residues | F82: kt
B83: DEM | C83: PL | D83: AGR_DEM_CROP_TRITICALE | E83: Crop Residues | F83: kt
B84: DEM | C84: PL | D84: AGR_DEM_CROP_OATS | E84: Crop Residues | F84: kt
B85: DEM | C85: PL | D85: AGR_DEM_CROP_RYE | E85: Crop Residues | F85: kt
B86: DEM | C86: PL | D86: AGR_DEM_CROP_MILL-BUCK | E86: Crop Residues | F86: kt
B87: DEM | C87: PL | D87: AGR_DEM_CROP_PULS-FEED | E87: Crop Residues | F87: kt
B88: DEM | C88: PL | D88: AGR_DEM_CROP_PULS-EDIB | E88: Crop Residues | F88: kt
B89: DEM | C89: PL | D89: AGR_DEM_CROP_POTATO | E89: Crop Residues | F89: kt
B90: DEM | C90: PL | D90: AGR_DEM_CROP_OIL | E90: Crop Residues | F90: kt
... B92: DEM | C92: PL | D92: AGR_DEM_CROP_VEG | E92: Crop Residues | F92: kt

Sheet OLD_AGR_LIV
B2: Hodowla zwierząt | Livestock
E4: XXX~FI_T:PL
B5: TechName | C5: * TechDesc | D5: Comm-IN | E5: Comm-OUT | F5: Comm-OUT-A | G5: Stock~2020 | H5: Stock~2050 | I5: Input | J5: OUTPUT | K5: Cap2Act
B6: * Technology name | C6: Technology description | D6: Commodity input | E6: Commodity output | G6: Thousands Animals | H6: Thousands Animals | I6: Fuel Input per 1000 Animals | J6: kt/1000 animals | K6: Animals per year
B7: AGR_EX_LIV_CAT_DAIRY | C7: AGR_LIV_CAT_DAIRY | D7: =AGR_Comm!$D$64 -> AGR_DUMMY_NRG_CATTLE | G7: 85.388 | H7: 85.388 | I7: 1 | K7: 1
E8: AGR_DEM_LIV_CAT_DAIRY
E9: AGR_LIV_MANURE_CAT_DAIRY | J9: 1.752
F10: AGR_CH4_ENT | J10: 0.12053186
F11: AGR_CH4_MAN | J11: 0.0078432905
F12: AGR_N2O | J12: 0.00080732056
B13: AGR_EX_LIV_CAT_NON-DAIRY | C13: AGR_LIV_CAT_NON-DAIRY | D13: =AGR_Comm!$D$64 -> AGR_DUMMY_NRG_CATTLE | G13: 93.213 | H13: 93.213 | I13: 1 | K13: 1
E14: AGR_DEM_LIV_CAT_NON-DAIRY
E15: AGR_LIV_MANURE_CAT_NON-DAIRY | J15: 0.657
F16: AGR_CH4_ENT | J16: 0.049685741
F17: AGR_CH4_MAN | J17: 0.0017337189
F18: AGR_N2O | J18: 0.00035346249
B19: AGR_EX_LIV_SHEEP | C19: AGR_LIV_SHEEP | D19: =AGR_Comm!$D$64 -> AGR_DUMMY_NRG_CATTLE | G19: 79.092 | H19: 79.092 | I19: 1 | K19: 1
E20: AGR_DEM_LIV_SHEEP
E21: AGR_LIV_MANURE_SHEEP | J21: 0.03066
F22: AGR_CH4_ENT | J22: 0.008
F23: AGR_CH4_MAN | J23: 0.00019
F24: AGR_N2O | J24: 4.4422318e-05
B25: AGR_EX_LIV_SWINE | C25: AGR_LIV_SWINE | D25: =AGR_Comm!$D$64 -> AGR_DUMMY_NRG_CATTLE | G25: 141.443 | H25: 141.443 | I25: 1 | K25: 1
E26: AGR_DEM_LIV_SWINE
E27: AGR_LIV_MANURE_SWINE | J27: 0.023186625
F28: AGR_CH4_ENT | J28: 0.0015
F29: AGR_CH4_MAN | J29: 0.0013777229
F30: AGR_N2O | J30: 8.5741217e-05
B31: AGR_EX_LIV_GOAT | C31: AGR_LIV_GOAT | D31: =AGR_Comm!$D$64 -> AGR_DUMMY_NRG_CATTLE | G31: 4.9765253 | H31: 4.9765253 | I31: 1 | K31: 1
E32: AGR_DEM_LIV_GOAT
E33: AGR_LIV_MANURE_GOAT | J33: 0.03066
F34: AGR_CH4_ENT | J34: 0.005
F35: AGR_CH4_MAN | J35: 0.00013
F36: AGR_N2O | J36: 3.4996311e-05
B37: AGR_EX_LIV_HORSE | C37: AGR_LIV_HORSE | D37: =AGR_Comm!$D$64 -> AGR_DUMMY_NRG_CATTLE | G37: 20.306 | H37: 20.306 | I37: 1 | K37: 1
E38: AGR_DEM_LIV_HORSE
E39: AGR_LIV_MANURE_HORSE | J39: 1.752
F40: AGR_CH4_ENT | J40: 0.018
F41: AGR_CH4_MAN | J41: 0.00156
F42: AGR_N2O | J42: 0.00033491071
B43: AGR_EX_LIV_POULTRY | C43: AGR_LIV_POULTRY | D43: =AGR_Comm!$D$64 -> AGR_DUMMY_NRG_CATTLE | G43: 5170.067 | H43: 5170.067 | I43: 1 | K43: 1
E44: AGR_DEM_LIV_POULTRY
E45: AGR_LIV_MANURE_POULTRY | J45: 0.005694
F46: AGR_CH4_MAN | J46: 2.7762588e-05
F47: AGR_N2O | J47: 1.1960522e-06
B48: AGR_EX_LIV_RABBIT | C48: AGR_LIV_RABBIT | D48: =AGR_Comm!$D$64 -> AGR_DUMMY_NRG_CATTLE | G48: 17.32 | H48: 17.32 | I48: 1 | K48: 1
E49: AGR_DEM_LIV_RABBIT
E50: AGR_LIV_MANURE_RABBIT | J50: 0.005694
F51: AGR_CH4_MAN | J51: 8e-05
F52: AGR_N2O | J52: 2.5457143e-05
B53: AGR_EX_LIV_FUR | C53: AGR_LIV_FUR | D53: =AGR_Comm!$D$64 -> AGR_DUMMY_NRG_CATTLE | G53: 16.899 | H53: 16.899 | I53: 1 | K53: 1
E54: AGR_DEM_LIV_FUR
E55: AGR_LIV_MANURE_FUR | J55: 0.005694
F56: AGR_CH4_MAN | J56: 0.00068
F57: AGR_N2O | J57: 2.0002179e-05
B58: AGR_EX_LIV_INDIRECT | C58: AGR_EX_LIV_INDIRECT | D58: =AGR_Comm!$D$64 -> AGR_DUMMY_NRG_CATTLE | G58: 5628.7045 | H58: 5628.7045 | I58: 1 | K58: 1
E59: AGR_DEM_LIV_INDIRECT
F60: AGR_N2O | J60: 2.553881e-05
D65: XXX~FI_T: PL
B66: TechName | C66: *TechDesc | D66: Comm-OUT | E66: Cost
B67: * Technology name | C67: Technology description | D67: Commodity output | E67: 100 IPI / thousand vehicle
B68: =AGR_Proc!D28 -> AGR_IMP_DUMMY_NRG_LIV | C68: =AGR_Proc!E28 -> Dummy Energy Import | D68: =AGR_Comm!$D$64 -> AGR_DUMMY_NRG_CATTLE | E68: 0.001
B69: =AGR_Proc!D29 -> AGR_IMP_LAND_RESIDUE | C69: =AGR_Proc!E29 -> Dummy Import of Crop Residues for Biogas Production | D69: =AGR_Comm!D67 -> AGR_DUMMY_LAND_RESIDUES | E69: 0.001

Sheet OLD_AGR_LAND
B2: Uprawa roślin | Land use in agrigulture
F4: OLD~FI_T:PL
B5: TechName | C5: *TechDesc | D5: Comm-IN | E5: Comm-OUT | F5: Comm-OUT-A | G5: Stock~2020~2050 | H5: Output~2020~AGR_N2O | I5: Output~2050~AGR_N2O | J5: Cap2Act | K5: AFA~FX | L5: Input
B6: * Technology name | C6: Technology description | E6: Commodity output | G6: k ha | H6: kt/k ha
B7: =AGR_Proc!D43 -> AGR_FERT_N_INORG | C7: =AGR_Proc!E43 -> AGR_FERT_N_INORG | D7: =AGR_Comm!$D$65 -> AGR_DUMMY_NRG_LAND | E7: =AGR_Comm!$D$66 -> AGR_DUMMY_DMD_LAND | F7: =AGR_Comm!$D$34 -> AGR_N2O | G7: 100 | H7: 0.0033536446 | I7: 0.0033536446 | J7: 1 | K7: 1 | L7: 1
B8: =AGR_Proc!D44 -> AGR_FERT_N_MANURE | C8: =AGR_Proc!E44 -> AGR_FERT_N_MANURE | D8: =AGR_Comm!$D$65 -> AGR_DUMMY_NRG_LAND | E8: =AGR_Comm!$D$66 -> AGR_DUMMY_DMD_LAND | F8: =AGR_Comm!$D$34 -> AGR_N2O | G8: 100 | H8: 0.0013636722 | I8: 0.0013636722 | J8: 1 | K8: 1 | L8: 1
B9: =AGR_Proc!D45 -> AGR_FERT_N_SLUDGE | C9: =AGR_Proc!E45 -> AGR_FERT_N_SLUDGE | D9: =AGR_Comm!$D$65 -> AGR_DUMMY_NRG_LAND | E9: =AGR_Comm!$D$66 -> AGR_DUMMY_DMD_LAND | F9: =AGR_Comm!$D$34 -> AGR_N2O | G9: 100 | H9: 1.6167877e-05 | I9: 1.6167877e-05 | J9: 1 | K9: 1 | L9: 1
B10: =AGR_Proc!D46 -> AGR_FERT_N_URINE | C10: =AGR_Proc!E46 -> AGR_FERT_N_URINE | D10: =AGR_Comm!$D$65 -> AGR_DUMMY_NRG_LAND | E10: =AGR_Comm!$D$66 -> AGR_DUMMY_DMD_LAND | F10: =AGR_Comm!$D$34 -> AGR_N2O | G10: 100 | H10: 0.00035521266 | I10: 0.00035521266 | J10: 1 | K10: 1 | L10: 1
B11: =AGR_Proc!D47 -> AGR_FERT_N_CROP-RES | C11: =AGR_Proc!E47 -> AGR_FERT_N_CROP-RES | D11: =AGR_Comm!$D$65 -> AGR_DUMMY_NRG_LAND | E11: =AGR_Comm!$D$66 -> AGR_DUMMY_DMD_LAND | F11: =AGR_Comm!$D$34 -> AGR_N2O | G11: 100 | H11: 0.0013317293 | I11: 0.0013317293 | J11: 1 | K11: 1 | L11: 1
B12: =AGR_Proc!D48 -> AGR_FERT_N_MIN | C12: =AGR_Proc!E48 -> AGR_FERT_N_MIN | D12: =AGR_Comm!$D$65 -> AGR_DUMMY_NRG_LAND | E12: =AGR_Comm!$D$66 -> AGR_DUMMY_DMD_LAND | F12: =AGR_Comm!$D$34 -> AGR_N2O | G12: 100 | H12: 3.3444093e-05 | I12: 3.3444093e-05 | J12: 1 | K12: 1 | L12: 1
B13: =AGR_Proc!D49 -> AGR_FERT_N_CULT | C13: =AGR_Proc!E49 -> AGR_FERT_N_CULT | D13: =AGR_Comm!$D$65 -> AGR_DUMMY_NRG_LAND | E13: =AGR_Comm!$D$66 -> AGR_DUMMY_DMD_LAND | F13: =AGR_Comm!$D$34 -> AGR_N2O | G13: 100 | H13: 0.0023921301 | I13: 0.0023921301 | J13: 1 | K13: 1 | L13: 1
B14: =AGR_Proc!D50 -> AGR_FERT_N_ATM-DEP | C14: =AGR_Proc!E50 -> AGR_FERT_N_ATM-DEP | D14: =AGR_Comm!$D$65 -> AGR_DUMMY_NRG_LAND | E14: =AGR_Comm!$D$66 -> AGR_DUMMY_DMD_LAND | F14: =AGR_Comm!$D$34 -> AGR_N2O | G14: 100 | H14: 0.00064745988 | I14: 0.00064745988 | J14: 1 | K14: 1 | L14: 1
B15: =AGR_Proc!D51 -> AGR_FERT_N_NITR-LEACH | C15: =AGR_Proc!E51 -> AGR_FERT_N_NITR-LEACH | D15: =AGR_Comm!$D$65 -> AGR_DUMMY_NRG_LAND | E15: =AGR_Comm!$D$66 -> AGR_DUMMY_DMD_LAND | F15: =AGR_Comm!$D$34 -> AGR_N2O | G15: 100 | H15: 0.0014128414 | I15: 0.0014128414 | J15: 1 | K15: 1 | L15: 1
F17: OLD~FI_T:PL
B18: TechName | C18: *TechDesc | D18: Comm-IN | E18: Comm-OUT | F18: Comm-OUT-A | G18: Stock~2020~2050 | H18: Output~2020~AGR_CO2 | I18: Output~2050~AGR_CO2 | J18: Cap2Act | K18: AFA~FX | L18: Input
B19: * Technology name | C19: Technology description | E19: Commodity output | G19: k ha | H19: kt/k ha
B20: =AGR_Proc!D52 -> AGR_LAND_FERT_CO2_LIM | C20: =AGR_Proc!E52 -> AGR_LAND_FERT_CO2_LIM | D20: =AGR_Comm!$D$65 -> AGR_DUMMY_NRG_LAND | E20: =AGR_Comm!$D$66 -> AGR_DUMMY_DMD_LAND | F20: =AGR_Comm!$D$23 -> AGR_CO2 | G20: 100 | H20: 0.13152132 | I20: 0.13152132 | J20: 1 | K20: 1 | L20: 1
B21: =AGR_Proc!D53 -> AGR_LAND_FERT_CO2_DOL | C21: =AGR_Proc!E53 -> AGR_LAND_FERT_CO2_DOL | D21: =AGR_Comm!$D$65 -> AGR_DUMMY_NRG_LAND | E21: =AGR_Comm!$D$66 -> AGR_DUMMY_DMD_LAND | F21: =AGR_Comm!$D$23 -> AGR_CO2 | G21: 100 | H21: 0.048130325 | I21: 0.048130325 | J21: 1 | K21: 1 | L21: 1
B22: =AGR_Proc!D54 -> AGR_LAND_FERT_CO2_UREA | C22: =AGR_Proc!E54 -> AGR_LAND_FERT_CO2_UREA | D22: =AGR_Comm!$D$65 -> AGR_DUMMY_NRG_LAND | E22: =AGR_Comm!$D$66 -> AGR_DUMMY_DMD_LAND | F22: =AGR_Comm!$D$23 -> AGR_CO2 | G22: 100 | H22: 0.089067159 | I22: 0.089067159 | J22: 1 | K22: 1 | L22: 1
B23: =AGR_Proc!D55 -> AGR_LAND_FERT_CO2_OTH | C23: =AGR_Proc!E55 -> AGR_LAND_FERT_CO2_OTH | D23: =AGR_Comm!$D$65 -> AGR_DUMMY_NRG_LAND | E23: =AGR_Comm!$D$66 -> AGR_DUMMY_DMD_LAND | F23: =AGR_Comm!$D$23 -> AGR_CO2 | G23: 100 | H23: 0.053429613 | I23: 0.053429613 | J23: 1 | K23: 1 | L23: 1
F26: OLD~FI_T:PL
B27: TechName | C27: *TechDesc | D27: Comm-IN | E27: Comm-OUT | F27: Comm-OUT-A | G27: Stock~2020~2050 | H27: Output~2020~AGR_CH4_LAND | I27: Output~2050~AGR_CH4_LAND | J27: Output~2020~AGR_N2O | K27: Output~2050~AGR_N2O | L27: Cap2Act | M27: AFA~FX | N27: Input
B28: * Technology name | C28: Technology description | E28: Commodity output | G28: k ha | H28: kt/k ha | J28: kt/k ha
B29: =AGR_Proc!D56 -> AGR_LAND_CROP_WHEAT | C29: =AGR_Proc!E56 -> AGR_LAND_CROP_WHEAT | D29: =AGR_Comm!$D$65 -> AGR_DUMMY_NRG_LAND | E29: =AGR_Comm!$D$66 -> AGR_DUMMY_DMD_LAND | F29: =AGR_Comm!$D$37&", "&AGR_Comm!$D$34 -> AGR_CH4_LAND, AGR_N2O | G29: 100 | H29: 5.2190655e-05 | I29: 5.2190655e-05 | J29: 1.2056041e-06 | K29: 1.2056041e-06 | L29: 1 | M29: 1 | N29: 1
E30: =AGR_Comm!D47 -> AGR_RESID_CROP_WHEAT
B31: =AGR_Proc!D57 -> AGR_LAND_CROP_BARLEY | C31: =AGR_Proc!E57 -> AGR_LAND_CROP_BARLEY | D31: =AGR_Comm!$D$65 -> AGR_DUMMY_NRG_LAND | E31: =AGR_Comm!$D$66 -> AGR_DUMMY_DMD_LAND | F31: =AGR_Comm!$D$37&", "&AGR_Comm!$D$34 -> AGR_CH4_LAND, AGR_N2O | G31: 100 | H31: 1.0543212e-05 | I31: 1.0543212e-05 | J31: 2.609445e-07 | K31: 2.609445e-07 | L31: 1 | M31: 1 | N31: 1
E32: =AGR_Comm!D48 -> AGR_RESID_CROP_BARLEY
B33: =AGR_Proc!D58 -> AGR_LAND_CROP_MAIZE | C33: =AGR_Proc!E58 -> AGR_LAND_CROP_MAIZE | D33: =AGR_Comm!$D$65 -> AGR_DUMMY_NRG_LAND | E33: =AGR_Comm!$D$66 -> AGR_DUMMY_DMD_LAND | F33: =AGR_Comm!$D$37&", "&AGR_Comm!$D$34 -> AGR_CH4_LAND, AGR_N2O | G33: 100 | H33: 9.713178e-06 | I33: 9.713178e-06 | J33: 3.2053487e-07 | K33: 3.2053487e-07 | L33: 1 | M33: 1 | N33: 1
E34: =AGR_Comm!D49 -> AGR_RESID_CROP_MAIZE
B35: =AGR_Proc!D59 -> AGR_LAND_CROP_CER-MIX | C35: =AGR_Proc!E59 -> AGR_LAND_CROP_CER-MIX | D35: =AGR_Comm!$D$65 -> AGR_DUMMY_NRG_LAND | E35: =AGR_Comm!$D$66 -> AGR_DUMMY_DMD_LAND | F35: =AGR_Comm!$D$37&", "&AGR_Comm!$D$34 -> AGR_CH4_LAND, AGR_N2O | G35: 100 | H35: 6.8122244e-06 | I35: 6.8122244e-06 | J35: 1.6860255e-07 | K35: 1.6860255e-07 | L35: 1 | M35: 1 | N35: 1
E36: =AGR_Comm!D50 -> AGR_RESID_CROP_CER-MIX
B37: =AGR_Proc!D60 -> AGR_LAND_CROP_TRITICALE | C37: =AGR_Proc!E60 -> AGR_LAND_CROP_TRITICALE | D37: =AGR_Comm!$D$65 -> AGR_DUMMY_NRG_LAND | E37: =AGR_Comm!$D$66 -> AGR_DUMMY_DMD_LAND | F37: =AGR_Comm!$D$37&", "&AGR_Comm!$D$34 -> AGR_CH4_LAND, AGR_N2O | G37: 100 | H37: 3.1805444e-05 | I37: 3.1805444e-05 | J37: 6.8222678e-07 | K37: 6.8222678e-07 | L37: 1 | M37: 1 | N37: 1
E38: =AGR_Comm!D51 -> AGR_RESID_CROP_TRITICALE
B39: =AGR_Proc!D61 -> AGR_LAND_CROP_OATS | C39: =AGR_Proc!E61 -> AGR_LAND_CROP_OATS | D39: =AGR_Comm!$D$65 -> AGR_DUMMY_NRG_LAND | E39: =AGR_Comm!$D$66 -> AGR_DUMMY_DMD_LAND | F39: =AGR_Comm!$D$37&", "&AGR_Comm!$D$34 -> AGR_CH4_LAND, AGR_N2O | G39: 100 | H39: 6.5948073e-06 | I39: 6.5948073e-06 | J39: 1.7410291e-07 | K39: 1.7410291e-07 | L39: 1 | M39: 1 | N39: 1
E40: =AGR_Comm!D52 -> AGR_RESID_CROP_OATS
B41: =AGR_Proc!D62 -> AGR_LAND_CROP_RYE | C41: =AGR_Proc!E62 -> AGR_LAND_CROP_RYE | D41: =AGR_Comm!$D$65 -> AGR_DUMMY_NRG_LAND | E41: =AGR_Comm!$D$66 -> AGR_DUMMY_DMD_LAND | F41: =AGR_Comm!$D$37&", "&AGR_Comm!$D$34 -> AGR_CH4_LAND, AGR_N2O | G41: 100 | H41: 1.9127809e-05 | I41: 1.9127809e-05 | J41: 3.4716973e-07 | K41: 3.4716973e-07 | L41: 1 | M41: 1 | N41: 1
E42: =AGR_Comm!D53 -> AGR_RESID_CROP_RYE
B43: =AGR_Proc!D63 -> AGR_LAND_CROP_MILL-BUCK | C43: =AGR_Proc!E63 -> AGR_LAND_CROP_MILL-BUCK | D43: =AGR_Comm!$D$65 -> AGR_DUMMY_NRG_LAND | E43: =AGR_Comm!$D$66 -> AGR_DUMMY_DMD_LAND | F43: =AGR_Comm!$D$37&", "&AGR_Comm!$D$34 -> AGR_CH4_LAND, AGR_N2O | G43: 100 | H43: 3.4600164e-07 | I43: 3.4600164e-07 | J43: 1.1418054e-08 | K43: 1.1418054e-08 | L43: 1 | M43: 1 | N43: 1
E44: =AGR_Comm!D54 -> AGR_RESID_CROP_MILL-BUCK
B45: =AGR_Proc!D64 -> AGR_LAND_CROP_PULS-FEED | C45: =AGR_Proc!E64 -> AGR_LAND_CROP_PULS-FEED | D45: =AGR_Comm!$D$65 -> AGR_DUMMY_NRG_LAND | E45: =AGR_Comm!$D$66 -> AGR_DUMMY_DMD_LAND | F45: =AGR_Comm!$D$37&", "&AGR_Comm!$D$34 -> AGR_CH4_LAND, AGR_N2O | G45: 100 | H45: 5.434404e-07 | I45: 5.434404e-07 | J45: 4.035045e-08 | K45: 4.035045e-08 | L45: 1 | M45: 1 | N45: 1
E46: =AGR_Comm!D55 -> AGR_RESID_CROP_PULS-FEED
B47: =AGR_Proc!D65 -> AGR_LAND_CROP_PULS-EDIB | C47: =AGR_Proc!E65 -> AGR_LAND_CROP_PULS-EDIB | D47: =AGR_Comm!$D$65 -> AGR_DUMMY_NRG_LAND | E47: =AGR_Comm!$D$66 -> AGR_DUMMY_DMD_LAND | F47: =AGR_Comm!$D$37&", "&AGR_Comm!$D$34 -> AGR_CH4_LAND, AGR_N2O | G47: 100 | H47: 1.4840557e-07 | I47: 1.4840557e-07 | J47: 9.7947679e-09 | K47: 9.7947679e-09 | L47: 1 | M47: 1 | N47: 1
E48: =AGR_Comm!D56 -> AGR_RESID_CROP_PULS-EDIB
B49: =AGR_Proc!D66 -> AGR_LAND_CROP_POTATO | C49: =AGR_Proc!E66 -> AGR_LAND_CROP_POTATO | D49: =AGR_Comm!$D$65 -> AGR_DUMMY_NRG_LAND | E49: =AGR_Comm!$D$66 -> AGR_DUMMY_DMD_LAND | F49: =AGR_Comm!$D$37&", "&AGR_Comm!$D$34 -> AGR_CH4_LAND, AGR_N2O | G49: 100 | H49: 1.787069e-05 | I49: 1.787069e-05 | J49: 1.4153586e-06 | K49: 1.4153586e-06 | L49: 1 | M49: 1 | N49: 1
E50: =AGR_Comm!D57 -> AGR_RESID_CROP_POTATO
B51: =AGR_Proc!D67 -> AGR_LAND_CROP_STR-HAY | C51: =AGR_Proc!E67 -> AGR_LAND_CROP_STR-HAY | D51: =AGR_Comm!$D$65 -> AGR_DUMMY_NRG_LAND | E51: =AGR_Comm!$D$66 -> AGR_DUMMY_DMD_LAND | F51: =AGR_Comm!$D$37&", "&AGR_Comm!$D$34 -> AGR_CH4_LAND, AGR_N2O | G51: 100 | H51: 8.8885821e-07 | I51: 8.8885821e-07 | J51: 6.5586974e-08 | K51: 6.5586974e-08 | L51: 1 | M51: 1 | N51: 1
E52: =AGR_Comm!D58 -> AGR_RESID_CROP_STR-HAY
B53: =AGR_Proc!D68 -> AGR_LAND_CROP_OIL | C53: =AGR_Proc!E68 -> AGR_LAND_CROP_OIL | D53: =AGR_Comm!$D$65 -> AGR_DUMMY_NRG_LAND | E53: =AGR_Comm!$D$66 -> AGR_DUMMY_DMD_LAND | F53: =AGR_Comm!$D$37&", "&AGR_Comm!$D$34 -> AGR_CH4_LAND, AGR_N2O | G53: 100 | H53: 0.00010698253 | I53: 0.00010698253 | J53: 2.6478175e-06 | K53: 2.6478175e-06 | L53: 1 | M53: 1 | N53: 1
E54: =AGR_Comm!D59 -> AGR_RESID_CROP_OIL
B55: =AGR_Proc!D69 -> AGR_LAND_CROP_FRUIT | C55: =AGR_Proc!E69 -> AGR_LAND_CROP_FRUIT | D55: =AGR_Comm!$D$65 -> AGR_DUMMY_NRG_LAND | E55: =AGR_Comm!$D$66 -> AGR_DUMMY_DMD_LAND | F55: =AGR_Comm!$D$37&", "&AGR_Comm!$D$34 -> AGR_CH4_LAND, AGR_N2O | G55: 100 | H55: 0.00014581099 | I55: 0.00014581099 | J55: 7.9394082e-06 | K55: 7.9394082e-06 | L55: 1 | M55: 1 | N55: 1
E56: =AGR_Comm!D60 -> AGR_RESID_CROP_FRUIT
B57: =AGR_Proc!D70 -> AGR_LAND_CROP_VEG | C57: =AGR_Proc!E70 -> AGR_LAND_CROP_VEG | D57: =AGR_Comm!$D$65 -> AGR_DUMMY_NRG_LAND | E57: =AGR_Comm!$D$66 -> AGR_DUMMY_DMD_LAND | F57: =AGR_Comm!$D$37&", "&AGR_Comm!$D$34 -> AGR_CH4_LAND, AGR_N2O | G57: 100 | H57: 3.2776807e-06 | I57: 3.2776807e-06 | J57: 3.0262276e-07 | K57: 3.0262276e-07 | L57: 1 | M57: 1 | N57: 1
E58: =AGR_Comm!D61 -> AGR_RESID_CROP_VEG
D61: OLD~FI_T:PL
B62: TechName | C62: *TechDesc | D62: Comm-OUT | E62: Cost
B63: * Technology name | C63: Technology description | D63: Commodity output | E63: 100 IPI / thousand vehicle
B64: =AGR_Proc!D30 -> AGR_IMP_DUMMY_NRG_LAND | C64: =AGR_Proc!E30 -> Dummy Land Import | D64: =AGR_Comm!$D$65 -> AGR_DUMMY_NRG_LAND | E64: 0.001

Sheet Arkusz1
B1: Paliwo/nośnik | C1: 2024 | D1: 2025 | E1: 2030 | F1: 2035 | G1: 2040 | H1: 2045 | I1: 2050
B3: Węgiel kamienny en. | C3: 13000 | D3: 12500 | E3: 10000 | F3: 7500 | G3: 5000 | H3: 2500 | I3: 0
B4: Węgiel brunatny | C4: 160 | D4: 153.84615 | E4: 123.07692 | F4: 92.307692 | G4: 61.538461 | H4: 30.76923 | I4: 0 | M4: AGR_HC | N4: Hard Coal
B5: Gaz ziemny razem | C5: 1847.8184 | D5: 1815.21 | E5: 1652.168 | F5: 1489.126 | G5: 1326.084 | H5: 1163.042 | I5: 1000 | M5: AGR_BC | N5: Brown Coal
B6: Torf i drewno | C6: 16349.378 | D6: 16105.171 | E6: 14884.137 | F6: 13663.103 | G6: 12442.069 | H6: 11221.034 | I6: 10000 | M6: AGR_OIL_GSL | N6: Gasoline
B7: Biogaz | C7: 556.87786 | D7: 823.92102 | E7: 2159.1368 | F7: 3494.3526 | G7: 4829.5684 | H7: 6164.7842 | I7: 7500 | M7: AGR_OIL_DSL | N7: Diesel
B8: Paliwa odpadowe i ciekłe bio. | C8: 41.77884 | D8: 136.32581 | E8: 609.06065 | F8: 1081.7955 | G8: 1554.5303 | H8: 2027.2652 | I8: 2500 | M8: AGR_OIL_LPG | N8: LPG
B9: Brykiety, koks i półkoks | C9: 47.0832 | D9: 45.272308 | E9: 36.217846 | F9: 27.163384 | G9: 18.108922 | H9: 9.05446 | I9: 0 | M9: AGR_OIL_FUE | N9: Fuel Oil
B10: Gaz ciekły | C10: 1840 | D10: 1788.4615 | E10: 1530.7692 | F10: 1273.0769 | G10: 1015.3846 | H10: 757.69231 | I10: 500 | M10: AGR_NAT_GAS | N10: Natural Gas
B11: Benzyny silnikowe i lotnicze | C11: 103.13769 | D11: 103.01701 | E11: 102.41361 | F11: 101.81021 | G11: 101.20681 | H11: 100.6034 | I11: 100 | M11: PRI_BIOG_AGR | N11: Biogas AGR
B12: Oleje napędowe | C12: 85469.984 | D12: 83759.6 | E12: 75207.68 | F12: 66655.76 | G12: 58103.84 | H12: 49551.92 | I12: 41000 | M12: PRI_BIO_CH4_AGR | N12: Biometan AGR
B13: Oleje opałowe | C13: 3094.6173 | D13: 2975.5936 | E13: 2380.4749 | F13: 1785.3562 | G13: 1190.2374 | H13: 595.11872 | I13: 0 | M13: AGR_BIOG | N13: Biogas AGR
B14: Energia elektryczna | C14: 6300 | D14: 7057.6923 | E14: 10846.154 | F14: 14634.615 | G14: 18423.077 | H14: 22211.538 | I14: 26000 | M14: AGR_BIOM | N14: Biomass
B15: Ciepło | C15: 620 | D15: 711.53846 | E15: 1169.2308 | F15: 1626.9231 | G15: 2084.6154 | H15: 2542.3077 | I15: 3000 | M15: AGR_RDF | N15: RDF
B16: Suma | C16: 129430.68 | D16: 127975.65 | E16: 120700.52 | F16: 113425.39 | G16: 106150.26 | H16: 98875.13 | I16: 91600 | M16: AGR_ELC | N16: Electricity
M17: AGR_DH | N17: District Heat
C18: 2024 | D18: 2025 | E18: 2030 | F18: 2035 | G18: 2040 | H18: 2045 | I18: 2050 | M18: AGR_OTH_FUE | N18: Other Fuels
B19: Węgiel kamienny | C19: =C3 -> 13000 | D19: =D3 -> 12500 | E19: =E3 -> 10000 | F19: =F3 -> 7500 | G19: =G3 -> 5000 | H19: =H3 -> 2500 | I19: =I3 -> 0 | M19: AGR_DEM | N19: Agriculture Demand
B20: Węgiel brunatny | C20: =C4 -> 160 | D20: =D4 -> 153.84615 | E20: =E4 -> 123.07692 | F20: =F4 -> 92.307692 | G20: =G4 -> 61.538461 | H20: =H4 -> 30.76923 | I20: =I4 -> 0 | M20: AGR_CO2 | N20: Carbon Dioxide - Combustion (AGR)
B21: Gaz ziemny | C21: =C5 -> 1847.8184 | D21: =D5 -> 1815.21 | E21: =E5 -> 1652.168 | F21: =F5 -> 1489.126 | G21: =G5 -> 1326.084 | H21: =H5 -> 1163.042 | I21: =I5 -> 1000 | M21: AGR_SO2 | N21: Sulphur Dioxide - Combustion (AGR)
B22: Biomasa | C22: =C6+C9 -> 16396.461 | D22: =D6+D9 -> 16150.444 | E22: =E6+E9 -> 14920.355 | F22: =F6+F9 -> 13690.266 | G22: =G6+G9 -> 12460.177 | H22: =H6+H9 -> 11230.089 | I22: =I6+I9 -> 10000 | M22: AGR_NOX | N22: Nitrogen Oxides - Combustion (AGR)
B23: Biogaz | C23: =C7 -> 556.87786 | D23: =D7 -> 823.92102 | E23: =E7 -> 2159.1368 | F23: =F7 -> 3494.3526 | G23: =G7 -> 4829.5684 | H23: =H7 -> 6164.7842 | I23: =I7 -> 7500 | M23: AGR_TSP | N23: Total Suspended Particulate - Combustion (AGR)
B24: RDF | C24: =C8 -> 41.77884 | D24: =D8 -> 136.32581 | E24: =E8 -> 609.06065 | F24: =F8 -> 1081.7955 | G24: =G8 -> 1554.5303 | H24: =H8 -> 2027.2652 | I24: =I8 -> 2500 | M24: AGR_PM10 | N24: Particulate Matter <= 10 um - Combustion (AGR)
B25: LPG | C25: =C10 -> 1840 | D25: =D10 -> 1788.4615 | E25: =E10 -> 1530.7692 | F25: =F10 -> 1273.0769 | G25: =G10 -> 1015.3846 | H25: =H10 -> 757.69231 | I25: =I10 -> 500 | M25: AGR_PM2.5 | N25: Particulate Matter <= 2.5 um - Combustion (AGR)
B26: Benzyna | C26: =C11 -> 103.13769 | D26: =D11 -> 103.01701 | E26: =E11 -> 102.41361 | F26: =F11 -> 101.81021 | G26: =G11 -> 101.20681 | H26: =H11 -> 100.6034 | I26: =I11 -> 100 | M26: AGR_HG | N26: Mercury - Combustion (AGR)
B27: Oleje napędowe | C27: =C12 -> 85469.984 | D27: =D12 -> 83759.6 | E27: =E12 -> 75207.68 | F27: =F12 -> 66655.76 | G27: =G12 -> 58103.84 | H27: =H12 -> 49551.92 | I27: =I12 -> 41000
B28: Oleje opałowe | C28: =C13 -> 3094.6173 | D28: =D13 -> 2975.5936 | E28: =E13 -> 2380.4749 | F28: =F13 -> 1785.3562 | G28: =G13 -> 1190.2374 | H28: =H13 -> 595.11872 | I28: =I13 -> 0
B29: Energia elektryczna | C29: =C14 -> 6300 | D29: =D14 -> 7057.6923 | E29: =E14 -> 10846.154 | F29: =F14 -> 14634.615 | G29: =G14 -> 18423.077 | H29: =H14 -> 22211.538 | I29: =I14 -> 26000
B30: Ciepło sieciowe | C30: =C15 -> 620 | D30: =D15 -> 711.53846 | E30: =E15 -> 1169.2308 | F30: =F15 -> 1626.9231 | G30: =G15 -> 2084.6154 | H30: =H15 -> 2542.3077 | I30: =I15 -> 3000
B31: Suma | C31: =SUM(C19:C30) -> 129430.68 | D31: =SUM(D19:D30) -> 127975.65 | E31: =SUM(E19:E30) -> 120700.52 | F31: =SUM(F19:F30) -> 113425.39 | G31: =SUM(G19:G30) -> 106150.26 | H31: =SUM(H19:H30) -> 98875.13 | I31: =SUM(I19:I30) -> 91600
B34: Rolnictwo - zapotrzebowanie na energię finalną [PJ]
C35: 2024 | D35: 2025 | E35: 2030 | F35: 2035 | G35: 2040 | H35: 2045 | I35: 2050
B36: Węgiel kamienny | C36: =C19/1000 -> 13 | D36: =D19/1000 -> 12.5 | E36: =E19/1000 -> 10 | F36: =F19/1000 -> 7.5 | G36: =G19/1000 -> 5 | H36: =H19/1000 -> 2.5 | I36: =I19/1000 -> 0
B37: Węgiel brunatny | C37: =C20/1000 -> 0.16 | D37: =D20/1000 -> 0.15384615 | E37: =E20/1000 -> 0.12307692 | F37: =F20/1000 -> 0.092307692 | G37: =G20/1000 -> 0.061538461 | H37: =H20/1000 -> 0.03076923 | I37: =I20/1000 -> 0
B38: Gaz ziemny | C38: =C21/1000 -> 1.8478184 | D38: =D21/1000 -> 1.81521 | E38: =E21/1000 -> 1.652168 | F38: =F21/1000 -> 1.489126 | G38: =G21/1000 -> 1.326084 | H38: =H21/1000 -> 1.163042 | I38: =I21/1000 -> 1
B39: Biomasa | C39: =C22/1000 -> 16.396461 | D39: =D22/1000 -> 16.150444 | E39: =E22/1000 -> 14.920355 | F39: =F22/1000 -> 13.690266 | G39: =G22/1000 -> 12.460177 | H39: =H22/1000 -> 11.230089 | I39: =I22/1000 -> 10
B40: Biogaz | C40: =C23/1000 -> 0.55687786 | D40: =D23/1000 -> 0.82392102 | E40: =E23/1000 -> 2.1591368 | F40: =F23/1000 -> 3.4943526 | G40: =G23/1000 -> 4.8295684 | H40: =H23/1000 -> 6.1647842 | I40: =I23/1000 -> 7.5
B41: RDF | C41: =C24/1000 -> 0.04177884 | D41: =D24/1000 -> 0.13632581 | E41: =E24/1000 -> 0.60906065 | F41: =F24/1000 -> 1.0817955 | G41: =G24/1000 -> 1.5545303 | H41: =H24/1000 -> 2.0272652 | I41: =I24/1000 -> 2.5
B42: LPG | C42: =C25/1000 -> 1.84 | D42: =D25/1000 -> 1.7884615 | E42: =E25/1000 -> 1.5307692 | F42: =F25/1000 -> 1.2730769 | G42: =G25/1000 -> 1.0153846 | H42: =H25/1000 -> 0.75769231 | I42: =I25/1000 -> 0.5
B43: Benzyna | C43: =C26/1000 -> 0.10313769 | D43: =D26/1000 -> 0.10301701 | E43: =E26/1000 -> 0.10241361 | F43: =F26/1000 -> 0.10181021 | G43: =G26/1000 -> 0.10120681 | H43: =H26/1000 -> 0.1006034 | I43: =I26/1000 -> 0.1
B44: Olej napędowy | C44: =C27/1000 -> 85.469984 | D44: =D27/1000 -> 83.7596 | E44: =E27/1000 -> 75.20768 | F44: =F27/1000 -> 66.65576 | G44: =G27/1000 -> 58.10384 | H44: =H27/1000 -> 49.55192 | I44: =I27/1000 -> 41
B45: Oleje opałowe | C45: =C28/1000 -> 3.0946174 | D45: =D28/1000 -> 2.9755936 | E45: =E28/1000 -> 2.3804749 | F45: =F28/1000 -> 1.7853562 | G45: =G28/1000 -> 1.1902374 | H45: =H28/1000 -> 0.59511872 | I45: =I28/1000 -> 0
B46: Energia elektryczna | C46: =C29/1000 -> 6.3 | D46: =D29/1000 -> 7.0576923 | E46: =E29/1000 -> 10.846154 | F46: =F29/1000 -> 14.634615 | G46: =G29/1000 -> 18.423077 | H46: =H29/1000 -> 22.211538 | I46: =I29/1000 -> 26
B47: Ciepło sieciowe | C47: =C30/1000 -> 0.62 | D47: =D30/1000 -> 0.71153846 | E47: =E30/1000 -> 1.1692308 | F47: =F30/1000 -> 1.6269231 | G47: =G30/1000 -> 2.0846154 | H47: =H30/1000 -> 2.5423077 | I47: =I30/1000 -> 3
B48: Suma | C48: =C31/1000 -> 129.43068 | D48: =D31/1000 -> 127.97565 | E48: =E31/1000 -> 120.70052 | F48: =F31/1000 -> 113.42539 | G48: =G31/1000 -> 106.15026 | H48: =H31/1000 -> 98.87513 | I48: =I31/1000 -> 91.6
